Workbook
Name tab: [1]info!$B$9

Sheet Peso Fardos
I2: CONSUMO MATÉRIA PRIMA SAPIENS | L2: SAIDA DA EMPRESA | O2: FATURADO | R2: NECESSIDADE MATÉRIA PRIMA A PRODUZIR
A3: CÓDIGO | B3: DESCRIÇÃO | C3: QUANT. DO FARDO | D3: PESO PACOTE | E3: PESO PACOTE | F3: PESO DO FARDO | G3: PESO DO FARDO | I3: PRODUÇÃO FARDOS | J3: PRODUÇÃO EM KILOS | L3: SAIDA FARDOS | M3: SAIDA EM KILOS | O3: SAIDA FARDOS | P3: SAIDA EM KILOS | R3: ENTRADA FARDOS | S3: ENTRADA EM KILOS
A4: 011 | B4: FLOCADO NUTRIVITA 12 X 500 | C4: 12 | D4: 0.5 | E4: 0.505 | F4: =C4*D4 -> 6 | G4: =C4*E4 -> 6.06 | I4: =IF(ISBLANK($A$2),SUMIFS(Entradas!C:C,Entradas!A:A,'Cadastro-Estoque'!A:A),SUMIFS(Entradas!C:C,Entradas!A:A,'Cadastro-Estoque'!A:A,Entradas!B:B,CONCATENATE("<=",$A$2))) -> 0 | J4: =I4*G4 -> 0 | L4: =IF(ISBLANK($A$2),SUMIFS(Saidas!C:C,Saidas!A:A,'Cadastro-Estoque'!A:A),SUMIFS(Saidas!C:C,Saidas!A:A,'Cadastro-Estoque'!A:A,Saidas!B:B,CONCATENATE("<=",$A$2))) -> 0 | M4: =L4*F4 -> 0 | O4: =IF(ISBLANK($A$2),SUMIFS(Faturado!C:C,Faturado!A:A,'Cadastro-Estoque'!A:A),SUMIFS(Faturado!C:C,Faturado!A:A,'Cadastro-Estoque'!A:A,Faturado!B:B,CONCATENATE("<=",$A$2))) -> 0 | P4: =O4*F4 -> 0 | R4: =IF(ISBLANK($A$2),SUMIFS('PRODUTOS A PRODUZIR'!C:C,'PRODUTOS A PRODUZIR'!A:A,'Cadastro-Estoque'!A:A),SUMIFS('PRODUTOS A PRODUZIR'!C:C,'PRODUTOS A PRODUZIR'!A:A,'Cadastro-Estoque'!A:A,'PRODUTOS A PRODUZIR'!B:B,CONCATENATE("<=",$A$2))) -> 0 | S4: =R4*F4 -> 0
A5: 011 | B5: FLOCADO NUTRIVITA 30 X 500 | C5: 30 | D5: 0.5 | E5: 0.505 | F5: =C5*D5 -> 15 | G5: =C5*E5 -> 15.15 | I5: =IF(ISBLANK($A$2),SUMIFS(Entradas!C:C,Entradas!A:A,'Cadastro-Estoque'!A:A),SUMIFS(Entradas!C:C,Entradas!A:A,'Cadastro-Estoque'!A:A,Entradas!B:B,CONCATENATE("<=",$A$2))) -> 1486 | J5: =I5*G5 -> 22512.9 | L5: =IF(ISBLANK($A$2),SUMIFS(Saidas!C:C,Saidas!A:A,'Cadastro-Estoque'!A:A),SUMIFS(Saidas!C:C,Saidas!A:A,'Cadastro-Estoque'!A:A,Saidas!B:B,CONCATENATE("<=",$A$2))) -> 4875 | M5: =L5*F5 -> 73125 | O5: =IF(ISBLANK($A$2),SUMIFS(Faturado!C:C,Faturado!A:A,'Cadastro-Estoque'!A:A),SUMIFS(Faturado!C:C,Faturado!A:A,'Cadastro-Estoque'!A:A,Faturado!B:B,CONCATENATE("<=",$A$2))) -> 0 | P5: =O5*F5 -> 0 | R5: =IF(ISBLANK($A$2),SUMIFS('PRODUTOS A PRODUZIR'!C:C,'PRODUTOS A PRODUZIR'!A:A,'Cadastro-Estoque'!A:A),SUMIFS('PRODUTOS A PRODUZIR'!C:C,'PRODUTOS A PRODUZIR'!A:A,'Cadastro-Estoque'!A:A,'PRODUTOS A PRODUZIR'!B:B,CONCATENATE("<=",$A$2))) -> 0 | S5: =R5*F5 -> 0
A6: 012 | B6: FLOCADO VITABEM 30 X 500 | C6: 30 | D6: 0.5 | E6: 0.505 | F6: =C6*D6 -> 15 | G6: =C6*E6 -> 15.15 | I6: =IF(ISBLANK($A$2),SUMIFS(Entradas!C:C,Entradas!A:A,'Cadastro-Estoque'!A:A),SUMIFS(Entradas!C:C,Entradas!A:A,'Cadastro-Estoque'!A:A,Entradas!B:B,CONCATENATE("<=",$A$2))) -> 0 | J6: =I6*G6 -> 0 | L6: =IF(ISBLANK($A$2),SUMIFS(Saidas!C:C,Saidas!A:A,'Cadastro-Estoque'!A:A),SUMIFS(Saidas!C:C,Saidas!A:A,'Cadastro-Estoque'!A:A,Saidas!B:B,CONCATENATE("<=",$A$2))) -> 0 | M6: =L6*F6 -> 0 | O6: =IF(ISBLANK($A$2),SUMIFS(Faturado!C:C,Faturado!A:A,'Cadastro-Estoque'!A:A),SUMIFS(Faturado!C:C,Faturado!A:A,'Cadastro-Estoque'!A:A,Faturado!B:B,CONCATENATE("<=",$A$2))) -> 0 | P6: =O6*F6 -> 0 | R6: =IF(ISBLANK($A$2),SUMIFS('PRODUTOS A PRODUZIR'!C:C,'PRODUTOS A PRODUZIR'!A:A,'Cadastro-Estoque'!A:A),SUMIFS('PRODUTOS A PRODUZIR'!C:C,'PRODUTOS A PRODUZIR'!A:A,'Cadastro-Estoque'!A:A,'PRODUTOS A PRODUZIR'!B:B,CONCATENATE("<=",$A$2))) -> 0 | S6: =R6*F6 -> 0
A7: 016 | B7: FLOCADO VITABRAS 30 X 400 | C7: 30 | D7: 0.5 | E7: 0.505 | F7: 12 | G7: 12.15 | I7: =IF(ISBLANK($A$2),SUMIFS(Entradas!C:C,Entradas!A:A,'Cadastro-Estoque'!A:A),SUMIFS(Entradas!C:C,Entradas!A:A,'Cadastro-Estoque'!A:A,Entradas!B:B,CONCATENATE("<=",$A$2))) -> 0 | J7: =I7*G7 -> 0 | L7: =IF(ISBLANK($A$2),SUMIFS(Saidas!C:C,Saidas!A:A,'Cadastro-Estoque'!A:A),SUMIFS(Saidas!C:C,Saidas!A:A,'Cadastro-Estoque'!A:A,Saidas!B:B,CONCATENATE("<=",$A$2))) -> 0 | M7: =L7*F7 -> 0 | O7: =IF(ISBLANK($A$2),SUMIFS(Faturado!C:C,Faturado!A:A,'Cadastro-Estoque'!A:A),SUMIFS(Faturado!C:C,Faturado!A:A,'Cadastro-Estoque'!A:A,Faturado!B:B,CONCATENATE("<=",$A$2))) -> 0 | P7: =O7*F7 -> 0 | R7: =IF(ISBLANK($A$2),SUMIFS('PRODUTOS A PRODUZIR'!C:C,'PRODUTOS A PRODUZIR'!A:A,'Cadastro-Estoque'!A:A),SUMIFS('PRODUTOS A PRODUZIR'!C:C,'PRODUTOS A PRODUZIR'!A:A,'Cadastro-Estoque'!A:A,'PRODUTOS A PRODUZIR'!B:B,CONCATENATE("<=",$A$2))) -> 0 | S7: =R7*F7 -> 0
A8: 022 | B8: FLOCADO VITABRASIL 30 X 500 | C8: 30 | D8: 0.4 | E8: 0.405 | F8: 15 | G8: 15.15 | I8: =IF(ISBLANK($A$2),SUMIFS(Entradas!C:C,Entradas!A:A,'Cadastro-Estoque'!A:A),SUMIFS(Entradas!C:C,Entradas!A:A,'Cadastro-Estoque'!A:A,Entradas!B:B,CONCATENATE("<=",$A$2))) -> 0 | J8: =I8*G8 -> 0 | L8: =IF(ISBLANK($A$2),SUMIFS(Saidas!C:C,Saidas!A:A,'Cadastro-Estoque'!A:A),SUMIFS(Saidas!C:C,Saidas!A:A,'Cadastro-Estoque'!A:A,Saidas!B:B,CONCATENATE("<=",$A$2))) -> 0 | M8: =L8*F8 -> 0 | O8: =IF(ISBLANK($A$2),SUMIFS(Faturado!C:C,Faturado!A:A,'Cadastro-Estoque'!A:A),SUMIFS(Faturado!C:C,Faturado!A:A,'Cadastro-Estoque'!A:A,Faturado!B:B,CONCATENATE("<=",$A$2))) -> 0 | P8: =O8*F8 -> 0 | R8: =IF(ISBLANK($A$2),SUMIFS('PRODUTOS A PRODUZIR'!C:C,'PRODUTOS A PRODUZIR'!A:A,'Cadastro-Estoque'!A:A),SUMIFS('PRODUTOS A PRODUZIR'!C:C,'PRODUTOS A PRODUZIR'!A:A,'Cadastro-Estoque'!A:A,'PRODUTOS A PRODUZIR'!B:B,CONCATENATE("<=",$A$2))) -> 0 | S8: =R8*F8 -> 0
A9: 019 | B9: FLOCADO PURO MILHO 12 X 500 | C9: 12 | D9: 0.5 | E9: 0.505 | F9: =C9*D9 -> 6 | G9: =C9*E9 -> 6.06 | I9: =IF(ISBLANK($A$2),SUMIFS(Entradas!C:C,Entradas!A:A,'Cadastro-Estoque'!A:A),SUMIFS(Entradas!C:C,Entradas!A:A,'Cadastro-Estoque'!A:A,Entradas!B:B,CONCATENATE("<=",$A$2))) -> 0 | J9: =I9*G9 -> 0 | L9: =IF(ISBLANK($A$2),SUMIFS(Saidas!C:C,Saidas!A:A,'Cadastro-Estoque'!A:A),SUMIFS(Saidas!C:C,Saidas!A:A,'Cadastro-Estoque'!A:A,Saidas!B:B,CONCATENATE("<=",$A$2))) -> 0 | M9: =L9*F9 -> 0 | O9: =IF(ISBLANK($A$2),SUMIFS(Faturado!C:C,Faturado!A:A,'Cadastro-Estoque'!A:A),SUMIFS(Faturado!C:C,Faturado!A:A,'Cadastro-Estoque'!A:A,Faturado!B:B,CONCATENATE("<=",$A$2))) -> 0 | P9: =O9*F9 -> 0 | R9: =IF(ISBLANK($A$2),SUMIFS('PRODUTOS A PRODUZIR'!C:C,'PRODUTOS A PRODUZIR'!A:A,'Cadastro-Estoque'!A:A),SUMIFS('PRODUTOS A PRODUZIR'!C:C,'PRODUTOS A PRODUZIR'!A:A,'Cadastro-Estoque'!A:A,'PRODUTOS A PRODUZIR'!B:B,CONCATENATE("<=",$A$2))) -> 0 | S9: =R9*F9 -> 0
A10: 019 | B10: FLOCADO PURO MILHO 30 X 500 | C10: 30 | D10: 0.5 | E10: 0.505 | F10: =C10*D10 -> 15 | G10: =C10*E10 -> 15.15 | I10: =IF(ISBLANK($A$2),SUMIFS(Entradas!C:C,Entradas!A:A,'Cadastro-Estoque'!A:A),SUMIFS(Entradas!C:C,Entradas!A:A,'Cadastro-Estoque'!A:A,Entradas!B:B,CONCATENATE("<=",$A$2))) -> 0 | J10: =I10*G10 -> 0 | L10: =IF(ISBLANK($A$2),SUMIFS(Saidas!C:C,Saidas!A:A,'Cadastro-Estoque'!A:A),SUMIFS(Saidas!C:C,Saidas!A:A,'Cadastro-Estoque'!A:A,Saidas!B:B,CONCATENATE("<=",$A$2))) -> 0 | M10: =L10*F10 -> 0 | O10: =IF(ISBLANK($A$2),SUMIFS(Faturado!C:C,Faturado!A:A,'Cadastro-Estoque'!A:A),SUMIFS(Faturado!C:C,Faturado!A:A,'Cadastro-Estoque'!A:A,Faturado!B:B,CONCATENATE("<=",$A$2))) -> 0 | P10: =O10*F10 -> 0 | R10: =IF(ISBLANK($A$2),SUMIFS('PRODUTOS A PRODUZIR'!C:C,'PRODUTOS A PRODUZIR'!A:A,'Cadastro-Estoque'!A:A),SUMIFS('PRODUTOS A PRODUZIR'!C:C,'PRODUTOS A PRODUZIR'!A:A,'Cadastro-Estoque'!A:A,'PRODUTOS A PRODUZIR'!B:B,CONCATENATE("<=",$A$2))) -> 0 | S10: =R10*F10 -> 0
A11: 050 | B11: FLOCADO CORDEIRO 30 X 500 | C11: 30 | D11: 0.5 | E11: 0.505 | F11: =C11*D11 -> 15 | G11: =C11*E11 -> 15.15 | I11: =IF(ISBLANK($A$2),SUMIFS(Entradas!C:C,Entradas!A:A,'Cadastro-Estoque'!A:A),SUMIFS(Entradas!C:C,Entradas!A:A,'Cadastro-Estoque'!A:A,Entradas!B:B,CONCATENATE("<=",$A$2))) -> 0 | J11: =I11*G11 -> 0 | L11: =IF(ISBLANK($A$2),SUMIFS(Saidas!C:C,Saidas!A:A,'Cadastro-Estoque'!A:A),SUMIFS(Saidas!C:C,Saidas!A:A,'Cadastro-Estoque'!A:A,Saidas!B:B,CONCATENATE("<=",$A$2))) -> 0 | M11: =L11*F11 -> 0 | O11: =IF(ISBLANK($A$2),SUMIFS(Faturado!C:C,Faturado!A:A,'Cadastro-Estoque'!A:A),SUMIFS(Faturado!C:C,Faturado!A:A,'Cadastro-Estoque'!A:A,Faturado!B:B,CONCATENATE("<=",$A$2))) -> 0 | P11: =O11*F11 -> 0 | R11: =IF(ISBLANK($A$2),SUMIFS('PRODUTOS A PRODUZIR'!C:C,'PRODUTOS A PRODUZIR'!A:A,'Cadastro-Estoque'!A:A),SUMIFS('PRODUTOS A PRODUZIR'!C:C,'PRODUTOS A PRODUZIR'!A:A,'Cadastro-Estoque'!A:A,'PRODUTOS A PRODUZIR'!B:B,CONCATENATE("<=",$A$2))) -> 0 | S11: =R11*F11 -> 0
A12: 094 | B12: FLOCADO M & K 12 X 500 | C12: 12 | D12: 0.5 | E12: 0.505 | F12: =C12*D12 -> 6 | G12: =C12*E12 -> 6.06 | I12: =IF(ISBLANK($A$2),SUMIFS(Entradas!C:C,Entradas!A:A,'Cadastro-Estoque'!A:A),SUMIFS(Entradas!C:C,Entradas!A:A,'Cadastro-Estoque'!A:A,Entradas!B:B,CONCATENATE("<=",$A$2))) -> 0 | J12: =I12*G12 -> 0 | L12: =IF(ISBLANK($A$2),SUMIFS(Saidas!C:C,Saidas!A:A,'Cadastro-Estoque'!A:A),SUMIFS(Saidas!C:C,Saidas!A:A,'Cadastro-Estoque'!A:A,Saidas!B:B,CONCATENATE("<=",$A$2))) -> 0 | M12: =L12*F12 -> 0 | O12: =IF(ISBLANK($A$2),SUMIFS(Faturado!C:C,Faturado!A:A,'Cadastro-Estoque'!A:A),SUMIFS(Faturado!C:C,Faturado!A:A,'Cadastro-Estoque'!A:A,Faturado!B:B,CONCATENATE("<=",$A$2))) -> 0 | P12: =O12*F12 -> 0 | R12: =IF(ISBLANK($A$2),SUMIFS('PRODUTOS A PRODUZIR'!C:C,'PRODUTOS A PRODUZIR'!A:A,'Cadastro-Estoque'!A:A),SUMIFS('PRODUTOS A PRODUZIR'!C:C,'PRODUTOS A PRODUZIR'!A:A,'Cadastro-Estoque'!A:A,'PRODUTOS A PRODUZIR'!B:B,CONCATENATE("<=",$A$2))) -> 0 | S12: =R12*F12 -> 0
F13: =C13*D13 -> 0 | G13: =C13*E13 -> 0 | I13: =IF(ISBLANK($A$2),SUMIFS(Entradas!C:C,Entradas!A:A,'Cadastro-Estoque'!A:A),SUMIFS(Entradas!C:C,Entradas!A:A,'Cadastro-Estoque'!A:A,Entradas!B:B,CONCATENATE("<=",$A$2))) -> 0 | J13: =I13*G13 -> 0 | L13: =IF(ISBLANK($A$2),SUMIFS(Saidas!C:C,Saidas!A:A,'Cadastro-Estoque'!A:A),SUMIFS(Saidas!C:C,Saidas!A:A,'Cadastro-Estoque'!A:A,Saidas!B:B,CONCATENATE("<=",$A$2))) -> 0 | M13: =L13*F13 -> 0 | O13: =IF(ISBLANK($A$2),SUMIFS(Faturado!C:C,Faturado!A:A,'Cadastro-Estoque'!A:A),SUMIFS(Faturado!C:C,Faturado!A:A,'Cadastro-Estoque'!A:A,Faturado!B:B,CONCATENATE("<=",$A$2))) -> 0 | P13: =O13*F13 -> 0 | R13: =IF(ISBLANK($A$2),SUMIFS('PRODUTOS A PRODUZIR'!C:C,'PRODUTOS A PRODUZIR'!A:A,'Cadastro-Estoque'!A:A),SUMIFS('PRODUTOS A PRODUZIR'!C:C,'PRODUTOS A PRODUZIR'!A:A,'Cadastro-Estoque'!A:A,'PRODUTOS A PRODUZIR'!B:B,CONCATENATE("<=",$A$2))) -> 0 | S13: =R13*F13 -> 0
A14: 036 | B14: POLENTA KISABOR 30 X 500 | C14: 30 | D14: 0.5 | E14: 0.505 | F14: =C14*D14 -> 15 | G14: =C14*E14 -> 15.15 | I14: =IF(ISBLANK($A$2),SUMIFS(Entradas!C:C,Entradas!A:A,'Cadastro-Estoque'!A:A),SUMIFS(Entradas!C:C,Entradas!A:A,'Cadastro-Estoque'!A:A,Entradas!B:B,CONCATENATE("<=",$A$2))) -> 0 | J14: =I14*G14 -> 0 | L14: =IF(ISBLANK($A$2),SUMIFS(Saidas!C:C,Saidas!A:A,'Cadastro-Estoque'!A:A),SUMIFS(Saidas!C:C,Saidas!A:A,'Cadastro-Estoque'!A:A,Saidas!B:B,CONCATENATE("<=",$A$2))) -> 0 | M14: =L14*F14 -> 0 | O14: =IF(ISBLANK($A$2),SUMIFS(Faturado!C:C,Faturado!A:A,'Cadastro-Estoque'!A:A),SUMIFS(Faturado!C:C,Faturado!A:A,'Cadastro-Estoque'!A:A,Faturado!B:B,CONCATENATE("<=",$A$2))) -> 0 | P14: =O14*F14 -> 0 | R14: =IF(ISBLANK($A$2),SUMIFS('PRODUTOS A PRODUZIR'!C:C,'PRODUTOS A PRODUZIR'!A:A,'Cadastro-Estoque'!A:A),SUMIFS('PRODUTOS A PRODUZIR'!C:C,'PRODUTOS A PRODUZIR'!A:A,'Cadastro-Estoque'!A:A,'PRODUTOS A PRODUZIR'!B:B,CONCATENATE("<=",$A$2))) -> 0 | S14: =R14*F14 -> 0
A15: 036 | B15: POLENTA KISABOR 12 X 500 | C15: 12 | D15: 0.5 | E15: 0.505 | F15: =C15*D15 -> 6 | G15: =C15*E15 -> 6.06 | I15: =IF(ISBLANK($A$2),SUMIFS(Entradas!C:C,Entradas!A:A,'Cadastro-Estoque'!A:A),SUMIFS(Entradas!C:C,Entradas!A:A,'Cadastro-Estoque'!A:A,Entradas!B:B,CONCATENATE("<=",$A$2))) -> 0 | J15: =I15*G15 -> 0 | L15: =IF(ISBLANK($A$2),SUMIFS(Saidas!C:C,Saidas!A:A,'Cadastro-Estoque'!A:A),SUMIFS(Saidas!C:C,Saidas!A:A,'Cadastro-Estoque'!A:A,Saidas!B:B,CONCATENATE("<=",$A$2))) -> 0 | M15: =L15*F15 -> 0 | O15: =IF(ISBLANK($A$2),SUMIFS(Faturado!C:C,Faturado!A:A,'Cadastro-Estoque'!A:A),SUMIFS(Faturado!C:C,Faturado!A:A,'Cadastro-Estoque'!A:A,Faturado!B:B,CONCATENATE("<=",$A$2))) -> 0 | P15: =O15*F15 -> 0 | R15: =IF(ISBLANK($A$2),SUMIFS('PRODUTOS A PRODUZIR'!C:C,'PRODUTOS A PRODUZIR'!A:A,'Cadastro-Estoque'!A:A),SUMIFS('PRODUTOS A PRODUZIR'!C:C,'PRODUTOS A PRODUZIR'!A:A,'Cadastro-Estoque'!A:A,'PRODUTOS A PRODUZIR'!B:B,CONCATENATE("<=",$A$2))) -> 0 | S15: =R15*F15 -> 0
A16: 037 | B16: POLENTA NUTRIVITA 30 X 500 | C16: 30 | D16: 0.5 | E16: 0.505 | F16: =C16*D16 -> 15 | G16: =C16*E16 -> 15.15 | I16: =IF(ISBLANK($A$2),SUMIFS(Entradas!C:C,Entradas!A:A,'Cadastro-Estoque'!A:A),SUMIFS(Entradas!C:C,Entradas!A:A,'Cadastro-Estoque'!A:A,Entradas!B:B,CONCATENATE("<=",$A$2))) -> 0 | J16: =I16*G16 -> 0 | L16: =IF(ISBLANK($A$2),SUMIFS(Saidas!C:C,Saidas!A:A,'Cadastro-Estoque'!A:A),SUMIFS(Saidas!C:C,Saidas!A:A,'Cadastro-Estoque'!A:A,Saidas!B:B,CONCATENATE("<=",$A$2))) -> 0 | M16: =L16*F16 -> 0 | O16: =IF(ISBLANK($A$2),SUMIFS(Faturado!C:C,Faturado!A:A,'Cadastro-Estoque'!A:A),SUMIFS(Faturado!C:C,Faturado!A:A,'Cadastro-Estoque'!A:A,Faturado!B:B,CONCATENATE("<=",$A$2))) -> 0 | P16: =O16*F16 -> 0 | R16: =IF(ISBLANK($A$2),SUMIFS('PRODUTOS A PRODUZIR'!C:C,'PRODUTOS A PRODUZIR'!A:A,'Cadastro-Estoque'!A:A),SUMIFS('PRODUTOS A PRODUZIR'!C:C,'PRODUTOS A PRODUZIR'!A:A,'Cadastro-Estoque'!A:A,'PRODUTOS A PRODUZIR'!B:B,CONCATENATE("<=",$A$2))) -> 0 | S16: =R16*F16 -> 0
A17: 037 | B17: POLENTA NUTRIVITA 30 X 400 | C17: 30 | D17: 0.4 | E17: 0.405 | F17: =C17*D17 -> 12 | G17: =C17*E17 -> 12.15 | I17: =IF(ISBLANK($A$2),SUMIFS(Entradas!C:C,Entradas!A:A,'Cadastro-Estoque'!A:A),SUMIFS(Entradas!C:C,Entradas!A:A,'Cadastro-Estoque'!A:A,Entradas!B:B,CONCATENATE("<=",$A$2))) -> 0 | J17: =I17*G17 -> 0 | L17: =IF(ISBLANK($A$2),SUMIFS(Saidas!C:C,Saidas!A:A,'Cadastro-Estoque'!A:A),SUMIFS(Saidas!C:C,Saidas!A:A,'Cadastro-Estoque'!A:A,Saidas!B:B,CONCATENATE("<=",$A$2))) -> 0 | M17: =L17*F17 -> 0 | O17: =IF(ISBLANK($A$2),SUMIFS(Faturado!C:C,Faturado!A:A,'Cadastro-Estoque'!A:A),SUMIFS(Faturado!C:C,Faturado!A:A,'Cadastro-Estoque'!A:A,Faturado!B:B,CONCATENATE("<=",$A$2))) -> 0 | P17: =O17*F17 -> 0 | R17: =IF(ISBLANK($A$2),SUMIFS('PRODUTOS A PRODUZIR'!C:C,'PRODUTOS A PRODUZIR'!A:A,'Cadastro-Estoque'!A:A),SUMIFS('PRODUTOS A PRODUZIR'!C:C,'PRODUTOS A PRODUZIR'!A:A,'Cadastro-Estoque'!A:A,'PRODUTOS A PRODUZIR'!B:B,CONCATENATE("<=",$A$2))) -> 0 | S17: =R17*F17 -> 0
A18: 039 | B18: POLENTA CBS 12 X 500 | C18: 12 | D18: 0.5 | E18: 0.505 | F18: =C18*D18 -> 6 | G18: =C18*E18 -> 6.06 | I18: =IF(ISBLANK($A$2),SUMIFS(Entradas!C:C,Entradas!A:A,'Cadastro-Estoque'!A:A),SUMIFS(Entradas!C:C,Entradas!A:A,'Cadastro-Estoque'!A:A,Entradas!B:B,CONCATENATE("<=",$A$2))) -> 0 | J18: =I18*G18 -> 0 | L18: =IF(ISBLANK($A$2),SUMIFS(Saidas!C:C,Saidas!A:A,'Cadastro-Estoque'!A:A),SUMIFS(Saidas!C:C,Saidas!A:A,'Cadastro-Estoque'!A:A,Saidas!B:B,CONCATENATE("<=",$A$2))) -> 0 | M18: =L18*F18 -> 0 | O18: =IF(ISBLANK($A$2),SUMIFS(Faturado!C:C,Faturado!A:A,'Cadastro-Estoque'!A:A),SUMIFS(Faturado!C:C,Faturado!A:A,'Cadastro-Estoque'!A:A,Faturado!B:B,CONCATENATE("<=",$A$2))) -> 0 | P18: =O18*F18 -> 0 | R18: =IF(ISBLANK($A$2),SUMIFS('PRODUTOS A PRODUZIR'!C:C,'PRODUTOS A PRODUZIR'!A:A,'Cadastro-Estoque'!A:A),SUMIFS('PRODUTOS A PRODUZIR'!C:C,'PRODUTOS A PRODUZIR'!A:A,'Cadastro-Estoque'!A:A,'PRODUTOS A PRODUZIR'!B:B,CONCATENATE("<=",$A$2))) -> 0 | S18: =R18*F18 -> 0
A19: 052 | B19: POLENTA FRITZ E FRIDA 12 X 500 | C19: 12 | D19: 0.5 | E19: 0.505 | F19: =C19*D19 -> 6 | G19: =C19*E19 -> 6.06 | I19: =IF(ISBLANK($A$2),SUMIFS(Entradas!C:C,Entradas!A:A,'Cadastro-Estoque'!A:A),SUMIFS(Entradas!C:C,Entradas!A:A,'Cadastro-Estoque'!A:A,Entradas!B:B,CONCATENATE("<=",$A$2))) -> 0 | J19: =I19*G19 -> 0 | L19: =IF(ISBLANK($A$2),SUMIFS(Saidas!C:C,Saidas!A:A,'Cadastro-Estoque'!A:A),SUMIFS(Saidas!C:C,Saidas!A:A,'Cadastro-Estoque'!A:A,Saidas!B:B,CONCATENATE("<=",$A$2))) -> 0 | M19: =L19*F19 -> 0 | O19: =IF(ISBLANK($A$2),SUMIFS(Faturado!C:C,Faturado!A:A,'Cadastro-Estoque'!A:A),SUMIFS(Faturado!C:C,Faturado!A:A,'Cadastro-Estoque'!A:A,Faturado!B:B,CONCATENATE("<=",$A$2))) -> 0 | P19: =O19*F19 -> 0 | R19: =IF(ISBLANK($A$2),SUMIFS('PRODUTOS A PRODUZIR'!C:C,'PRODUTOS A PRODUZIR'!A:A,'Cadastro-Estoque'!A:A),SUMIFS('PRODUTOS A PRODUZIR'!C:C,'PRODUTOS A PRODUZIR'!A:A,'Cadastro-Estoque'!A:A,'PRODUTOS A PRODUZIR'!B:B,CONCATENATE("<=",$A$2))) -> 5610 | S19: =R19*F19 -> 33660
A20: 064 | B20: POLENTA PERDIZ 12 X 1K | C20: 12 | D20: 1 | E20: 1.005 | F20: =C20*D20 -> 12 | G20: =C20*E20 -> 12.06 | I20: =IF(ISBLANK($A$2),SUMIFS(Entradas!C:C,Entradas!A:A,'Cadastro-Estoque'!A:A),SUMIFS(Entradas!C:C,Entradas!A:A,'Cadastro-Estoque'!A:A,Entradas!B:B,CONCATENATE("<=",$A$2))) -> 0 | J20: =I20*G20 -> 0 | L20: =IF(ISBLANK($A$2),SUMIFS(Saidas!C:C,Saidas!A:A,'Cadastro-Estoque'!A:A),SUMIFS(Saidas!C:C,Saidas!A:A,'Cadastro-Estoque'!A:A,Saidas!B:B,CONCATENATE("<=",$A$2))) -> 0 | M20: =L20*F20 -> 0 | O20: =IF(ISBLANK($A$2),SUMIFS(Faturado!C:C,Faturado!A:A,'Cadastro-Estoque'!A:A),SUMIFS(Faturado!C:C,Faturado!A:A,'Cadastro-Estoque'!A:A,Faturado!B:B,CONCATENATE("<=",$A$2))) -> 0 | P20: =O20*F20 -> 0 | R20: =IF(ISBLANK($A$2),SUMIFS('PRODUTOS A PRODUZIR'!C:C,'PRODUTOS A PRODUZIR'!A:A,'Cadastro-Estoque'!A:A),SUMIFS('PRODUTOS A PRODUZIR'!C:C,'PRODUTOS A PRODUZIR'!A:A,'Cadastro-Estoque'!A:A,'PRODUTOS A PRODUZIR'!B:B,CONCATENATE("<=",$A$2))) -> 0 | S20: =R20*F20 -> 0
A21: 064 | B21: POLENTA PERDIZ 12 X 500 G | C21: 12 | D21: 0.5 | E21: 0.505 | F21: =C21*D21 -> 6 | G21: =C21*E21 -> 6.06 | I21: =IF(ISBLANK($A$2),SUMIFS(Entradas!C:C,Entradas!A:A,'Cadastro-Estoque'!A:A),SUMIFS(Entradas!C:C,Entradas!A:A,'Cadastro-Estoque'!A:A,Entradas!B:B,CONCATENATE("<=",$A$2))) -> 0 | J21: =I21*G21 -> 0 | L21: =IF(ISBLANK($A$2),SUMIFS(Saidas!C:C,Saidas!A:A,'Cadastro-Estoque'!A:A),SUMIFS(Saidas!C:C,Saidas!A:A,'Cadastro-Estoque'!A:A,Saidas!B:B,CONCATENATE("<=",$A$2))) -> 0 | M21: =L21*F21 -> 0 | O21: =IF(ISBLANK($A$2),SUMIFS(Faturado!C:C,Faturado!A:A,'Cadastro-Estoque'!A:A),SUMIFS(Faturado!C:C,Faturado!A:A,'Cadastro-Estoque'!A:A,Faturado!B:B,CONCATENATE("<=",$A$2))) -> 0 | P21: =O21*F21 -> 0 | R21: =IF(ISBLANK($A$2),SUMIFS('PRODUTOS A PRODUZIR'!C:C,'PRODUTOS A PRODUZIR'!A:A,'Cadastro-Estoque'!A:A),SUMIFS('PRODUTOS A PRODUZIR'!C:C,'PRODUTOS A PRODUZIR'!A:A,'Cadastro-Estoque'!A:A,'PRODUTOS A PRODUZIR'!B:B,CONCATENATE("<=",$A$2))) -> 0 | S21: =R21*F21 -> 0
A22: 078 | B22: POLENTA BEATRIZ 12 X 500 G | C22: 12 | D22: 0.5 | E22: 0.505 | F22: =C22*D22 -> 6 | G22: =C22*E22 -> 6.06 | I22: =IF(ISBLANK($A$2),SUMIFS(Entradas!C:C,Entradas!A:A,'Cadastro-Estoque'!A:A),SUMIFS(Entradas!C:C,Entradas!A:A,'Cadastro-Estoque'!A:A,Entradas!B:B,CONCATENATE("<=",$A$2))) -> 0 | J22: =I22*G22 -> 0 | L22: =IF(ISBLANK($A$2),SUMIFS(Saidas!C:C,Saidas!A:A,'Cadastro-Estoque'!A:A),SUMIFS(Saidas!C:C,Saidas!A:A,'Cadastro-Estoque'!A:A,Saidas!B:B,CONCATENATE("<=",$A$2))) -> 0 | M22: =L22*F22 -> 0 | O22: =IF(ISBLANK($A$2),SUMIFS(Faturado!C:C,Faturado!A:A,'Cadastro-Estoque'!A:A),SUMIFS(Faturado!C:C,Faturado!A:A,'Cadastro-Estoque'!A:A,Faturado!B:B,CONCATENATE("<=",$A$2))) -> 0 | P22: =O22*F22 -> 0 | R22: =IF(ISBLANK($A$2),SUMIFS('PRODUTOS A PRODUZIR'!C:C,'PRODUTOS A PRODUZIR'!A:A,'Cadastro-Estoque'!A:A),SUMIFS('PRODUTOS A PRODUZIR'!C:C,'PRODUTOS A PRODUZIR'!A:A,'Cadastro-Estoque'!A:A,'PRODUTOS A PRODUZIR'!B:B,CONCATENATE("<=",$A$2))) -> 0 | S22: =R22*F22 -> 0
A23: 079 | B23: POLENTA KISABOR PRÉ COZIDO 24 X 500 | C23: 24 | D23: 0.5 | E23: 0.505 | F23: 12 | G23: =C23*E23 -> 12.12 | I23: =IF(ISBLANK($A$2),SUMIFS(Entradas!C:C,Entradas!A:A,'Cadastro-Estoque'!A:A),SUMIFS(Entradas!C:C,Entradas!A:A,'Cadastro-Estoque'!A:A,Entradas!B:B,CONCATENATE("<=",$A$2))) -> 0 | J23: =I23*G23 -> 0 | L23: =IF(ISBLANK($A$2),SUMIFS(Saidas!C:C,Saidas!A:A,'Cadastro-Estoque'!A:A),SUMIFS(Saidas!C:C,Saidas!A:A,'Cadastro-Estoque'!A:A,Saidas!B:B,CONCATENATE("<=",$A$2))) -> 0 | M23: =L23*F23 -> 0 | O23: =IF(ISBLANK($A$2),SUMIFS(Faturado!C:C,Faturado!A:A,'Cadastro-Estoque'!A:A),SUMIFS(Faturado!C:C,Faturado!A:A,'Cadastro-Estoque'!A:A,Faturado!B:B,CONCATENATE("<=",$A$2))) -> 0 | P23: =O23*F23 -> 0 | R23: =IF(ISBLANK($A$2),SUMIFS('PRODUTOS A PRODUZIR'!C:C,'PRODUTOS A PRODUZIR'!A:A,'Cadastro-Estoque'!A:A),SUMIFS('PRODUTOS A PRODUZIR'!C:C,'PRODUTOS A PRODUZIR'!A:A,'Cadastro-Estoque'!A:A,'PRODUTOS A PRODUZIR'!B:B,CONCATENATE("<=",$A$2))) -> 0 | S23: =R23*F23 -> 0
A24: 084 | B24: FUBÁ PRÉ COZIDO AREPA LAMPIONE 12 X 1 | C24: 12 | D24: 1 | E24: 1.005 | F24: =C24*D24 -> 12 | G24: =C24*E24 -> 12.06 | I24: =IF(ISBLANK($A$2),SUMIFS(Entradas!C:C,Entradas!A:A,'Cadastro-Estoque'!A:A),SUMIFS(Entradas!C:C,Entradas!A:A,'Cadastro-Estoque'!A:A,Entradas!B:B,CONCATENATE("<=",$A$2))) -> 0 | J24: =I24*G24 -> 0 | L24: =IF(ISBLANK($A$2),SUMIFS(Saidas!C:C,Saidas!A:A,'Cadastro-Estoque'!A:A),SUMIFS(Saidas!C:C,Saidas!A:A,'Cadastro-Estoque'!A:A,Saidas!B:B,CONCATENATE("<=",$A$2))) -> 0 | M24: =L24*F24 -> 0 | O24: =IF(ISBLANK($A$2),SUMIFS(Faturado!C:C,Faturado!A:A,'Cadastro-Estoque'!A:A),SUMIFS(Faturado!C:C,Faturado!A:A,'Cadastro-Estoque'!A:A,Faturado!B:B,CONCATENATE("<=",$A$2))) -> 0 | P24: =O24*F24 -> 0 | R24: =IF(ISBLANK($A$2),SUMIFS('PRODUTOS A PRODUZIR'!C:C,'PRODUTOS A PRODUZIR'!A:A,'Cadastro-Estoque'!A:A),SUMIFS('PRODUTOS A PRODUZIR'!C:C,'PRODUTOS A PRODUZIR'!A:A,'Cadastro-Estoque'!A:A,'PRODUTOS A PRODUZIR'!B:B,CONCATENATE("<=",$A$2))) -> 0 | S24: =R24*F24 -> 0
A25: 092 | B25: FUBÁ PRÉ COZIDO AREPA NUTRIVITA 12 X 1 | C25: 12 | D25: 1 | E25: 1.005 | F25: =C25*D25 -> 12 | G25: =C25*E25 -> 12.06 | I25: =IF(ISBLANK($A$2),SUMIFS(Entradas!C:C,Entradas!A:A,'Cadastro-Estoque'!A:A),SUMIFS(Entradas!C:C,Entradas!A:A,'Cadastro-Estoque'!A:A,Entradas!B:B,CONCATENATE("<=",$A$2))) -> 0 | J25: =I25*G25 -> 0 | L25: =IF(ISBLANK($A$2),SUMIFS(Saidas!C:C,Saidas!A:A,'Cadastro-Estoque'!A:A),SUMIFS(Saidas!C:C,Saidas!A:A,'Cadastro-Estoque'!A:A,Saidas!B:B,CONCATENATE("<=",$A$2))) -> 0 | M25: =L25*F25 -> 0 | O25: =IF(ISBLANK($A$2),SUMIFS(Faturado!C:C,Faturado!A:A,'Cadastro-Estoque'!A:A),SUMIFS(Faturado!C:C,Faturado!A:A,'Cadastro-Estoque'!A:A,Faturado!B:B,CONCATENATE("<=",$A$2))) -> 0 | P25: =O25*F25 -> 0 | R25: =IF(ISBLANK($A$2),SUMIFS('PRODUTOS A PRODUZIR'!C:C,'PRODUTOS A PRODUZIR'!A:A,'Cadastro-Estoque'!A:A),SUMIFS('PRODUTOS A PRODUZIR'!C:C,'PRODUTOS A PRODUZIR'!A:A,'Cadastro-Estoque'!A:A,'PRODUTOS A PRODUZIR'!B:B,CONCATENATE("<=",$A$2))) -> 0 | S25: =R25*F25 -> 0
A26: 092 | B26: FUBÁ PRÉ COZIDO AREPA NUTRIVITA 30 X 500 | C26: 30 | D26: 0.5 | E26: 0.505 | F26: =C26*D26 -> 15 | G26: =C26*E26 -> 15.15 | I26: =IF(ISBLANK($A$2),SUMIFS(Entradas!C:C,Entradas!A:A,'Cadastro-Estoque'!A:A),SUMIFS(Entradas!C:C,Entradas!A:A,'Cadastro-Estoque'!A:A,Entradas!B:B,CONCATENATE("<=",$A$2))) -> 0 | J26: =I26*G26 -> 0 | L26: =IF(ISBLANK($A$2),SUMIFS(Saidas!C:C,Saidas!A:A,'Cadastro-Estoque'!A:A),SUMIFS(Saidas!C:C,Saidas!A:A,'Cadastro-Estoque'!A:A,Saidas!B:B,CONCATENATE("<=",$A$2))) -> 0 | M26: =L26*F26 -> 0 | O26: =IF(ISBLANK($A$2),SUMIFS(Faturado!C:C,Faturado!A:A,'Cadastro-Estoque'!A:A),SUMIFS(Faturado!C:C,Faturado!A:A,'Cadastro-Estoque'!A:A,Faturado!B:B,CONCATENATE("<=",$A$2))) -> 0 | P26: =O26*F26 -> 0 | R26: =IF(ISBLANK($A$2),SUMIFS('PRODUTOS A PRODUZIR'!C:C,'PRODUTOS A PRODUZIR'!A:A,'Cadastro-Estoque'!A:A),SUMIFS('PRODUTOS A PRODUZIR'!C:C,'PRODUTOS A PRODUZIR'!A:A,'Cadastro-Estoque'!A:A,'PRODUTOS A PRODUZIR'!B:B,CONCATENATE("<=",$A$2))) -> 0 | S26: =R26*F26 -> 0
A27: 095 | B27: FUBÁ PRÉ COZIDO BOA NOVA 30 X 500 | C27: 30 | D27: 0.5 | E27: 0.505 | F27: =C27*D27 -> 15 | G27: =C27*E27 -> 15.15 | I27: =IF(ISBLANK($A$2),SUMIFS(Entradas!C:C,Entradas!A:A,'Cadastro-Estoque'!A:A),SUMIFS(Entradas!C:C,Entradas!A:A,'Cadastro-Estoque'!A:A,Entradas!B:B,CONCATENATE("<=",$A$2))) -> 0 | J27: =I27*G27 -> 0 | L27: =IF(ISBLANK($A$2),SUMIFS(Saidas!C:C,Saidas!A:A,'Cadastro-Estoque'!A:A),SUMIFS(Saidas!C:C,Saidas!A:A,'Cadastro-Estoque'!A:A,Saidas!B:B,CONCATENATE("<=",$A$2))) -> 0 | M27: =L27*F27 -> 0 | O27: =IF(ISBLANK($A$2),SUMIFS(Faturado!C:C,Faturado!A:A,'Cadastro-Estoque'!A:A),SUMIFS(Faturado!C:C,Faturado!A:A,'Cadastro-Estoque'!A:A,Faturado!B:B,CONCATENATE("<=",$A$2))) -> 0 | P27: =O27*F27 -> 0 | R27: =IF(ISBLANK($A$2),SUMIFS('PRODUTOS A PRODUZIR'!C:C,'PRODUTOS A PRODUZIR'!A:A,'Cadastro-Estoque'!A:A),SUMIFS('PRODUTOS A PRODUZIR'!C:C,'PRODUTOS A PRODUZIR'!A:A,'Cadastro-Estoque'!A:A,'PRODUTOS A PRODUZIR'!B:B,CONCATENATE("<=",$A$2))) -> 0 | S27: =R27*F27 -> 0
A28: 098 | B28: FUBÁ PRÉ COZIDO AREPA REINAREPA 12 X 1 | C28: 12 | D28: 1 | E28: 1.005 | F28: =C28*D28 -> 12 | G28: =C28*E28 -> 12.06 | I28: =IF(ISBLANK($A$2),SUMIFS(Entradas!C:C,Entradas!A:A,'Cadastro-Estoque'!A:A),SUMIFS(Entradas!C:C,Entradas!A:A,'Cadastro-Estoque'!A:A,Entradas!B:B,CONCATENATE("<=",$A$2))) -> 0 | J28: =I28*G28 -> 0 | L28: =IF(ISBLANK($A$2),SUMIFS(Saidas!C:C,Saidas!A:A,'Cadastro-Estoque'!A:A),SUMIFS(Saidas!C:C,Saidas!A:A,'Cadastro-Estoque'!A:A,Saidas!B:B,CONCATENATE("<=",$A$2))) -> 0 | M28: =L28*F28 -> 0 | O28: =IF(ISBLANK($A$2),SUMIFS(Faturado!C:C,Faturado!A:A,'Cadastro-Estoque'!A:A),SUMIFS(Faturado!C:C,Faturado!A:A,'Cadastro-Estoque'!A:A,Faturado!B:B,CONCATENATE("<=",$A$2))) -> 0 | P28: =O28*F28 -> 0 | R28: =IF(ISBLANK($A$2),SUMIFS('PRODUTOS A PRODUZIR'!C:C,'PRODUTOS A PRODUZIR'!A:A,'Cadastro-Estoque'!A:A),SUMIFS('PRODUTOS A PRODUZIR'!C:C,'PRODUTOS A PRODUZIR'!A:A,'Cadastro-Estoque'!A:A,'PRODUTOS A PRODUZIR'!B:B,CONCATENATE("<=",$A$2))) -> 0 | S28: =R28*F28 -> 0
A29: 098 | B29: FUBÁ PRÉ COZIDO AREPA REINAREPA 30 x 500 | C29: 30 | D29: 0.5 | E29: 0.505 | F29: =C29*D29 -> 15 | G29: =C29*E29 -> 15.15 | I29: =IF(ISBLANK($A$2),SUMIFS(Entradas!C:C,Entradas!A:A,'Cadastro-Estoque'!A:A),SUMIFS(Entradas!C:C,Entradas!A:A,'Cadastro-Estoque'!A:A,Entradas!B:B,CONCATENATE("<=",$A$2))) -> 0 | J29: =I29*G29 -> 0 | L29: =IF(ISBLANK($A$2),SUMIFS(Saidas!C:C,Saidas!A:A,'Cadastro-Estoque'!A:A),SUMIFS(Saidas!C:C,Saidas!A:A,'Cadastro-Estoque'!A:A,Saidas!B:B,CONCATENATE("<=",$A$2))) -> 0 | M29: =L29*F29 -> 0 | O29: =IF(ISBLANK($A$2),SUMIFS(Faturado!C:C,Faturado!A:A,'Cadastro-Estoque'!A:A),SUMIFS(Faturado!C:C,Faturado!A:A,'Cadastro-Estoque'!A:A,Faturado!B:B,CONCATENATE("<=",$A$2))) -> 0 | P29: =O29*F29 -> 0 | R29: =IF(ISBLANK($A$2),SUMIFS('PRODUTOS A PRODUZIR'!C:C,'PRODUTOS A PRODUZIR'!A:A,'Cadastro-Estoque'!A:A),SUMIFS('PRODUTOS A PRODUZIR'!C:C,'PRODUTOS A PRODUZIR'!A:A,'Cadastro-Estoque'!A:A,'PRODUTOS A PRODUZIR'!B:B,CONCATENATE("<=",$A$2))) -> 0 | S29: =R29*F29 -> 0
A30: 100 | B30: POLENTA TUPÃ PRE COZIDO 30 X 500 | C30: 30 | D30: 0.5 | E30: 0.505 | F30: =C30*D30 -> 15 | G30: =C30*E30 -> 15.15 | I30: =IF(ISBLANK($A$2),SUMIFS(Entradas!C:C,Entradas!A:A,'Cadastro-Estoque'!A:A),SUMIFS(Entradas!C:C,Entradas!A:A,'Cadastro-Estoque'!A:A,Entradas!B:B,CONCATENATE("<=",$A$2))) -> 0 | J30: =I30*G30 -> 0 | L30: =IF(ISBLANK($A$2),SUMIFS(Saidas!C:C,Saidas!A:A,'Cadastro-Estoque'!A:A),SUMIFS(Saidas!C:C,Saidas!A:A,'Cadastro-Estoque'!A:A,Saidas!B:B,CONCATENATE("<=",$A$2))) -> 0 | M30: =L30*F30 -> 0 | O30: =IF(ISBLANK($A$2),SUMIFS(Faturado!C:C,Faturado!A:A,'Cadastro-Estoque'!A:A),SUMIFS(Faturado!C:C,Faturado!A:A,'Cadastro-Estoque'!A:A,Faturado!B:B,CONCATENATE("<=",$A$2))) -> 0 | P30: =O30*F30 -> 0 | R30: =IF(ISBLANK($A$2),SUMIFS('PRODUTOS A PRODUZIR'!C:C,'PRODUTOS A PRODUZIR'!A:A,'Cadastro-Estoque'!A:A),SUMIFS('PRODUTOS A PRODUZIR'!C:C,'PRODUTOS A PRODUZIR'!A:A,'Cadastro-Estoque'!A:A,'PRODUTOS A PRODUZIR'!B:B,CONCATENATE("<=",$A$2))) -> 0 | S30: =R30*F30 -> 0
A31: 105 | B31: FUBÁ PRÉ COZIDO AREPITA CARIBE 30 x 500 | C31: 30 | D31: 0.5 | E31: 0.505 | F31: =C31*D31 -> 15 | G31: =C31*E31 -> 15.15 | I31: =IF(ISBLANK($A$2),SUMIFS(Entradas!C:C,Entradas!A:A,'Cadastro-Estoque'!A:A),SUMIFS(Entradas!C:C,Entradas!A:A,'Cadastro-Estoque'!A:A,Entradas!B:B,CONCATENATE("<=",$A$2))) -> 0 | J31: =I31*G31 -> 0 | L31: =IF(ISBLANK($A$2),SUMIFS(Saidas!C:C,Saidas!A:A,'Cadastro-Estoque'!A:A),SUMIFS(Saidas!C:C,Saidas!A:A,'Cadastro-Estoque'!A:A,Saidas!B:B,CONCATENATE("<=",$A$2))) -> 0 | M31: =L31*F31 -> 0 | O31: =IF(ISBLANK($A$2),SUMIFS(Faturado!C:C,Faturado!A:A,'Cadastro-Estoque'!A:A),SUMIFS(Faturado!C:C,Faturado!A:A,'Cadastro-Estoque'!A:A,Faturado!B:B,CONCATENATE("<=",$A$2))) -> 0 | P31: =O31*F31 -> 0 | R31: =IF(ISBLANK($A$2),SUMIFS('PRODUTOS A PRODUZIR'!C:C,'PRODUTOS A PRODUZIR'!A:A,'Cadastro-Estoque'!A:A),SUMIFS('PRODUTOS A PRODUZIR'!C:C,'PRODUTOS A PRODUZIR'!A:A,'Cadastro-Estoque'!A:A,'PRODUTOS A PRODUZIR'!B:B,CONCATENATE("<=",$A$2))) -> 0 | S31: =R31*F31 -> 0
I32: =IF(ISBLANK($A$2),SUMIFS(Entradas!C:C,Entradas!A:A,'Cadastro-Estoque'!A:A),SUMIFS(Entradas!C:C,Entradas!A:A,'Cadastro-Estoque'!A:A,Entradas!B:B,CONCATENATE("<=",$A$2))) -> 0 | J32: =I32*G32 -> 0 | L32: =IF(ISBLANK($A$2),SUMIFS(Saidas!C:C,Saidas!A:A,'Cadastro-Estoque'!A:A),SUMIFS(Saidas!C:C,Saidas!A:A,'Cadastro-Estoque'!A:A,Saidas!B:B,CONCATENATE("<=",$A$2))) -> 0 | M32: =L32*F32 -> 0 | O32: =IF(ISBLANK($A$2),SUMIFS(Faturado!C:C,Faturado!A:A,'Cadastro-Estoque'!A:A),SUMIFS(Faturado!C:C,Faturado!A:A,'Cadastro-Estoque'!A:A,Faturado!B:B,CONCATENATE("<=",$A$2))) -> 0 | P32: =O32*F32 -> 0 | R32: =IF(ISBLANK($A$2),SUMIFS('PRODUTOS A PRODUZIR'!C:C,'PRODUTOS A PRODUZIR'!A:A,'Cadastro-Estoque'!A:A),SUMIFS('PRODUTOS A PRODUZIR'!C:C,'PRODUTOS A PRODUZIR'!A:A,'Cadastro-Estoque'!A:A,'PRODUTOS A PRODUZIR'!B:B,CONCATENATE("<=",$A$2))) -> 0 | S32: =R32*F32 -> 0
A33: 201 | B33: FLOÇÃO MILHO NUTRIVITA 20 X 500 | C33: 20 | D33: 0.5 | E33: 0.505 | F33: =C33*D33 -> 10 | G33: =C33*E33 -> 10.1 | I33: =IF(ISBLANK($A$2),SUMIFS(Entradas!C:C,Entradas!A:A,'Cadastro-Estoque'!A:A),SUMIFS(Entradas!C:C,Entradas!A:A,'Cadastro-Estoque'!A:A,Entradas!B:B,CONCATENATE("<=",$A$2))) -> 1841 | J33: =I33*G33 -> 18594.1 | L33: =IF(ISBLANK($A$2),SUMIFS(Saidas!C:C,Saidas!A:A,'Cadastro-Estoque'!A:A),SUMIFS(Saidas!C:C,Saidas!A:A,'Cadastro-Estoque'!A:A,Saidas!B:B,CONCATENATE("<=",$A$2))) -> 1668 | M33: =L33*F33 -> 16680 | O33: =IF(ISBLANK($A$2),SUMIFS(Faturado!C:C,Faturado!A:A,'Cadastro-Estoque'!A:A),SUMIFS(Faturado!C:C,Faturado!A:A,'Cadastro-Estoque'!A:A,Faturado!B:B,CONCATENATE("<=",$A$2))) -> 0 | P33: =O33*F33 -> 0 | R33: =IF(ISBLANK($A$2),SUMIFS('PRODUTOS A PRODUZIR'!C:C,'PRODUTOS A PRODUZIR'!A:A,'Cadastro-Estoque'!A:A),SUMIFS('PRODUTOS A PRODUZIR'!C:C,'PRODUTOS A PRODUZIR'!A:A,'Cadastro-Estoque'!A:A,'PRODUTOS A PRODUZIR'!B:B,CONCATENATE("<=",$A$2))) -> 0 | S33: =R33*F33 -> 0
A34: 201 | B34: FLOÇÃO MILHO NUTRIVITA 10 X 500 | C34: 10 | D34: 0.5 | E34: 0.505 | F34: =C34*D34 -> 5 | G34: =C34*E34 -> 5.05 | I34: =IF(ISBLANK($A$2),SUMIFS(Entradas!C:C,Entradas!A:A,'Cadastro-Estoque'!A:A),SUMIFS(Entradas!C:C,Entradas!A:A,'Cadastro-Estoque'!A:A,Entradas!B:B,CONCATENATE("<=",$A$2))) -> 0 | J34: =I34*G34 -> 0 | L34: =IF(ISBLANK($A$2),SUMIFS(Saidas!C:C,Saidas!A:A,'Cadastro-Estoque'!A:A),SUMIFS(Saidas!C:C,Saidas!A:A,'Cadastro-Estoque'!A:A,Saidas!B:B,CONCATENATE("<=",$A$2))) -> 0 | M34: =L34*F34 -> 0 | O34: =IF(ISBLANK($A$2),SUMIFS(Faturado!C:C,Faturado!A:A,'Cadastro-Estoque'!A:A),SUMIFS(Faturado!C:C,Faturado!A:A,'Cadastro-Estoque'!A:A,Faturado!B:B,CONCATENATE("<=",$A$2))) -> 0 | P34: =O34*F34 -> 0 | R34: =IF(ISBLANK($A$2),SUMIFS('PRODUTOS A PRODUZIR'!C:C,'PRODUTOS A PRODUZIR'!A:A,'Cadastro-Estoque'!A:A),SUMIFS('PRODUTOS A PRODUZIR'!C:C,'PRODUTOS A PRODUZIR'!A:A,'Cadastro-Estoque'!A:A,'PRODUTOS A PRODUZIR'!B:B,CONCATENATE("<=",$A$2))) -> 0 | S34: =R34*F34 -> 0
A35: 205 | B35: FLOÇÃO MILHO VITABEM 20 X 500 | C35: 20 | D35: 0.5 | E35: 0.505 | F35: =C35*D35 -> 10 | G35: =C35*E35 -> 10.1 | I35: =IF(ISBLANK($A$2),SUMIFS(Entradas!C:C,Entradas!A:A,'Cadastro-Estoque'!A:A),SUMIFS(Entradas!C:C,Entradas!A:A,'Cadastro-Estoque'!A:A,Entradas!B:B,CONCATENATE("<=",$A$2))) -> 0 | J35: =I35*G35 -> 0 | L35: =IF(ISBLANK($A$2),SUMIFS(Saidas!C:C,Saidas!A:A,'Cadastro-Estoque'!A:A),SUMIFS(Saidas!C:C,Saidas!A:A,'Cadastro-Estoque'!A:A,Saidas!B:B,CONCATENATE("<=",$A$2))) -> 0 | M35: =L35*F35 -> 0 | O35: =IF(ISBLANK($A$2),SUMIFS(Faturado!C:C,Faturado!A:A,'Cadastro-Estoque'!A:A),SUMIFS(Faturado!C:C,Faturado!A:A,'Cadastro-Estoque'!A:A,Faturado!B:B,CONCATENATE("<=",$A$2))) -> 0 | P35: =O35*F35 -> 0 | R35: =IF(ISBLANK($A$2),SUMIFS('PRODUTOS A PRODUZIR'!C:C,'PRODUTOS A PRODUZIR'!A:A,'Cadastro-Estoque'!A:A),SUMIFS('PRODUTOS A PRODUZIR'!C:C,'PRODUTOS A PRODUZIR'!A:A,'Cadastro-Estoque'!A:A,'PRODUTOS A PRODUZIR'!B:B,CONCATENATE("<=",$A$2))) -> 0 | S35: =R35*F35 -> 0
A36: 207 | B36: FLOÇÃO MILHO VITABRAS 20 X 400 | C36: 20 | D36: 0.4 | E36: 0.404 | F36: =C36*D36 -> 8 | G36: =C36*E36 -> 8.08 | I36: =IF(ISBLANK($A$2),SUMIFS(Entradas!C:C,Entradas!A:A,'Cadastro-Estoque'!A:A),SUMIFS(Entradas!C:C,Entradas!A:A,'Cadastro-Estoque'!A:A,Entradas!B:B,CONCATENATE("<=",$A$2))) -> 0 | J36: =I36*G36 -> 0 | L36: =IF(ISBLANK($A$2),SUMIFS(Saidas!C:C,Saidas!A:A,'Cadastro-Estoque'!A:A),SUMIFS(Saidas!C:C,Saidas!A:A,'Cadastro-Estoque'!A:A,Saidas!B:B,CONCATENATE("<=",$A$2))) -> 0 | M36: =L36*F36 -> 0 | O36: =IF(ISBLANK($A$2),SUMIFS(Faturado!C:C,Faturado!A:A,'Cadastro-Estoque'!A:A),SUMIFS(Faturado!C:C,Faturado!A:A,'Cadastro-Estoque'!A:A,Faturado!B:B,CONCATENATE("<=",$A$2))) -> 0 | P36: =O36*F36 -> 0 | R36: =IF(ISBLANK($A$2),SUMIFS('PRODUTOS A PRODUZIR'!C:C,'PRODUTOS A PRODUZIR'!A:A,'Cadastro-Estoque'!A:A),SUMIFS('PRODUTOS A PRODUZIR'!C:C,'PRODUTOS A PRODUZIR'!A:A,'Cadastro-Estoque'!A:A,'PRODUTOS A PRODUZIR'!B:B,CONCATENATE("<=",$A$2))) -> 0 | S36: =R36*F36 -> 0
A37: 208 | B37: FLOÇÃO MILHO PURO MILHO 12 X 500 | C37: 12 | D37: 0.5 | E37: 0.505 | F37: =C37*D37 -> 6 | G37: =C37*E37 -> 6.06 | I37: =IF(ISBLANK($A$2),SUMIFS(Entradas!C:C,Entradas!A:A,'Cadastro-Estoque'!A:A),SUMIFS(Entradas!C:C,Entradas!A:A,'Cadastro-Estoque'!A:A,Entradas!B:B,CONCATENATE("<=",$A$2))) -> 0 | J37: =I37*G37 -> 0 | L37: =IF(ISBLANK($A$2),SUMIFS(Saidas!C:C,Saidas!A:A,'Cadastro-Estoque'!A:A),SUMIFS(Saidas!C:C,Saidas!A:A,'Cadastro-Estoque'!A:A,Saidas!B:B,CONCATENATE("<=",$A$2))) -> 10400 | M37: =L37*F37 -> 62400 | O37: =IF(ISBLANK($A$2),SUMIFS(Faturado!C:C,Faturado!A:A,'Cadastro-Estoque'!A:A),SUMIFS(Faturado!C:C,Faturado!A:A,'Cadastro-Estoque'!A:A,Faturado!B:B,CONCATENATE("<=",$A$2))) -> 0 | P37: =O37*F37 -> 0 | R37: =IF(ISBLANK($A$2),SUMIFS('PRODUTOS A PRODUZIR'!C:C,'PRODUTOS A PRODUZIR'!A:A,'Cadastro-Estoque'!A:A),SUMIFS('PRODUTOS A PRODUZIR'!C:C,'PRODUTOS A PRODUZIR'!A:A,'Cadastro-Estoque'!A:A,'PRODUTOS A PRODUZIR'!B:B,CONCATENATE("<=",$A$2))) -> 0 | S37: =R37*F37 -> 0
A38: 209 | B38: FLOCÃO DE MILHO QUALITÁ 12 X 500 | C38: 12 | D38: 0.5 | E38: 0.505 | F38: =C38*D38 -> 6 | G38: =C38*E38 -> 6.06 | I38: =IF(ISBLANK($A$2),SUMIFS(Entradas!C:C,Entradas!A:A,'Cadastro-Estoque'!A:A),SUMIFS(Entradas!C:C,Entradas!A:A,'Cadastro-Estoque'!A:A,Entradas!B:B,CONCATENATE("<=",$A$2))) -> 0 | J38: =I38*G38 -> 0 | L38: =IF(ISBLANK($A$2),SUMIFS(Saidas!C:C,Saidas!A:A,'Cadastro-Estoque'!A:A),SUMIFS(Saidas!C:C,Saidas!A:A,'Cadastro-Estoque'!A:A,Saidas!B:B,CONCATENATE("<=",$A$2))) -> 0 | M38: =L38*F38 -> 0 | O38: =IF(ISBLANK($A$2),SUMIFS(Faturado!C:C,Faturado!A:A,'Cadastro-Estoque'!A:A),SUMIFS(Faturado!C:C,Faturado!A:A,'Cadastro-Estoque'!A:A,Faturado!B:B,CONCATENATE("<=",$A$2))) -> 0 | P38: =O38*F38 -> 0 | R38: =IF(ISBLANK($A$2),SUMIFS('PRODUTOS A PRODUZIR'!C:C,'PRODUTOS A PRODUZIR'!A:A,'Cadastro-Estoque'!A:A),SUMIFS('PRODUTOS A PRODUZIR'!C:C,'PRODUTOS A PRODUZIR'!A:A,'Cadastro-Estoque'!A:A,'PRODUTOS A PRODUZIR'!B:B,CONCATENATE("<=",$A$2))) -> 0 | S38: =R38*F38 -> 0
A39: 212 | B39: FLOCAO DE MILHO LESTE 20 X 500 | C39: 20 | D39: 0.5 | E39: 0.505 | F39: =C39*D39 -> 10 | G39: =C39*E39 -> 10.1 | I39: =IF(ISBLANK($A$2),SUMIFS(Entradas!C:C,Entradas!A:A,'Cadastro-Estoque'!A:A),SUMIFS(Entradas!C:C,Entradas!A:A,'Cadastro-Estoque'!A:A,Entradas!B:B,CONCATENATE("<=",$A$2))) -> 0 | J39: =I39*G39 -> 0 | L39: =IF(ISBLANK($A$2),SUMIFS(Saidas!C:C,Saidas!A:A,'Cadastro-Estoque'!A:A),SUMIFS(Saidas!C:C,Saidas!A:A,'Cadastro-Estoque'!A:A,Saidas!B:B,CONCATENATE("<=",$A$2))) -> 0 | M39: =L39*F39 -> 0 | O39: =IF(ISBLANK($A$2),SUMIFS(Faturado!C:C,Faturado!A:A,'Cadastro-Estoque'!A:A),SUMIFS(Faturado!C:C,Faturado!A:A,'Cadastro-Estoque'!A:A,Faturado!B:B,CONCATENATE("<=",$A$2))) -> 0 | P39: =O39*F39 -> 0 | R39: =IF(ISBLANK($A$2),SUMIFS('PRODUTOS A PRODUZIR'!C:C,'PRODUTOS A PRODUZIR'!A:A,'Cadastro-Estoque'!A:A),SUMIFS('PRODUTOS A PRODUZIR'!C:C,'PRODUTOS A PRODUZIR'!A:A,'Cadastro-Estoque'!A:A,'PRODUTOS A PRODUZIR'!B:B,CONCATENATE("<=",$A$2))) -> 0 | S39: =R39*F39 -> 0
A40: 216 | B40: FLOÇÃO MILHO M & K 12 X 500 | C40: 12 | D40: 0.5 | E40: 0.505 | F40: =C40*D40 -> 6 | G40: =C40*E40 -> 6.06 | I40: =IF(ISBLANK($A$2),SUMIFS(Entradas!C:C,Entradas!A:A,'Cadastro-Estoque'!A:A),SUMIFS(Entradas!C:C,Entradas!A:A,'Cadastro-Estoque'!A:A,Entradas!B:B,CONCATENATE("<=",$A$2))) -> 0 | J40: =I40*G40 -> 0 | L40: =IF(ISBLANK($A$2),SUMIFS(Saidas!C:C,Saidas!A:A,'Cadastro-Estoque'!A:A),SUMIFS(Saidas!C:C,Saidas!A:A,'Cadastro-Estoque'!A:A,Saidas!B:B,CONCATENATE("<=",$A$2))) -> 0 | M40: =L40*F40 -> 0 | O40: =IF(ISBLANK($A$2),SUMIFS(Faturado!C:C,Faturado!A:A,'Cadastro-Estoque'!A:A),SUMIFS(Faturado!C:C,Faturado!A:A,'Cadastro-Estoque'!A:A,Faturado!B:B,CONCATENATE("<=",$A$2))) -> 0 | P40: =O40*F40 -> 0 | R40: =IF(ISBLANK($A$2),SUMIFS('PRODUTOS A PRODUZIR'!C:C,'PRODUTOS A PRODUZIR'!A:A,'Cadastro-Estoque'!A:A),SUMIFS('PRODUTOS A PRODUZIR'!C:C,'PRODUTOS A PRODUZIR'!A:A,'Cadastro-Estoque'!A:A,'PRODUTOS A PRODUZIR'!B:B,CONCATENATE("<=",$A$2))) -> 0 | S40: =R40*F40 -> 0
A41: 218 | B41: FLOÇÃO MILHO CBS 12 X 500 | C41: 12 | D41: 0.5 | E41: 0.505 | F41: =C41*D41 -> 6 | G41: =C41*E41 -> 6.06 | I41: =IF(ISBLANK($A$2),SUMIFS(Entradas!C:C,Entradas!A:A,'Cadastro-Estoque'!A:A),SUMIFS(Entradas!C:C,Entradas!A:A,'Cadastro-Estoque'!A:A,Entradas!B:B,CONCATENATE("<=",$A$2))) -> 0 | J41: =I41*G41 -> 0 | L41: =IF(ISBLANK($A$2),SUMIFS(Saidas!C:C,Saidas!A:A,'Cadastro-Estoque'!A:A),SUMIFS(Saidas!C:C,Saidas!A:A,'Cadastro-Estoque'!A:A,Saidas!B:B,CONCATENATE("<=",$A$2))) -> 0 | M41: =L41*F41 -> 0 | O41: =IF(ISBLANK($A$2),SUMIFS(Faturado!C:C,Faturado!A:A,'Cadastro-Estoque'!A:A),SUMIFS(Faturado!C:C,Faturado!A:A,'Cadastro-Estoque'!A:A,Faturado!B:B,CONCATENATE("<=",$A$2))) -> 0 | P41: =O41*F41 -> 0 | R41: =IF(ISBLANK($A$2),SUMIFS('PRODUTOS A PRODUZIR'!C:C,'PRODUTOS A PRODUZIR'!A:A,'Cadastro-Estoque'!A:A),SUMIFS('PRODUTOS A PRODUZIR'!C:C,'PRODUTOS A PRODUZIR'!A:A,'Cadastro-Estoque'!A:A,'PRODUTOS A PRODUZIR'!B:B,CONCATENATE("<=",$A$2))) -> 0 | S41: =R41*F41 -> 0
A42: 220 | B42: FLOÇÃO MILHO CORDEIRO 20 X 500 | C42: 20 | D42: 0.5 | E42: 0.505 | F42: =C42*D42 -> 10 | G42: =C42*E42 -> 10.1 | I42: =IF(ISBLANK($A$2),SUMIFS(Entradas!C:C,Entradas!A:A,'Cadastro-Estoque'!A:A),SUMIFS(Entradas!C:C,Entradas!A:A,'Cadastro-Estoque'!A:A,Entradas!B:B,CONCATENATE("<=",$A$2))) -> 0 | J42: =I42*G42 -> 0 | L42: =IF(ISBLANK($A$2),SUMIFS(Saidas!C:C,Saidas!A:A,'Cadastro-Estoque'!A:A),SUMIFS(Saidas!C:C,Saidas!A:A,'Cadastro-Estoque'!A:A,Saidas!B:B,CONCATENATE("<=",$A$2))) -> 0 | M42: =L42*F42 -> 0 | O42: =IF(ISBLANK($A$2),SUMIFS(Faturado!C:C,Faturado!A:A,'Cadastro-Estoque'!A:A),SUMIFS(Faturado!C:C,Faturado!A:A,'Cadastro-Estoque'!A:A,Faturado!B:B,CONCATENATE("<=",$A$2))) -> 0 | P42: =O42*F42 -> 0 | R42: =IF(ISBLANK($A$2),SUMIFS('PRODUTOS A PRODUZIR'!C:C,'PRODUTOS A PRODUZIR'!A:A,'Cadastro-Estoque'!A:A),SUMIFS('PRODUTOS A PRODUZIR'!C:C,'PRODUTOS A PRODUZIR'!A:A,'Cadastro-Estoque'!A:A,'PRODUTOS A PRODUZIR'!B:B,CONCATENATE("<=",$A$2))) -> 0 | S42: =R42*F42 -> 0
A43: 221 | B43: FLOÇÃO MILHO PUBLIC 24 X 500 | C43: 24 | D43: 0.5 | E43: 0.505 | F43: =C43*D43 -> 12 | G43: =C43*E43 -> 12.12 | I43: =IF(ISBLANK($A$2),SUMIFS(Entradas!C:C,Entradas!A:A,'Cadastro-Estoque'!A:A),SUMIFS(Entradas!C:C,Entradas!A:A,'Cadastro-Estoque'!A:A,Entradas!B:B,CONCATENATE("<=",$A$2))) -> 0 | J43: =I43*G43 -> 0 | L43: =IF(ISBLANK($A$2),SUMIFS(Saidas!C:C,Saidas!A:A,'Cadastro-Estoque'!A:A),SUMIFS(Saidas!C:C,Saidas!A:A,'Cadastro-Estoque'!A:A,Saidas!B:B,CONCATENATE("<=",$A$2))) -> 0 | M43: =L43*F43 -> 0 | O43: =IF(ISBLANK($A$2),SUMIFS(Faturado!C:C,Faturado!A:A,'Cadastro-Estoque'!A:A),SUMIFS(Faturado!C:C,Faturado!A:A,'Cadastro-Estoque'!A:A,Faturado!B:B,CONCATENATE("<=",$A$2))) -> 0 | P43: =O43*F43 -> 0 | R43: =IF(ISBLANK($A$2),SUMIFS('PRODUTOS A PRODUZIR'!C:C,'PRODUTOS A PRODUZIR'!A:A,'Cadastro-Estoque'!A:A),SUMIFS('PRODUTOS A PRODUZIR'!C:C,'PRODUTOS A PRODUZIR'!A:A,'Cadastro-Estoque'!A:A,'PRODUTOS A PRODUZIR'!B:B,CONCATENATE("<=",$A$2))) -> 0 | S43: =R43*F43 -> 0
A44: 222 | B44: FLOÇÃO MILHO PANAMERICAN 12 X 500 | C44: 12 | D44: 0.5 | E44: 0.505 | F44: =C44*D44 -> 6 | G44: =C44*E44 -> 6.06 | I44: =IF(ISBLANK($A$2),SUMIFS(Entradas!C:C,Entradas!A:A,'Cadastro-Estoque'!A:A),SUMIFS(Entradas!C:C,Entradas!A:A,'Cadastro-Estoque'!A:A,Entradas!B:B,CONCATENATE("<=",$A$2))) -> 0 | J44: =I44*G44 -> 0 | L44: =IF(ISBLANK($A$2),SUMIFS(Saidas!C:C,Saidas!A:A,'Cadastro-Estoque'!A:A),SUMIFS(Saidas!C:C,Saidas!A:A,'Cadastro-Estoque'!A:A,Saidas!B:B,CONCATENATE("<=",$A$2))) -> 0 | M44: =L44*F44 -> 0 | O44: =IF(ISBLANK($A$2),SUMIFS(Faturado!C:C,Faturado!A:A,'Cadastro-Estoque'!A:A),SUMIFS(Faturado!C:C,Faturado!A:A,'Cadastro-Estoque'!A:A,Faturado!B:B,CONCATENATE("<=",$A$2))) -> 0 | P44: =O44*F44 -> 0 | R44: =IF(ISBLANK($A$2),SUMIFS('PRODUTOS A PRODUZIR'!C:C,'PRODUTOS A PRODUZIR'!A:A,'Cadastro-Estoque'!A:A),SUMIFS('PRODUTOS A PRODUZIR'!C:C,'PRODUTOS A PRODUZIR'!A:A,'Cadastro-Estoque'!A:A,'PRODUTOS A PRODUZIR'!B:B,CONCATENATE("<=",$A$2))) -> 0 | S44: =R44*F44 -> 0
... A49: 229 | B49: FLOCÃO DE MILHO LAMPIONE 20 X 500 | C49: 20 | D49: 0.5 | E49: 0.505 | F49: =C49*D49 -> 10 | G49: =C49*E49 -> 10.1 | I49: =IF(ISBLANK($A$2),SUMIFS(Entradas!C:C,Entradas!A:A,'Cadastro-Estoque'!A:A),SUMIFS(Entradas!C:C,Entradas!A:A,'Cadastro-Estoque'!A:A,Entradas!B:B,CONCATENATE("<=",$A$2))) -> 0 | J49: =I49*G49 -> 0 | L49: =IF(ISBLANK($A$2),SUMIFS(Saidas!C:C,Saidas!A:A,'Cadastro-Estoque'!A:A),SUMIFS(Saidas!C:C,Saidas!A:A,'Cadastro-Estoque'!A:A,Saidas!B:B,CONCATENATE("<=",$A$2))) -> 0 | M49: =L49*F49 -> 0 | O49: =IF(ISBLANK($A$2),SUMIFS(Faturado!C:C,Faturado!A:A,'Cadastro-Estoque'!A:A),SUMIFS(Faturado!C:C,Faturado!A:A,'Cadastro-Estoque'!A:A,Faturado!B:B,CONCATENATE("<=",$A$2))) -> 0 | P49: =O49*F49 -> 0 | R49: =IF(ISBLANK($A$2),SUMIFS('PRODUTOS A PRODUZIR'!C:C,'PRODUTOS A PRODUZIR'!A:A,'Cadastro-Estoque'!A:A),SUMIFS('PRODUTOS A PRODUZIR'!C:C,'PRODUTOS A PRODUZIR'!A:A,'Cadastro-Estoque'!A:A,'PRODUTOS A PRODUZIR'!B:B,CONCATENATE("<=",$A$2))) -> 0 | S49: =R49*F49 -> 0
F50: =C50*D50 -> 0 | G50: =C50*E50 -> 0 | I50: =IF(ISBLANK($A$2),SUMIFS(Entradas!C:C,Entradas!A:A,'Cadastro-Estoque'!A:A),SUMIFS(Entradas!C:C,Entradas!A:A,'Cadastro-Estoque'!A:A,Entradas!B:B,CONCATENATE("<=",$A$2))) -> 0 | J50: =I50*G50 -> 0 | L50: =IF(ISBLANK($A$2),SUMIFS(Saidas!C:C,Saidas!A:A,'Cadastro-Estoque'!A:A),SUMIFS(Saidas!C:C,Saidas!A:A,'Cadastro-Estoque'!A:A,Saidas!B:B,CONCATENATE("<=",$A$2))) -> 0 | M50: =L50*F50 -> 0 | O50: =IF(ISBLANK($A$2),SUMIFS(Faturado!C:C,Faturado!A:A,'Cadastro-Estoque'!A:A),SUMIFS(Faturado!C:C,Faturado!A:A,'Cadastro-Estoque'!A:A,Faturado!B:B,CONCATENATE("<=",$A$2))) -> 0 | P50: =O50*F50 -> 0 | R50: =IF(ISBLANK($A$2),SUMIFS('PRODUTOS A PRODUZIR'!C:C,'PRODUTOS A PRODUZIR'!A:A,'Cadastro-Estoque'!A:A),SUMIFS('PRODUTOS A PRODUZIR'!C:C,'PRODUTOS A PRODUZIR'!A:A,'Cadastro-Estoque'!A:A,'PRODUTOS A PRODUZIR'!B:B,CONCATENATE("<=",$A$2))) -> 0 | S50: =R50*F50 -> 0
A51: 204 | B51: FLOÇÃO ARROZ NUTRIVITA 20 X 500 | C51: 20 | D51: 0.5 | E51: 0.505 | F51: =C51*D51 -> 10 | G51: =C51*E51 -> 10.1 | I51: =IF(ISBLANK($A$2),SUMIFS(Entradas!C:C,Entradas!A:A,'Cadastro-Estoque'!A:A),SUMIFS(Entradas!C:C,Entradas!A:A,'Cadastro-Estoque'!A:A,Entradas!B:B,CONCATENATE("<=",$A$2))) -> 2131 | J51: =I51*G51 -> 21523.1 | L51: =IF(ISBLANK($A$2),SUMIFS(Saidas!C:C,Saidas!A:A,'Cadastro-Estoque'!A:A),SUMIFS(Saidas!C:C,Saidas!A:A,'Cadastro-Estoque'!A:A,Saidas!B:B,CONCATENATE("<=",$A$2))) -> 2500 | M51: =L51*F51 -> 25000 | O51: =IF(ISBLANK($A$2),SUMIFS(Faturado!C:C,Faturado!A:A,'Cadastro-Estoque'!A:A),SUMIFS(Faturado!C:C,Faturado!A:A,'Cadastro-Estoque'!A:A,Faturado!B:B,CONCATENATE("<=",$A$2))) -> 0 | P51: =O51*F51 -> 0 | R51: =IF(ISBLANK($A$2),SUMIFS('PRODUTOS A PRODUZIR'!C:C,'PRODUTOS A PRODUZIR'!A:A,'Cadastro-Estoque'!A:A),SUMIFS('PRODUTOS A PRODUZIR'!C:C,'PRODUTOS A PRODUZIR'!A:A,'Cadastro-Estoque'!A:A,'PRODUTOS A PRODUZIR'!B:B,CONCATENATE("<=",$A$2))) -> 0 | S51: =R51*F51 -> 0
A52: 204 | B52: FLOÇÃO ARROZ NUTRIVITA 10 X 500 | C52: 10 | D52: 0.5 | E52: 0.505 | F52: =C52*D52 -> 5 | G52: =C52*E52 -> 5.05 | I52: =IF(ISBLANK($A$2),SUMIFS(Entradas!C:C,Entradas!A:A,'Cadastro-Estoque'!A:A),SUMIFS(Entradas!C:C,Entradas!A:A,'Cadastro-Estoque'!A:A,Entradas!B:B,CONCATENATE("<=",$A$2))) -> 0 | J52: =I52*G52 -> 0 | L52: =IF(ISBLANK($A$2),SUMIFS(Saidas!C:C,Saidas!A:A,'Cadastro-Estoque'!A:A),SUMIFS(Saidas!C:C,Saidas!A:A,'Cadastro-Estoque'!A:A,Saidas!B:B,CONCATENATE("<=",$A$2))) -> 0 | M52: =L52*F52 -> 0 | O52: =IF(ISBLANK($A$2),SUMIFS(Faturado!C:C,Faturado!A:A,'Cadastro-Estoque'!A:A),SUMIFS(Faturado!C:C,Faturado!A:A,'Cadastro-Estoque'!A:A,Faturado!B:B,CONCATENATE("<=",$A$2))) -> 0 | P52: =O52*F52 -> 0 | R52: =IF(ISBLANK($A$2),SUMIFS('PRODUTOS A PRODUZIR'!C:C,'PRODUTOS A PRODUZIR'!A:A,'Cadastro-Estoque'!A:A),SUMIFS('PRODUTOS A PRODUZIR'!C:C,'PRODUTOS A PRODUZIR'!A:A,'Cadastro-Estoque'!A:A,'PRODUTOS A PRODUZIR'!B:B,CONCATENATE("<=",$A$2))) -> 0 | S52: =R52*F52 -> 0
F53: =C53*D53 -> 0 | G53: =C53*E53 -> 0 | I53: =IF(ISBLANK($A$2),SUMIFS(Entradas!C:C,Entradas!A:A,'Cadastro-Estoque'!A:A),SUMIFS(Entradas!C:C,Entradas!A:A,'Cadastro-Estoque'!A:A,Entradas!B:B,CONCATENATE("<=",$A$2))) -> 0 | J53: =I53*G53 -> 0 | L53: =IF(ISBLANK($A$2),SUMIFS(Saidas!C:C,Saidas!A:A,'Cadastro-Estoque'!A:A),SUMIFS(Saidas!C:C,Saidas!A:A,'Cadastro-Estoque'!A:A,Saidas!B:B,CONCATENATE("<=",$A$2))) -> 0 | M53: =L53*F53 -> 0 | O53: =IF(ISBLANK($A$2),SUMIFS(Faturado!C:C,Faturado!A:A,'Cadastro-Estoque'!A:A),SUMIFS(Faturado!C:C,Faturado!A:A,'Cadastro-Estoque'!A:A,Faturado!B:B,CONCATENATE("<=",$A$2))) -> 0 | P53: =O53*F53 -> 0 | R53: =IF(ISBLANK($A$2),SUMIFS('PRODUTOS A PRODUZIR'!C:C,'PRODUTOS A PRODUZIR'!A:A,'Cadastro-Estoque'!A:A),SUMIFS('PRODUTOS A PRODUZIR'!C:C,'PRODUTOS A PRODUZIR'!A:A,'Cadastro-Estoque'!A:A,'PRODUTOS A PRODUZIR'!B:B,CONCATENATE("<=",$A$2))) -> 0 | S53: =R53*F53 -> 0
A54: 057 | B54: FUBÁ KISABOR 12 X 1 K | C54: 12 | D54: 1 | E54: 1.005 | F54: =C54*D54 -> 12 | G54: =C54*E54 -> 12.06 | I54: =IF(ISBLANK($A$2),SUMIFS(Entradas!C:C,Entradas!A:A,'Cadastro-Estoque'!A:A),SUMIFS(Entradas!C:C,Entradas!A:A,'Cadastro-Estoque'!A:A,Entradas!B:B,CONCATENATE("<=",$A$2))) -> 0 | J54: =I54*G54 -> 0 | L54: =IF(ISBLANK($A$2),SUMIFS(Saidas!C:C,Saidas!A:A,'Cadastro-Estoque'!A:A),SUMIFS(Saidas!C:C,Saidas!A:A,'Cadastro-Estoque'!A:A,Saidas!B:B,CONCATENATE("<=",$A$2))) -> 0 | M54: =L54*F54 -> 0 | O54: =IF(ISBLANK($A$2),SUMIFS(Faturado!C:C,Faturado!A:A,'Cadastro-Estoque'!A:A),SUMIFS(Faturado!C:C,Faturado!A:A,'Cadastro-Estoque'!A:A,Faturado!B:B,CONCATENATE("<=",$A$2))) -> 0 | P54: =O54*F54 -> 0 | R54: =IF(ISBLANK($A$2),SUMIFS('PRODUTOS A PRODUZIR'!C:C,'PRODUTOS A PRODUZIR'!A:A,'Cadastro-Estoque'!A:A),SUMIFS('PRODUTOS A PRODUZIR'!C:C,'PRODUTOS A PRODUZIR'!A:A,'Cadastro-Estoque'!A:A,'PRODUTOS A PRODUZIR'!B:B,CONCATENATE("<=",$A$2))) -> 0 | S54: =R54*F54 -> 0
A55: 057 | B55: FUBÁ KISABOR 12 X 500 G | C55: 12 | D55: 0.5 | E55: 0.505 | F55: =C55*D55 -> 6 | G55: =C55*E55 -> 6.06 | I55: =IF(ISBLANK($A$2),SUMIFS(Entradas!C:C,Entradas!A:A,'Cadastro-Estoque'!A:A),SUMIFS(Entradas!C:C,Entradas!A:A,'Cadastro-Estoque'!A:A,Entradas!B:B,CONCATENATE("<=",$A$2))) -> 0 | J55: =I55*G55 -> 0 | L55: =IF(ISBLANK($A$2),SUMIFS(Saidas!C:C,Saidas!A:A,'Cadastro-Estoque'!A:A),SUMIFS(Saidas!C:C,Saidas!A:A,'Cadastro-Estoque'!A:A,Saidas!B:B,CONCATENATE("<=",$A$2))) -> 0 | M55: =L55*F55 -> 0 | O55: =IF(ISBLANK($A$2),SUMIFS(Faturado!C:C,Faturado!A:A,'Cadastro-Estoque'!A:A),SUMIFS(Faturado!C:C,Faturado!A:A,'Cadastro-Estoque'!A:A,Faturado!B:B,CONCATENATE("<=",$A$2))) -> 0 | P55: =O55*F55 -> 0 | R55: =IF(ISBLANK($A$2),SUMIFS('PRODUTOS A PRODUZIR'!C:C,'PRODUTOS A PRODUZIR'!A:A,'Cadastro-Estoque'!A:A),SUMIFS('PRODUTOS A PRODUZIR'!C:C,'PRODUTOS A PRODUZIR'!A:A,'Cadastro-Estoque'!A:A,'PRODUTOS A PRODUZIR'!B:B,CONCATENATE("<=",$A$2))) -> 0 | S55: =R55*F55 -> 0
A56: 057 | B56: FUBÁ KISABOR 24 X 500 G | C56: 24 | D56: 0.5 | E56: 0.505 | F56: =C56*D56 -> 12 | G56: =C56*E56 -> 12.12 | I56: =IF(ISBLANK($A$2),SUMIFS(Entradas!C:C,Entradas!A:A,'Cadastro-Estoque'!A:A),SUMIFS(Entradas!C:C,Entradas!A:A,'Cadastro-Estoque'!A:A,Entradas!B:B,CONCATENATE("<=",$A$2))) -> 0 | J56: =I56*G56 -> 0 | L56: =IF(ISBLANK($A$2),SUMIFS(Saidas!C:C,Saidas!A:A,'Cadastro-Estoque'!A:A),SUMIFS(Saidas!C:C,Saidas!A:A,'Cadastro-Estoque'!A:A,Saidas!B:B,CONCATENATE("<=",$A$2))) -> 0 | M56: =L56*F56 -> 0 | O56: =IF(ISBLANK($A$2),SUMIFS(Faturado!C:C,Faturado!A:A,'Cadastro-Estoque'!A:A),SUMIFS(Faturado!C:C,Faturado!A:A,'Cadastro-Estoque'!A:A,Faturado!B:B,CONCATENATE("<=",$A$2))) -> 0 | P56: =O56*F56 -> 0 | R56: =IF(ISBLANK($A$2),SUMIFS('PRODUTOS A PRODUZIR'!C:C,'PRODUTOS A PRODUZIR'!A:A,'Cadastro-Estoque'!A:A),SUMIFS('PRODUTOS A PRODUZIR'!C:C,'PRODUTOS A PRODUZIR'!A:A,'Cadastro-Estoque'!A:A,'PRODUTOS A PRODUZIR'!B:B,CONCATENATE("<=",$A$2))) -> 0 | S56: =R56*F56 -> 0
A57: 063 | B57: FUBÁ NUTRIVITA 12 X 1 K | C57: 12 | D57: 1 | E57: 1.005 | F57: =C57*D57 -> 12 | G57: =C57*E57 -> 12.06 | I57: =IF(ISBLANK($A$2),SUMIFS(Entradas!C:C,Entradas!A:A,'Cadastro-Estoque'!A:A),SUMIFS(Entradas!C:C,Entradas!A:A,'Cadastro-Estoque'!A:A,Entradas!B:B,CONCATENATE("<=",$A$2))) -> 0 | J57: =I57*G57 -> 0 | L57: =IF(ISBLANK($A$2),SUMIFS(Saidas!C:C,Saidas!A:A,'Cadastro-Estoque'!A:A),SUMIFS(Saidas!C:C,Saidas!A:A,'Cadastro-Estoque'!A:A,Saidas!B:B,CONCATENATE("<=",$A$2))) -> 0 | M57: =L57*F57 -> 0 | O57: =IF(ISBLANK($A$2),SUMIFS(Faturado!C:C,Faturado!A:A,'Cadastro-Estoque'!A:A),SUMIFS(Faturado!C:C,Faturado!A:A,'Cadastro-Estoque'!A:A,Faturado!B:B,CONCATENATE("<=",$A$2))) -> 0 | P57: =O57*F57 -> 0 | R57: =IF(ISBLANK($A$2),SUMIFS('PRODUTOS A PRODUZIR'!C:C,'PRODUTOS A PRODUZIR'!A:A,'Cadastro-Estoque'!A:A),SUMIFS('PRODUTOS A PRODUZIR'!C:C,'PRODUTOS A PRODUZIR'!A:A,'Cadastro-Estoque'!A:A,'PRODUTOS A PRODUZIR'!B:B,CONCATENATE("<=",$A$2))) -> 0 | S57: =R57*F57 -> 0
A58: 063 | B58: FUBÁ NUTRIVITA 12 X 500 G | C58: 12 | D58: 0.5 | E58: 0.505 | F58: =C58*D58 -> 6 | G58: =C58*E58 -> 6.06 | I58: =IF(ISBLANK($A$2),SUMIFS(Entradas!C:C,Entradas!A:A,'Cadastro-Estoque'!A:A),SUMIFS(Entradas!C:C,Entradas!A:A,'Cadastro-Estoque'!A:A,Entradas!B:B,CONCATENATE("<=",$A$2))) -> 0 | J58: =I58*G58 -> 0 | L58: =IF(ISBLANK($A$2),SUMIFS(Saidas!C:C,Saidas!A:A,'Cadastro-Estoque'!A:A),SUMIFS(Saidas!C:C,Saidas!A:A,'Cadastro-Estoque'!A:A,Saidas!B:B,CONCATENATE("<=",$A$2))) -> 0 | M58: =L58*F58 -> 0 | O58: =IF(ISBLANK($A$2),SUMIFS(Faturado!C:C,Faturado!A:A,'Cadastro-Estoque'!A:A),SUMIFS(Faturado!C:C,Faturado!A:A,'Cadastro-Estoque'!A:A,Faturado!B:B,CONCATENATE("<=",$A$2))) -> 0 | P58: =O58*F58 -> 0 | R58: =IF(ISBLANK($A$2),SUMIFS('PRODUTOS A PRODUZIR'!C:C,'PRODUTOS A PRODUZIR'!A:A,'Cadastro-Estoque'!A:A),SUMIFS('PRODUTOS A PRODUZIR'!C:C,'PRODUTOS A PRODUZIR'!A:A,'Cadastro-Estoque'!A:A,'PRODUTOS A PRODUZIR'!B:B,CONCATENATE("<=",$A$2))) -> 0 | S58: =R58*F58 -> 0
A59: 063 | B59: FUBÁ NUTRIVITA 24 X 500 G | C59: 24 | D59: 0.5 | E59: 0.505 | F59: =C59*D59 -> 12 | G59: =C59*E59 -> 12.12 | I59: =IF(ISBLANK($A$2),SUMIFS(Entradas!C:C,Entradas!A:A,'Cadastro-Estoque'!A:A),SUMIFS(Entradas!C:C,Entradas!A:A,'Cadastro-Estoque'!A:A,Entradas!B:B,CONCATENATE("<=",$A$2))) -> 0 | J59: =I59*G59 -> 0 | L59: =IF(ISBLANK($A$2),SUMIFS(Saidas!C:C,Saidas!A:A,'Cadastro-Estoque'!A:A),SUMIFS(Saidas!C:C,Saidas!A:A,'Cadastro-Estoque'!A:A,Saidas!B:B,CONCATENATE("<=",$A$2))) -> 0 | M59: =L59*F59 -> 0 | O59: =IF(ISBLANK($A$2),SUMIFS(Faturado!C:C,Faturado!A:A,'Cadastro-Estoque'!A:A),SUMIFS(Faturado!C:C,Faturado!A:A,'Cadastro-Estoque'!A:A,Faturado!B:B,CONCATENATE("<=",$A$2))) -> 0 | P59: =O59*F59 -> 0 | R59: =IF(ISBLANK($A$2),SUMIFS('PRODUTOS A PRODUZIR'!C:C,'PRODUTOS A PRODUZIR'!A:A,'Cadastro-Estoque'!A:A),SUMIFS('PRODUTOS A PRODUZIR'!C:C,'PRODUTOS A PRODUZIR'!A:A,'Cadastro-Estoque'!A:A,'PRODUTOS A PRODUZIR'!B:B,CONCATENATE("<=",$A$2))) -> 0 | S59: =R59*F59 -> 0
A60: 065 | B60: FARINHA NUTRIVITA 12 X 1 K | C60: 12 | D60: 1 | E60: 1.005 | F60: =C60*D60 -> 12 | G60: =C60*E60 -> 12.06 | I60: =IF(ISBLANK($A$2),SUMIFS(Entradas!C:C,Entradas!A:A,'Cadastro-Estoque'!A:A),SUMIFS(Entradas!C:C,Entradas!A:A,'Cadastro-Estoque'!A:A,Entradas!B:B,CONCATENATE("<=",$A$2))) -> 0 | J60: =I60*G60 -> 0 | L60: =IF(ISBLANK($A$2),SUMIFS(Saidas!C:C,Saidas!A:A,'Cadastro-Estoque'!A:A),SUMIFS(Saidas!C:C,Saidas!A:A,'Cadastro-Estoque'!A:A,Saidas!B:B,CONCATENATE("<=",$A$2))) -> 0 | M60: =L60*F60 -> 0 | O60: =IF(ISBLANK($A$2),SUMIFS(Faturado!C:C,Faturado!A:A,'Cadastro-Estoque'!A:A),SUMIFS(Faturado!C:C,Faturado!A:A,'Cadastro-Estoque'!A:A,Faturado!B:B,CONCATENATE("<=",$A$2))) -> 0 | P60: =O60*F60 -> 0 | R60: =IF(ISBLANK($A$2),SUMIFS('PRODUTOS A PRODUZIR'!C:C,'PRODUTOS A PRODUZIR'!A:A,'Cadastro-Estoque'!A:A),SUMIFS('PRODUTOS A PRODUZIR'!C:C,'PRODUTOS A PRODUZIR'!A:A,'Cadastro-Estoque'!A:A,'PRODUTOS A PRODUZIR'!B:B,CONCATENATE("<=",$A$2))) -> 0 | S60: =R60*F60 -> 0
A61: 076 | B61: FARINHA FRITZ E FRIDA 10 X 1 K | C61: 10 | D61: 1 | E61: 1.005 | F61: =C61*D61 -> 10 | G61: =C61*E61 -> 10.05 | I61: =IF(ISBLANK($A$2),SUMIFS(Entradas!C:C,Entradas!A:A,'Cadastro-Estoque'!A:A),SUMIFS(Entradas!C:C,Entradas!A:A,'Cadastro-Estoque'!A:A,Entradas!B:B,CONCATENATE("<=",$A$2))) -> 0 | J61: =I61*G61 -> 0 | L61: =IF(ISBLANK($A$2),SUMIFS(Saidas!C:C,Saidas!A:A,'Cadastro-Estoque'!A:A),SUMIFS(Saidas!C:C,Saidas!A:A,'Cadastro-Estoque'!A:A,Saidas!B:B,CONCATENATE("<=",$A$2))) -> 0 | M61: =L61*F61 -> 0 | O61: =IF(ISBLANK($A$2),SUMIFS(Faturado!C:C,Faturado!A:A,'Cadastro-Estoque'!A:A),SUMIFS(Faturado!C:C,Faturado!A:A,'Cadastro-Estoque'!A:A,Faturado!B:B,CONCATENATE("<=",$A$2))) -> 0 | P61: =O61*F61 -> 0 | R61: =IF(ISBLANK($A$2),SUMIFS('PRODUTOS A PRODUZIR'!C:C,'PRODUTOS A PRODUZIR'!A:A,'Cadastro-Estoque'!A:A),SUMIFS('PRODUTOS A PRODUZIR'!C:C,'PRODUTOS A PRODUZIR'!A:A,'Cadastro-Estoque'!A:A,'PRODUTOS A PRODUZIR'!B:B,CONCATENATE("<=",$A$2))) -> 0 | S61: =R61*F61 -> 0
F62: =C62*D62 -> 0 | G62: =C62*E62 -> 0 | I62: =IF(ISBLANK($A$2),SUMIFS(Entradas!C:C,Entradas!A:A,'Cadastro-Estoque'!A:A),SUMIFS(Entradas!C:C,Entradas!A:A,'Cadastro-Estoque'!A:A,Entradas!B:B,CONCATENATE("<=",$A$2))) -> 0 | J62: =I62*G62 -> 0 | L62: =IF(ISBLANK($A$2),SUMIFS(Saidas!C:C,Saidas!A:A,'Cadastro-Estoque'!A:A),SUMIFS(Saidas!C:C,Saidas!A:A,'Cadastro-Estoque'!A:A,Saidas!B:B,CONCATENATE("<=",$A$2))) -> 0 | M62: =L62*F62 -> 0 | O62: =IF(ISBLANK($A$2),SUMIFS(Faturado!C:C,Faturado!A:A,'Cadastro-Estoque'!A:A),SUMIFS(Faturado!C:C,Faturado!A:A,'Cadastro-Estoque'!A:A,Faturado!B:B,CONCATENATE("<=",$A$2))) -> 0 | P62: =O62*F62 -> 0 | R62: =IF(ISBLANK($A$2),SUMIFS('PRODUTOS A PRODUZIR'!C:C,'PRODUTOS A PRODUZIR'!A:A,'Cadastro-Estoque'!A:A),SUMIFS('PRODUTOS A PRODUZIR'!C:C,'PRODUTOS A PRODUZIR'!A:A,'Cadastro-Estoque'!A:A,'PRODUTOS A PRODUZIR'!B:B,CONCATENATE("<=",$A$2))) -> 0 | S62: =R62*F62 -> 0
A63: 066 | B63: FARINHA MÉDIA NUTRIVITA 12 X 1 K | C63: 12 | D63: 1 | E63: 1.005 | F63: =C63*D63 -> 12 | G63: =C63*E63 -> 12.06 | I63: =IF(ISBLANK($A$2),SUMIFS(Entradas!C:C,Entradas!A:A,'Cadastro-Estoque'!A:A),SUMIFS(Entradas!C:C,Entradas!A:A,'Cadastro-Estoque'!A:A,Entradas!B:B,CONCATENATE("<=",$A$2))) -> 0 | J63: =I63*G63 -> 0 | L63: =IF(ISBLANK($A$2),SUMIFS(Saidas!C:C,Saidas!A:A,'Cadastro-Estoque'!A:A),SUMIFS(Saidas!C:C,Saidas!A:A,'Cadastro-Estoque'!A:A,Saidas!B:B,CONCATENATE("<=",$A$2))) -> 0 | M63: =L63*F63 -> 0 | O63: =IF(ISBLANK($A$2),SUMIFS(Faturado!C:C,Faturado!A:A,'Cadastro-Estoque'!A:A),SUMIFS(Faturado!C:C,Faturado!A:A,'Cadastro-Estoque'!A:A,Faturado!B:B,CONCATENATE("<=",$A$2))) -> 0 | P63: =O63*F63 -> 0 | R63: =IF(ISBLANK($A$2),SUMIFS('PRODUTOS A PRODUZIR'!C:C,'PRODUTOS A PRODUZIR'!A:A,'Cadastro-Estoque'!A:A),SUMIFS('PRODUTOS A PRODUZIR'!C:C,'PRODUTOS A PRODUZIR'!A:A,'Cadastro-Estoque'!A:A,'PRODUTOS A PRODUZIR'!B:B,CONCATENATE("<=",$A$2))) -> 0 | S63: =R63*F63 -> 0
A64: 068 | B64: FARINHA MÉDIA PERDIZ 12 X 1 K | C64: 12 | D64: 1 | E64: 1.005 | F64: =C64*D64 -> 12 | G64: =C64*E64 -> 12.06 | I64: =IF(ISBLANK($A$2),SUMIFS(Entradas!C:C,Entradas!A:A,'Cadastro-Estoque'!A:A),SUMIFS(Entradas!C:C,Entradas!A:A,'Cadastro-Estoque'!A:A,Entradas!B:B,CONCATENATE("<=",$A$2))) -> 0 | J64: =I64*G64 -> 0 | L64: =IF(ISBLANK($A$2),SUMIFS(Saidas!C:C,Saidas!A:A,'Cadastro-Estoque'!A:A),SUMIFS(Saidas!C:C,Saidas!A:A,'Cadastro-Estoque'!A:A,Saidas!B:B,CONCATENATE("<=",$A$2))) -> 0 | M64: =L64*F64 -> 0 | O64: =IF(ISBLANK($A$2),SUMIFS(Faturado!C:C,Faturado!A:A,'Cadastro-Estoque'!A:A),SUMIFS(Faturado!C:C,Faturado!A:A,'Cadastro-Estoque'!A:A,Faturado!B:B,CONCATENATE("<=",$A$2))) -> 0 | P64: =O64*F64 -> 0 | R64: =IF(ISBLANK($A$2),SUMIFS('PRODUTOS A PRODUZIR'!C:C,'PRODUTOS A PRODUZIR'!A:A,'Cadastro-Estoque'!A:A),SUMIFS('PRODUTOS A PRODUZIR'!C:C,'PRODUTOS A PRODUZIR'!A:A,'Cadastro-Estoque'!A:A,'PRODUTOS A PRODUZIR'!B:B,CONCATENATE("<=",$A$2))) -> 0 | S64: =R64*F64 -> 0
A65: 068 | B65: FARINHA MÉDIA PERDIZ 12 X 500G | C65: 12 | D65: 0.5 | E65: 0.505 | F65: 6 | G65: =C65*E65 -> 6.06 | I65: =IF(ISBLANK($A$2),SUMIFS(Entradas!C:C,Entradas!A:A,'Cadastro-Estoque'!A:A),SUMIFS(Entradas!C:C,Entradas!A:A,'Cadastro-Estoque'!A:A,Entradas!B:B,CONCATENATE("<=",$A$2))) -> 0 | J65: =I65*G65 -> 0 | L65: =IF(ISBLANK($A$2),SUMIFS(Saidas!C:C,Saidas!A:A,'Cadastro-Estoque'!A:A),SUMIFS(Saidas!C:C,Saidas!A:A,'Cadastro-Estoque'!A:A,Saidas!B:B,CONCATENATE("<=",$A$2))) -> 0 | M65: =L65*F65 -> 0 | O65: =IF(ISBLANK($A$2),SUMIFS(Faturado!C:C,Faturado!A:A,'Cadastro-Estoque'!A:A),SUMIFS(Faturado!C:C,Faturado!A:A,'Cadastro-Estoque'!A:A,Faturado!B:B,CONCATENATE("<=",$A$2))) -> 0 | P65: =O65*F65 -> 0 | R65: =IF(ISBLANK($A$2),SUMIFS('PRODUTOS A PRODUZIR'!C:C,'PRODUTOS A PRODUZIR'!A:A,'Cadastro-Estoque'!A:A),SUMIFS('PRODUTOS A PRODUZIR'!C:C,'PRODUTOS A PRODUZIR'!A:A,'Cadastro-Estoque'!A:A,'PRODUTOS A PRODUZIR'!B:B,CONCATENATE("<=",$A$2))) -> 0 | S65: =R65*F65 -> 0
A66: 068 | B66: FARINHA MÉDIA PERDIZ 06 X 1 K | C66: 6 | D66: 1 | E66: 1.005 | F66: =C66*D66 -> 6 | G66: =C66*E66 -> 6.03 | I66: =IF(ISBLANK($A$2),SUMIFS(Entradas!C:C,Entradas!A:A,'Cadastro-Estoque'!A:A),SUMIFS(Entradas!C:C,Entradas!A:A,'Cadastro-Estoque'!A:A,Entradas!B:B,CONCATENATE("<=",$A$2))) -> 0 | J66: =I66*G66 -> 0 | L66: =IF(ISBLANK($A$2),SUMIFS(Saidas!C:C,Saidas!A:A,'Cadastro-Estoque'!A:A),SUMIFS(Saidas!C:C,Saidas!A:A,'Cadastro-Estoque'!A:A,Saidas!B:B,CONCATENATE("<=",$A$2))) -> 0 | M66: =L66*F66 -> 0 | O66: =IF(ISBLANK($A$2),SUMIFS(Faturado!C:C,Faturado!A:A,'Cadastro-Estoque'!A:A),SUMIFS(Faturado!C:C,Faturado!A:A,'Cadastro-Estoque'!A:A,Faturado!B:B,CONCATENATE("<=",$A$2))) -> 0 | P66: =O66*F66 -> 0 | R66: =IF(ISBLANK($A$2),SUMIFS('PRODUTOS A PRODUZIR'!C:C,'PRODUTOS A PRODUZIR'!A:A,'Cadastro-Estoque'!A:A),SUMIFS('PRODUTOS A PRODUZIR'!C:C,'PRODUTOS A PRODUZIR'!A:A,'Cadastro-Estoque'!A:A,'PRODUTOS A PRODUZIR'!B:B,CONCATENATE("<=",$A$2))) -> 0 | S66: =R66*F66 -> 0
A67: 073 | B67: FARINHA MÉDIA FRITZ E FRIDA 10 X 1 K | C67: 10 | D67: 1 | E67: 1.005 | F67: =C67*D67 -> 10 | G67: =C67*E67 -> 10.05 | I67: =IF(ISBLANK($A$2),SUMIFS(Entradas!C:C,Entradas!A:A,'Cadastro-Estoque'!A:A),SUMIFS(Entradas!C:C,Entradas!A:A,'Cadastro-Estoque'!A:A,Entradas!B:B,CONCATENATE("<=",$A$2))) -> 0 | J67: =I67*G67 -> 0 | L67: =IF(ISBLANK($A$2),SUMIFS(Saidas!C:C,Saidas!A:A,'Cadastro-Estoque'!A:A),SUMIFS(Saidas!C:C,Saidas!A:A,'Cadastro-Estoque'!A:A,Saidas!B:B,CONCATENATE("<=",$A$2))) -> 0 | M67: =L67*F67 -> 0 | O67: =IF(ISBLANK($A$2),SUMIFS(Faturado!C:C,Faturado!A:A,'Cadastro-Estoque'!A:A),SUMIFS(Faturado!C:C,Faturado!A:A,'Cadastro-Estoque'!A:A,Faturado!B:B,CONCATENATE("<=",$A$2))) -> 0 | P67: =O67*F67 -> 0 | R67: =IF(ISBLANK($A$2),SUMIFS('PRODUTOS A PRODUZIR'!C:C,'PRODUTOS A PRODUZIR'!A:A,'Cadastro-Estoque'!A:A),SUMIFS('PRODUTOS A PRODUZIR'!C:C,'PRODUTOS A PRODUZIR'!A:A,'Cadastro-Estoque'!A:A,'PRODUTOS A PRODUZIR'!B:B,CONCATENATE("<=",$A$2))) -> 0 | S67: =R67*F67 -> 0
F68: =C68*D68 -> 0 | G68: =C68*E68 -> 0 | I68: =IF(ISBLANK($A$2),SUMIFS(Entradas!C:C,Entradas!A:A,'Cadastro-Estoque'!A:A),SUMIFS(Entradas!C:C,Entradas!A:A,'Cadastro-Estoque'!A:A,Entradas!B:B,CONCATENATE("<=",$A$2))) -> 0 | J68: =I68*G68 -> 0 | L68: =IF(ISBLANK($A$2),SUMIFS(Saidas!C:C,Saidas!A:A,'Cadastro-Estoque'!A:A),SUMIFS(Saidas!C:C,Saidas!A:A,'Cadastro-Estoque'!A:A,Saidas!B:B,CONCATENATE("<=",$A$2))) -> 0 | M68: =L68*F68 -> 0 | O68: =IF(ISBLANK($A$2),SUMIFS(Faturado!C:C,Faturado!A:A,'Cadastro-Estoque'!A:A),SUMIFS(Faturado!C:C,Faturado!A:A,'Cadastro-Estoque'!A:A,Faturado!B:B,CONCATENATE("<=",$A$2))) -> 0 | P68: =O68*F68 -> 0 | R68: =IF(ISBLANK($A$2),SUMIFS('PRODUTOS A PRODUZIR'!C:C,'PRODUTOS A PRODUZIR'!A:A,'Cadastro-Estoque'!A:A),SUMIFS('PRODUTOS A PRODUZIR'!C:C,'PRODUTOS A PRODUZIR'!A:A,'Cadastro-Estoque'!A:A,'PRODUTOS A PRODUZIR'!B:B,CONCATENATE("<=",$A$2))) -> 0 | S68: =R68*F68 -> 0
A69: 067 | B69: FARINHA GROSSA NUTRIVITA 12 X 1 K | C69: 12 | D69: 1 | E69: 1.005 | F69: =C69*D69 -> 12 | G69: =C69*E69 -> 12.06 | I69: =IF(ISBLANK($A$2),SUMIFS(Entradas!C:C,Entradas!A:A,'Cadastro-Estoque'!A:A),SUMIFS(Entradas!C:C,Entradas!A:A,'Cadastro-Estoque'!A:A,Entradas!B:B,CONCATENATE("<=",$A$2))) -> 0 | J69: =I69*G69 -> 0 | L69: =IF(ISBLANK($A$2),SUMIFS(Saidas!C:C,Saidas!A:A,'Cadastro-Estoque'!A:A),SUMIFS(Saidas!C:C,Saidas!A:A,'Cadastro-Estoque'!A:A,Saidas!B:B,CONCATENATE("<=",$A$2))) -> 0 | M69: =L69*F69 -> 0 | O69: =IF(ISBLANK($A$2),SUMIFS(Faturado!C:C,Faturado!A:A,'Cadastro-Estoque'!A:A),SUMIFS(Faturado!C:C,Faturado!A:A,'Cadastro-Estoque'!A:A,Faturado!B:B,CONCATENATE("<=",$A$2))) -> 0 | P69: =O69*F69 -> 0 | R69: =IF(ISBLANK($A$2),SUMIFS('PRODUTOS A PRODUZIR'!C:C,'PRODUTOS A PRODUZIR'!A:A,'Cadastro-Estoque'!A:A),SUMIFS('PRODUTOS A PRODUZIR'!C:C,'PRODUTOS A PRODUZIR'!A:A,'Cadastro-Estoque'!A:A,'PRODUTOS A PRODUZIR'!B:B,CONCATENATE("<=",$A$2))) -> 0 | S69: =R69*F69 -> 0
A70: 069 | B70: FARINHA GROSSA PERDIZ 12 X 1 K | C70: 12 | D70: 1 | E70: 1.005 | F70: =C70*D70 -> 12 | G70: =C70*E70 -> 12.06 | I70: =IF(ISBLANK($A$2),SUMIFS(Entradas!C:C,Entradas!A:A,'Cadastro-Estoque'!A:A),SUMIFS(Entradas!C:C,Entradas!A:A,'Cadastro-Estoque'!A:A,Entradas!B:B,CONCATENATE("<=",$A$2))) -> 0 | J70: =I70*G70 -> 0 | L70: =IF(ISBLANK($A$2),SUMIFS(Saidas!C:C,Saidas!A:A,'Cadastro-Estoque'!A:A),SUMIFS(Saidas!C:C,Saidas!A:A,'Cadastro-Estoque'!A:A,Saidas!B:B,CONCATENATE("<=",$A$2))) -> 0 | M70: =L70*F70 -> 0 | O70: =IF(ISBLANK($A$2),SUMIFS(Faturado!C:C,Faturado!A:A,'Cadastro-Estoque'!A:A),SUMIFS(Faturado!C:C,Faturado!A:A,'Cadastro-Estoque'!A:A,Faturado!B:B,CONCATENATE("<=",$A$2))) -> 0 | P70: =O70*F70 -> 0 | R70: =IF(ISBLANK($A$2),SUMIFS('PRODUTOS A PRODUZIR'!C:C,'PRODUTOS A PRODUZIR'!A:A,'Cadastro-Estoque'!A:A),SUMIFS('PRODUTOS A PRODUZIR'!C:C,'PRODUTOS A PRODUZIR'!A:A,'Cadastro-Estoque'!A:A,'PRODUTOS A PRODUZIR'!B:B,CONCATENATE("<=",$A$2))) -> 0 | S70: =R70*F70 -> 0
A71: 069 | B71: FARINHA GROSSA PERDIZ 06 X 1 K | C71: 6 | D71: 1 | E71: 1.005 | F71: =C71*D71 -> 6 | G71: =C71*E71 -> 6.03 | I71: =IF(ISBLANK($A$2),SUMIFS(Entradas!C:C,Entradas!A:A,'Cadastro-Estoque'!A:A),SUMIFS(Entradas!C:C,Entradas!A:A,'Cadastro-Estoque'!A:A,Entradas!B:B,CONCATENATE("<=",$A$2))) -> 0 | J71: =I71*G71 -> 0 | L71: =IF(ISBLANK($A$2),SUMIFS(Saidas!C:C,Saidas!A:A,'Cadastro-Estoque'!A:A),SUMIFS(Saidas!C:C,Saidas!A:A,'Cadastro-Estoque'!A:A,Saidas!B:B,CONCATENATE("<=",$A$2))) -> 0 | M71: =L71*F71 -> 0 | O71: =IF(ISBLANK($A$2),SUMIFS(Faturado!C:C,Faturado!A:A,'Cadastro-Estoque'!A:A),SUMIFS(Faturado!C:C,Faturado!A:A,'Cadastro-Estoque'!A:A,Faturado!B:B,CONCATENATE("<=",$A$2))) -> 0 | P71: =O71*F71 -> 0 | R71: =IF(ISBLANK($A$2),SUMIFS('PRODUTOS A PRODUZIR'!C:C,'PRODUTOS A PRODUZIR'!A:A,'Cadastro-Estoque'!A:A),SUMIFS('PRODUTOS A PRODUZIR'!C:C,'PRODUTOS A PRODUZIR'!A:A,'Cadastro-Estoque'!A:A,'PRODUTOS A PRODUZIR'!B:B,CONCATENATE("<=",$A$2))) -> 0 | S71: =R71*F71 -> 0
A72: 074 | B72: FARINHA GROSSA FRITZ E FRIDA 10 X 1 K | C72: 10 | D72: 1 | E72: 1.005 | F72: =C72*D72 -> 10 | G72: =C72*E72 -> 10.05 | I72: =IF(ISBLANK($A$2),SUMIFS(Entradas!C:C,Entradas!A:A,'Cadastro-Estoque'!A:A),SUMIFS(Entradas!C:C,Entradas!A:A,'Cadastro-Estoque'!A:A,Entradas!B:B,CONCATENATE("<=",$A$2))) -> 0 | J72: =I72*G72 -> 0 | L72: =IF(ISBLANK($A$2),SUMIFS(Saidas!C:C,Saidas!A:A,'Cadastro-Estoque'!A:A),SUMIFS(Saidas!C:C,Saidas!A:A,'Cadastro-Estoque'!A:A,Saidas!B:B,CONCATENATE("<=",$A$2))) -> 0 | M72: =L72*F72 -> 0 | O72: =IF(ISBLANK($A$2),SUMIFS(Faturado!C:C,Faturado!A:A,'Cadastro-Estoque'!A:A),SUMIFS(Faturado!C:C,Faturado!A:A,'Cadastro-Estoque'!A:A,Faturado!B:B,CONCATENATE("<=",$A$2))) -> 0 | P72: =O72*F72 -> 0 | R72: =IF(ISBLANK($A$2),SUMIFS('PRODUTOS A PRODUZIR'!C:C,'PRODUTOS A PRODUZIR'!A:A,'Cadastro-Estoque'!A:A),SUMIFS('PRODUTOS A PRODUZIR'!C:C,'PRODUTOS A PRODUZIR'!A:A,'Cadastro-Estoque'!A:A,'PRODUTOS A PRODUZIR'!B:B,CONCATENATE("<=",$A$2))) -> 0 | S72: =R72*F72 -> 0
F73: =C73*D73 -> 0 | G73: =C73*E73 -> 0 | I73: =IF(ISBLANK($A$2),SUMIFS(Entradas!C:C,Entradas!A:A,'Cadastro-Estoque'!A:A),SUMIFS(Entradas!C:C,Entradas!A:A,'Cadastro-Estoque'!A:A,Entradas!B:B,CONCATENATE("<=",$A$2))) -> 0 | J73: =I73*G73 -> 0 | L73: =IF(ISBLANK($A$2),SUMIFS(Saidas!C:C,Saidas!A:A,'Cadastro-Estoque'!A:A),SUMIFS(Saidas!C:C,Saidas!A:A,'Cadastro-Estoque'!A:A,Saidas!B:B,CONCATENATE("<=",$A$2))) -> 0 | M73: =L73*F73 -> 0 | O73: =IF(ISBLANK($A$2),SUMIFS(Faturado!C:C,Faturado!A:A,'Cadastro-Estoque'!A:A),SUMIFS(Faturado!C:C,Faturado!A:A,'Cadastro-Estoque'!A:A,Faturado!B:B,CONCATENATE("<=",$A$2))) -> 0 | P73: =O73*F73 -> 0 | R73: =IF(ISBLANK($A$2),SUMIFS('PRODUTOS A PRODUZIR'!C:C,'PRODUTOS A PRODUZIR'!A:A,'Cadastro-Estoque'!A:A),SUMIFS('PRODUTOS A PRODUZIR'!C:C,'PRODUTOS A PRODUZIR'!A:A,'Cadastro-Estoque'!A:A,'PRODUTOS A PRODUZIR'!B:B,CONCATENATE("<=",$A$2))) -> 0 | S73: =R73*F73 -> 0
A74: 003 | B74: CANJICA MUNGUZÁ 20 X 500 | C74: 20 | D74: 0.5 | E74: 0.505 | F74: =C74*D74 -> 10 | G74: =C74*E74 -> 10.1 | I74: =IF(ISBLANK($A$2),SUMIFS(Entradas!C:C,Entradas!A:A,'Cadastro-Estoque'!A:A),SUMIFS(Entradas!C:C,Entradas!A:A,'Cadastro-Estoque'!A:A,Entradas!B:B,CONCATENATE("<=",$A$2))) -> 0 | J74: =I74*G74 -> 0 | L74: =IF(ISBLANK($A$2),SUMIFS(Saidas!C:C,Saidas!A:A,'Cadastro-Estoque'!A:A),SUMIFS(Saidas!C:C,Saidas!A:A,'Cadastro-Estoque'!A:A,Saidas!B:B,CONCATENATE("<=",$A$2))) -> 0 | M74: =L74*F74 -> 0 | O74: =IF(ISBLANK($A$2),SUMIFS(Faturado!C:C,Faturado!A:A,'Cadastro-Estoque'!A:A),SUMIFS(Faturado!C:C,Faturado!A:A,'Cadastro-Estoque'!A:A,Faturado!B:B,CONCATENATE("<=",$A$2))) -> 0 | P74: =O74*F74 -> 0 | R74: =IF(ISBLANK($A$2),SUMIFS('PRODUTOS A PRODUZIR'!C:C,'PRODUTOS A PRODUZIR'!A:A,'Cadastro-Estoque'!A:A),SUMIFS('PRODUTOS A PRODUZIR'!C:C,'PRODUTOS A PRODUZIR'!A:A,'Cadastro-Estoque'!A:A,'PRODUTOS A PRODUZIR'!B:B,CONCATENATE("<=",$A$2))) -> 0 | S74: =R74*F74 -> 0
A75: 024 | B75: CANJICA XERÉM 20 X 500 | C75: 20 | D75: 0.5 | E75: 0.505 | F75: =C75*D75 -> 10 | G75: =C75*E75 -> 10.1 | I75: =IF(ISBLANK($A$2),SUMIFS(Entradas!C:C,Entradas!A:A,'Cadastro-Estoque'!A:A),SUMIFS(Entradas!C:C,Entradas!A:A,'Cadastro-Estoque'!A:A,Entradas!B:B,CONCATENATE("<=",$A$2))) -> 0 | J75: =I75*G75 -> 0 | L75: =IF(ISBLANK($A$2),SUMIFS(Saidas!C:C,Saidas!A:A,'Cadastro-Estoque'!A:A),SUMIFS(Saidas!C:C,Saidas!A:A,'Cadastro-Estoque'!A:A,Saidas!B:B,CONCATENATE("<=",$A$2))) -> 0 | M75: =L75*F75 -> 0 | O75: =IF(ISBLANK($A$2),SUMIFS(Faturado!C:C,Faturado!A:A,'Cadastro-Estoque'!A:A),SUMIFS(Faturado!C:C,Faturado!A:A,'Cadastro-Estoque'!A:A,Faturado!B:B,CONCATENATE("<=",$A$2))) -> 0 | P75: =O75*F75 -> 0 | R75: =IF(ISBLANK($A$2),SUMIFS('PRODUTOS A PRODUZIR'!C:C,'PRODUTOS A PRODUZIR'!A:A,'Cadastro-Estoque'!A:A),SUMIFS('PRODUTOS A PRODUZIR'!C:C,'PRODUTOS A PRODUZIR'!A:A,'Cadastro-Estoque'!A:A,'PRODUTOS A PRODUZIR'!B:B,CONCATENATE("<=",$A$2))) -> 0 | S75: =R75*F75 -> 0
A76: 051 | B76: PIPOCA NUTRIVITA 20 X 500 | C76: 20 | D76: 0.5 | E76: 0.505 | F76: =C76*D76 -> 10 | G76: =C76*E76 -> 10.1 | I76: =IF(ISBLANK($A$2),SUMIFS(Entradas!C:C,Entradas!A:A,'Cadastro-Estoque'!A:A),SUMIFS(Entradas!C:C,Entradas!A:A,'Cadastro-Estoque'!A:A,Entradas!B:B,CONCATENATE("<=",$A$2))) -> 0 | J76: =I76*G76 -> 0 | L76: =IF(ISBLANK($A$2),SUMIFS(Saidas!C:C,Saidas!A:A,'Cadastro-Estoque'!A:A),SUMIFS(Saidas!C:C,Saidas!A:A,'Cadastro-Estoque'!A:A,Saidas!B:B,CONCATENATE("<=",$A$2))) -> 0 | M76: =L76*F76 -> 0 | O76: =IF(ISBLANK($A$2),SUMIFS(Faturado!C:C,Faturado!A:A,'Cadastro-Estoque'!A:A),SUMIFS(Faturado!C:C,Faturado!A:A,'Cadastro-Estoque'!A:A,Faturado!B:B,CONCATENATE("<=",$A$2))) -> 0 | P76: =O76*F76 -> 0 | R76: =IF(ISBLANK($A$2),SUMIFS('PRODUTOS A PRODUZIR'!C:C,'PRODUTOS A PRODUZIR'!A:A,'Cadastro-Estoque'!A:A),SUMIFS('PRODUTOS A PRODUZIR'!C:C,'PRODUTOS A PRODUZIR'!A:A,'Cadastro-Estoque'!A:A,'PRODUTOS A PRODUZIR'!B:B,CONCATENATE("<=",$A$2))) -> 0 | S76: =R76*F76 -> 0
A77: 096 | B77: CANJICA XERÉM M & K 12 X 500 | C77: 12 | D77: 0.5 | E77: 0.505 | F77: =C77*D77 -> 6 | G77: =C77*E77 -> 6.06 | I77: =IF(ISBLANK($A$2),SUMIFS(Entradas!C:C,Entradas!A:A,'Cadastro-Estoque'!A:A),SUMIFS(Entradas!C:C,Entradas!A:A,'Cadastro-Estoque'!A:A,Entradas!B:B,CONCATENATE("<=",$A$2))) -> 0 | J77: =I77*G77 -> 0 | L77: =IF(ISBLANK($A$2),SUMIFS(Saidas!C:C,Saidas!A:A,'Cadastro-Estoque'!A:A),SUMIFS(Saidas!C:C,Saidas!A:A,'Cadastro-Estoque'!A:A,Saidas!B:B,CONCATENATE("<=",$A$2))) -> 0 | M77: =L77*F77 -> 0 | O77: =IF(ISBLANK($A$2),SUMIFS(Faturado!C:C,Faturado!A:A,'Cadastro-Estoque'!A:A),SUMIFS(Faturado!C:C,Faturado!A:A,'Cadastro-Estoque'!A:A,Faturado!B:B,CONCATENATE("<=",$A$2))) -> 0 | P77: =O77*F77 -> 0 | R77: =IF(ISBLANK($A$2),SUMIFS('PRODUTOS A PRODUZIR'!C:C,'PRODUTOS A PRODUZIR'!A:A,'Cadastro-Estoque'!A:A),SUMIFS('PRODUTOS A PRODUZIR'!C:C,'PRODUTOS A PRODUZIR'!A:A,'Cadastro-Estoque'!A:A,'PRODUTOS A PRODUZIR'!B:B,CONCATENATE("<=",$A$2))) -> 0 | S77: =R77*F77 -> 0
A78: 082 | B78: CANJICA MUNGUZÁ KISABOR 12X400 | C78: 12 | D78: 0.4 | E78: 0.405 | F78: 4.8 | G78: =C78*E78 -> 4.86 | I78: =IF(ISBLANK($A$2),SUMIFS(Entradas!C:C,Entradas!A:A,'Cadastro-Estoque'!A:A),SUMIFS(Entradas!C:C,Entradas!A:A,'Cadastro-Estoque'!A:A,Entradas!B:B,CONCATENATE("<=",$A$2))) -> 0 | J78: =I78*G78 -> 0 | L78: =IF(ISBLANK($A$2),SUMIFS(Saidas!C:C,Saidas!A:A,'Cadastro-Estoque'!A:A),SUMIFS(Saidas!C:C,Saidas!A:A,'Cadastro-Estoque'!A:A,Saidas!B:B,CONCATENATE("<=",$A$2))) -> 0 | M78: =L78*F78 -> 0 | O78: =IF(ISBLANK($A$2),SUMIFS(Faturado!C:C,Faturado!A:A,'Cadastro-Estoque'!A:A),SUMIFS(Faturado!C:C,Faturado!A:A,'Cadastro-Estoque'!A:A,Faturado!B:B,CONCATENATE("<=",$A$2))) -> 0 | P78: =O78*F78 -> 0 | R78: =IF(ISBLANK($A$2),SUMIFS('PRODUTOS A PRODUZIR'!C:C,'PRODUTOS A PRODUZIR'!A:A,'Cadastro-Estoque'!A:A),SUMIFS('PRODUTOS A PRODUZIR'!C:C,'PRODUTOS A PRODUZIR'!A:A,'Cadastro-Estoque'!A:A,'PRODUTOS A PRODUZIR'!B:B,CONCATENATE("<=",$A$2))) -> 0 | S78: =R78*F78 -> 0
A79: 083 | B79: CANJICA XERÉM KISABOR 12X400 | C79: 12 | D79: 0.4 | E79: 0.405 | F79: 4.8 | G79: =C79*E79 -> 4.86 | I79: =IF(ISBLANK($A$2),SUMIFS(Entradas!C:C,Entradas!A:A,'Cadastro-Estoque'!A:A),SUMIFS(Entradas!C:C,Entradas!A:A,'Cadastro-Estoque'!A:A,Entradas!B:B,CONCATENATE("<=",$A$2))) -> 0 | J79: =I79*G79 -> 0 | L79: =IF(ISBLANK($A$2),SUMIFS(Saidas!C:C,Saidas!A:A,'Cadastro-Estoque'!A:A),SUMIFS(Saidas!C:C,Saidas!A:A,'Cadastro-Estoque'!A:A,Saidas!B:B,CONCATENATE("<=",$A$2))) -> 0 | M79: =L79*F79 -> 0 | O79: =IF(ISBLANK($A$2),SUMIFS(Faturado!C:C,Faturado!A:A,'Cadastro-Estoque'!A:A),SUMIFS(Faturado!C:C,Faturado!A:A,'Cadastro-Estoque'!A:A,Faturado!B:B,CONCATENATE("<=",$A$2))) -> 0 | P79: =O79*F79 -> 0 | R79: =IF(ISBLANK($A$2),SUMIFS('PRODUTOS A PRODUZIR'!C:C,'PRODUTOS A PRODUZIR'!A:A,'Cadastro-Estoque'!A:A),SUMIFS('PRODUTOS A PRODUZIR'!C:C,'PRODUTOS A PRODUZIR'!A:A,'Cadastro-Estoque'!A:A,'PRODUTOS A PRODUZIR'!B:B,CONCATENATE("<=",$A$2))) -> 0 | S79: =R79*F79 -> 0
I80: =IF(ISBLANK($A$2),SUMIFS(Entradas!C:C,Entradas!A:A,'Cadastro-Estoque'!A:A),SUMIFS(Entradas!C:C,Entradas!A:A,'Cadastro-Estoque'!A:A,Entradas!B:B,CONCATENATE("<=",$A$2))) -> 0 | J80: =I80*G80 -> 0 | L80: =IF(ISBLANK($A$2),SUMIFS(Saidas!C:C,Saidas!A:A,'Cadastro-Estoque'!A:A),SUMIFS(Saidas!C:C,Saidas!A:A,'Cadastro-Estoque'!A:A,Saidas!B:B,CONCATENATE("<=",$A$2))) -> 0 | M80: =L80*F80 -> 0 | O80: =IF(ISBLANK($A$2),SUMIFS(Faturado!C:C,Faturado!A:A,'Cadastro-Estoque'!A:A),SUMIFS(Faturado!C:C,Faturado!A:A,'Cadastro-Estoque'!A:A,Faturado!B:B,CONCATENATE("<=",$A$2))) -> 0 | P80: =O80*F80 -> 0 | R80: =IF(ISBLANK($A$2),SUMIFS('PRODUTOS A PRODUZIR'!C:C,'PRODUTOS A PRODUZIR'!A:A,'Cadastro-Estoque'!A:A),SUMIFS('PRODUTOS A PRODUZIR'!C:C,'PRODUTOS A PRODUZIR'!A:A,'Cadastro-Estoque'!A:A,'PRODUTOS A PRODUZIR'!B:B,CONCATENATE("<=",$A$2))) -> 0 | S80: =R80*F80 -> 0
A81: 014 | B81: COLORÍFICO NUTRIVITA 10 X 100 G | C81: 10 | D81: 0.1 | E81: 0.102 | F81: =C81*D81 -> 1 | G81: =C81*E81 -> 1.02 | I81: =IF(ISBLANK($A$2),SUMIFS(Entradas!C:C,Entradas!A:A,'Cadastro-Estoque'!A:A),SUMIFS(Entradas!C:C,Entradas!A:A,'Cadastro-Estoque'!A:A,Entradas!B:B,CONCATENATE("<=",$A$2))) -> 0 | J81: =I81*G81 -> 0 | L81: =IF(ISBLANK($A$2),SUMIFS(Saidas!C:C,Saidas!A:A,'Cadastro-Estoque'!A:A),SUMIFS(Saidas!C:C,Saidas!A:A,'Cadastro-Estoque'!A:A,Saidas!B:B,CONCATENATE("<=",$A$2))) -> 0 | M81: =L81*F81 -> 0 | O81: =IF(ISBLANK($A$2),SUMIFS(Faturado!C:C,Faturado!A:A,'Cadastro-Estoque'!A:A),SUMIFS(Faturado!C:C,Faturado!A:A,'Cadastro-Estoque'!A:A,Faturado!B:B,CONCATENATE("<=",$A$2))) -> 0 | P81: =O81*F81 -> 0 | R81: =IF(ISBLANK($A$2),SUMIFS('PRODUTOS A PRODUZIR'!C:C,'PRODUTOS A PRODUZIR'!A:A,'Cadastro-Estoque'!A:A),SUMIFS('PRODUTOS A PRODUZIR'!C:C,'PRODUTOS A PRODUZIR'!A:A,'Cadastro-Estoque'!A:A,'PRODUTOS A PRODUZIR'!B:B,CONCATENATE("<=",$A$2))) -> 0 | S81: =R81*F81 -> 0
A82: 014 | B82: COLORÍFICO NUTRIVITA 100 X 100 G | C82: 100 | D82: 0.1 | E82: 0.102 | F82: =C82*D82 -> 10 | G82: =C82*E82 -> 10.2 | I82: =IF(ISBLANK($A$2),SUMIFS(Entradas!C:C,Entradas!A:A,'Cadastro-Estoque'!A:A),SUMIFS(Entradas!C:C,Entradas!A:A,'Cadastro-Estoque'!A:A,Entradas!B:B,CONCATENATE("<=",$A$2))) -> 0 | J82: =I82*G82 -> 0 | L82: =IF(ISBLANK($A$2),SUMIFS(Saidas!C:C,Saidas!A:A,'Cadastro-Estoque'!A:A),SUMIFS(Saidas!C:C,Saidas!A:A,'Cadastro-Estoque'!A:A,Saidas!B:B,CONCATENATE("<=",$A$2))) -> 0 | M82: =L82*F82 -> 0 | O82: =IF(ISBLANK($A$2),SUMIFS(Faturado!C:C,Faturado!A:A,'Cadastro-Estoque'!A:A),SUMIFS(Faturado!C:C,Faturado!A:A,'Cadastro-Estoque'!A:A,Faturado!B:B,CONCATENATE("<=",$A$2))) -> 0 | P82: =O82*F82 -> 0 | R82: =IF(ISBLANK($A$2),SUMIFS('PRODUTOS A PRODUZIR'!C:C,'PRODUTOS A PRODUZIR'!A:A,'Cadastro-Estoque'!A:A),SUMIFS('PRODUTOS A PRODUZIR'!C:C,'PRODUTOS A PRODUZIR'!A:A,'Cadastro-Estoque'!A:A,'PRODUTOS A PRODUZIR'!B:B,CONCATENATE("<=",$A$2))) -> 0 | S82: =R82*F82 -> 0
A83: 014 | B83: COLORÍFICO NUTRIVITA 20 X 500 G | C83: 20 | D83: 0.5 | E83: 0.505 | F83: =C83*D83 -> 10 | G83: =C83*E83 -> 10.1 | I83: =IF(ISBLANK($A$2),SUMIFS(Entradas!C:C,Entradas!A:A,'Cadastro-Estoque'!A:A),SUMIFS(Entradas!C:C,Entradas!A:A,'Cadastro-Estoque'!A:A,Entradas!B:B,CONCATENATE("<=",$A$2))) -> 0 | J83: =I83*G83 -> 0 | L83: =IF(ISBLANK($A$2),SUMIFS(Saidas!C:C,Saidas!A:A,'Cadastro-Estoque'!A:A),SUMIFS(Saidas!C:C,Saidas!A:A,'Cadastro-Estoque'!A:A,Saidas!B:B,CONCATENATE("<=",$A$2))) -> 0 | M83: =L83*F83 -> 0 | O83: =IF(ISBLANK($A$2),SUMIFS(Faturado!C:C,Faturado!A:A,'Cadastro-Estoque'!A:A),SUMIFS(Faturado!C:C,Faturado!A:A,'Cadastro-Estoque'!A:A,Faturado!B:B,CONCATENATE("<=",$A$2))) -> 0 | P83: =O83*F83 -> 0 | R83: =IF(ISBLANK($A$2),SUMIFS('PRODUTOS A PRODUZIR'!C:C,'PRODUTOS A PRODUZIR'!A:A,'Cadastro-Estoque'!A:A),SUMIFS('PRODUTOS A PRODUZIR'!C:C,'PRODUTOS A PRODUZIR'!A:A,'Cadastro-Estoque'!A:A,'PRODUTOS A PRODUZIR'!B:B,CONCATENATE("<=",$A$2))) -> 0 | S83: =R83*F83 -> 0
A84: 077 | B84: COLORÍFICO BEATRIZ 100 X 100 G | C84: 100 | D84: 0.1 | E84: 0.102 | F84: =C84*D84 -> 10 | G84: =C84*E84 -> 10.2 | I84: =IF(ISBLANK($A$2),SUMIFS(Entradas!C:C,Entradas!A:A,'Cadastro-Estoque'!A:A),SUMIFS(Entradas!C:C,Entradas!A:A,'Cadastro-Estoque'!A:A,Entradas!B:B,CONCATENATE("<=",$A$2))) -> 0 | J84: =I84*G84 -> 0 | L84: =IF(ISBLANK($A$2),SUMIFS(Saidas!C:C,Saidas!A:A,'Cadastro-Estoque'!A:A),SUMIFS(Saidas!C:C,Saidas!A:A,'Cadastro-Estoque'!A:A,Saidas!B:B,CONCATENATE("<=",$A$2))) -> 0 | M84: =L84*F84 -> 0 | O84: =IF(ISBLANK($A$2),SUMIFS(Faturado!C:C,Faturado!A:A,'Cadastro-Estoque'!A:A),SUMIFS(Faturado!C:C,Faturado!A:A,'Cadastro-Estoque'!A:A,Faturado!B:B,CONCATENATE("<=",$A$2))) -> 0 | P84: =O84*F84 -> 0 | R84: =IF(ISBLANK($A$2),SUMIFS('PRODUTOS A PRODUZIR'!C:C,'PRODUTOS A PRODUZIR'!A:A,'Cadastro-Estoque'!A:A),SUMIFS('PRODUTOS A PRODUZIR'!C:C,'PRODUTOS A PRODUZIR'!A:A,'Cadastro-Estoque'!A:A,'PRODUTOS A PRODUZIR'!B:B,CONCATENATE("<=",$A$2))) -> 0 | S84: =R84*F84 -> 0
A85: 097 | B85: COLORÍFICO FRITZ E FRIDA 105X100 G | C85: 105 | D85: 0.1 | E85: 0.102 | F85: =C85*D85 -> 10.5 | G85: =C85*E85 -> 10.71 | I85: =IF(ISBLANK($A$2),SUMIFS(Entradas!C:C,Entradas!A:A,'Cadastro-Estoque'!A:A),SUMIFS(Entradas!C:C,Entradas!A:A,'Cadastro-Estoque'!A:A,Entradas!B:B,CONCATENATE("<=",$A$2))) -> 0 | J85: =I85*G85 -> 0 | L85: =IF(ISBLANK($A$2),SUMIFS(Saidas!C:C,Saidas!A:A,'Cadastro-Estoque'!A:A),SUMIFS(Saidas!C:C,Saidas!A:A,'Cadastro-Estoque'!A:A,Saidas!B:B,CONCATENATE("<=",$A$2))) -> 0 | M85: =L85*F85 -> 0 | O85: =IF(ISBLANK($A$2),SUMIFS(Faturado!C:C,Faturado!A:A,'Cadastro-Estoque'!A:A),SUMIFS(Faturado!C:C,Faturado!A:A,'Cadastro-Estoque'!A:A,Faturado!B:B,CONCATENATE("<=",$A$2))) -> 0 | P85: =O85*F85 -> 0 | R85: =IF(ISBLANK($A$2),SUMIFS('PRODUTOS A PRODUZIR'!C:C,'PRODUTOS A PRODUZIR'!A:A,'Cadastro-Estoque'!A:A),SUMIFS('PRODUTOS A PRODUZIR'!C:C,'PRODUTOS A PRODUZIR'!A:A,'Cadastro-Estoque'!A:A,'PRODUTOS A PRODUZIR'!B:B,CONCATENATE("<=",$A$2))) -> 144 | S85: =R85*F85 -> 1512
F86: =C86*D86 -> 0 | G86: =C86*E86 -> 0 | I86: =IF(ISBLANK($A$2),SUMIFS(Entradas!C:C,Entradas!A:A,'Cadastro-Estoque'!A:A),SUMIFS(Entradas!C:C,Entradas!A:A,'Cadastro-Estoque'!A:A,Entradas!B:B,CONCATENATE("<=",$A$2))) -> 0 | J86: =I86*G86 -> 0 | L86: =IF(ISBLANK($A$2),SUMIFS(Saidas!C:C,Saidas!A:A,'Cadastro-Estoque'!A:A),SUMIFS(Saidas!C:C,Saidas!A:A,'Cadastro-Estoque'!A:A,Saidas!B:B,CONCATENATE("<=",$A$2))) -> 0 | M86: =L86*F86 -> 0 | O86: =IF(ISBLANK($A$2),SUMIFS(Faturado!C:C,Faturado!A:A,'Cadastro-Estoque'!A:A),SUMIFS(Faturado!C:C,Faturado!A:A,'Cadastro-Estoque'!A:A,Faturado!B:B,CONCATENATE("<=",$A$2))) -> 0 | P86: =O86*F86 -> 0 | R86: =IF(ISBLANK($A$2),SUMIFS('PRODUTOS A PRODUZIR'!C:C,'PRODUTOS A PRODUZIR'!A:A,'Cadastro-Estoque'!A:A),SUMIFS('PRODUTOS A PRODUZIR'!C:C,'PRODUTOS A PRODUZIR'!A:A,'Cadastro-Estoque'!A:A,'PRODUTOS A PRODUZIR'!B:B,CONCATENATE("<=",$A$2))) -> 0 | S86: =R86*F86 -> 0
A87: 027 | B87: AMIDO NUTRIVITA 12 X 200 | C87: 12 | D87: 0.2 | E87: 0.204 | F87: =C87*D87 -> 2.4 | G87: =C87*E87 -> 2.448 | I87: =IF(ISBLANK($A$2),SUMIFS(Entradas!C:C,Entradas!A:A,'Cadastro-Estoque'!A:A),SUMIFS(Entradas!C:C,Entradas!A:A,'Cadastro-Estoque'!A:A,Entradas!B:B,CONCATENATE("<=",$A$2))) -> 40 | J87: =I87*G87 -> 97.92 | L87: =IF(ISBLANK($A$2),SUMIFS(Saidas!C:C,Saidas!A:A,'Cadastro-Estoque'!A:A),SUMIFS(Saidas!C:C,Saidas!A:A,'Cadastro-Estoque'!A:A,Saidas!B:B,CONCATENATE("<=",$A$2))) -> 0 | M87: =L87*F87 -> 0 | O87: =IF(ISBLANK($A$2),SUMIFS(Faturado!C:C,Faturado!A:A,'Cadastro-Estoque'!A:A),SUMIFS(Faturado!C:C,Faturado!A:A,'Cadastro-Estoque'!A:A,Faturado!B:B,CONCATENATE("<=",$A$2))) -> 0 | P87: =O87*F87 -> 0 | R87: =IF(ISBLANK($A$2),SUMIFS('PRODUTOS A PRODUZIR'!C:C,'PRODUTOS A PRODUZIR'!A:A,'Cadastro-Estoque'!A:A),SUMIFS('PRODUTOS A PRODUZIR'!C:C,'PRODUTOS A PRODUZIR'!A:A,'Cadastro-Estoque'!A:A,'PRODUTOS A PRODUZIR'!B:B,CONCATENATE("<=",$A$2))) -> 0 | S87: =R87*F87 -> 0
A88: 027 | B88: AMIDO NUTRIVITA 50 X 200 | C88: 50 | D88: 0.2 | E88: 0.204 | F88: =C88*D88 -> 10 | G88: =C88*E88 -> 10.2 | I88: =IF(ISBLANK($A$2),SUMIFS(Entradas!C:C,Entradas!A:A,'Cadastro-Estoque'!A:A),SUMIFS(Entradas!C:C,Entradas!A:A,'Cadastro-Estoque'!A:A,Entradas!B:B,CONCATENATE("<=",$A$2))) -> 0 | J88: =I88*G88 -> 0 | L88: =IF(ISBLANK($A$2),SUMIFS(Saidas!C:C,Saidas!A:A,'Cadastro-Estoque'!A:A),SUMIFS(Saidas!C:C,Saidas!A:A,'Cadastro-Estoque'!A:A,Saidas!B:B,CONCATENATE("<=",$A$2))) -> 0 | M88: =L88*F88 -> 0 | O88: =IF(ISBLANK($A$2),SUMIFS(Faturado!C:C,Faturado!A:A,'Cadastro-Estoque'!A:A),SUMIFS(Faturado!C:C,Faturado!A:A,'Cadastro-Estoque'!A:A,Faturado!B:B,CONCATENATE("<=",$A$2))) -> 0 | P88: =O88*F88 -> 0 | R88: =IF(ISBLANK($A$2),SUMIFS('PRODUTOS A PRODUZIR'!C:C,'PRODUTOS A PRODUZIR'!A:A,'Cadastro-Estoque'!A:A),SUMIFS('PRODUTOS A PRODUZIR'!C:C,'PRODUTOS A PRODUZIR'!A:A,'Cadastro-Estoque'!A:A,'PRODUTOS A PRODUZIR'!B:B,CONCATENATE("<=",$A$2))) -> 0 | S88: =R88*F88 -> 0
A89: 027 | B89: AMIDO NUTRIVITA 12 X 500 | C89: 12 | D89: 0.5 | E89: 0.509 | F89: =C89*D89 -> 6 | G89: =C89*E89 -> 6.108 | I89: =IF(ISBLANK($A$2),SUMIFS(Entradas!C:C,Entradas!A:A,'Cadastro-Estoque'!A:A),SUMIFS(Entradas!C:C,Entradas!A:A,'Cadastro-Estoque'!A:A,Entradas!B:B,CONCATENATE("<=",$A$2))) -> 0 | J89: =I89*G89 -> 0 | L89: =IF(ISBLANK($A$2),SUMIFS(Saidas!C:C,Saidas!A:A,'Cadastro-Estoque'!A:A),SUMIFS(Saidas!C:C,Saidas!A:A,'Cadastro-Estoque'!A:A,Saidas!B:B,CONCATENATE("<=",$A$2))) -> 0 | M89: =L89*F89 -> 0 | O89: =IF(ISBLANK($A$2),SUMIFS(Faturado!C:C,Faturado!A:A,'Cadastro-Estoque'!A:A),SUMIFS(Faturado!C:C,Faturado!A:A,'Cadastro-Estoque'!A:A,Faturado!B:B,CONCATENATE("<=",$A$2))) -> 0 | P89: =O89*F89 -> 0 | R89: =IF(ISBLANK($A$2),SUMIFS('PRODUTOS A PRODUZIR'!C:C,'PRODUTOS A PRODUZIR'!A:A,'Cadastro-Estoque'!A:A),SUMIFS('PRODUTOS A PRODUZIR'!C:C,'PRODUTOS A PRODUZIR'!A:A,'Cadastro-Estoque'!A:A,'PRODUTOS A PRODUZIR'!B:B,CONCATENATE("<=",$A$2))) -> 0 | S89: =R89*F89 -> 0
A90: 027 | B90: AMIDO NUTRIVITA 20 X 500 | C90: 20 | D90: 0.5 | E90: 0.509 | F90: =C90*D90 -> 10 | G90: =C90*E90 -> 10.18 | I90: =IF(ISBLANK($A$2),SUMIFS(Entradas!C:C,Entradas!A:A,'Cadastro-Estoque'!A:A),SUMIFS(Entradas!C:C,Entradas!A:A,'Cadastro-Estoque'!A:A,Entradas!B:B,CONCATENATE("<=",$A$2))) -> 0 | J90: =I90*G90 -> 0 | L90: =IF(ISBLANK($A$2),SUMIFS(Saidas!C:C,Saidas!A:A,'Cadastro-Estoque'!A:A),SUMIFS(Saidas!C:C,Saidas!A:A,'Cadastro-Estoque'!A:A,Saidas!B:B,CONCATENATE("<=",$A$2))) -> 0 | M90: =L90*F90 -> 0 | O90: =IF(ISBLANK($A$2),SUMIFS(Faturado!C:C,Faturado!A:A,'Cadastro-Estoque'!A:A),SUMIFS(Faturado!C:C,Faturado!A:A,'Cadastro-Estoque'!A:A,Faturado!B:B,CONCATENATE("<=",$A$2))) -> 0 | P90: =O90*F90 -> 0 | R90: =IF(ISBLANK($A$2),SUMIFS('PRODUTOS A PRODUZIR'!C:C,'PRODUTOS A PRODUZIR'!A:A,'Cadastro-Estoque'!A:A),SUMIFS('PRODUTOS A PRODUZIR'!C:C,'PRODUTOS A PRODUZIR'!A:A,'Cadastro-Estoque'!A:A,'PRODUTOS A PRODUZIR'!B:B,CONCATENATE("<=",$A$2))) -> 0 | S90: =R90*F90 -> 0
A91: 059 | B91: AMIDO FRITZ E FRIDA 12 X 1 | C91: 12 | D91: 1 | E91: 1.01 | F91: =C91*D91 -> 12 | G91: =C91*E91 -> 12.12 | I91: =IF(ISBLANK($A$2),SUMIFS(Entradas!C:C,Entradas!A:A,'Cadastro-Estoque'!A:A),SUMIFS(Entradas!C:C,Entradas!A:A,'Cadastro-Estoque'!A:A,Entradas!B:B,CONCATENATE("<=",$A$2))) -> 0 | J91: =I91*G91 -> 0 | L91: =IF(ISBLANK($A$2),SUMIFS(Saidas!C:C,Saidas!A:A,'Cadastro-Estoque'!A:A),SUMIFS(Saidas!C:C,Saidas!A:A,'Cadastro-Estoque'!A:A,Saidas!B:B,CONCATENATE("<=",$A$2))) -> 0 | M91: =L91*F91 -> 0 | O91: =IF(ISBLANK($A$2),SUMIFS(Faturado!C:C,Faturado!A:A,'Cadastro-Estoque'!A:A),SUMIFS(Faturado!C:C,Faturado!A:A,'Cadastro-Estoque'!A:A,Faturado!B:B,CONCATENATE("<=",$A$2))) -> 0 | P91: =O91*F91 -> 0 | R91: =IF(ISBLANK($A$2),SUMIFS('PRODUTOS A PRODUZIR'!C:C,'PRODUTOS A PRODUZIR'!A:A,'Cadastro-Estoque'!A:A),SUMIFS('PRODUTOS A PRODUZIR'!C:C,'PRODUTOS A PRODUZIR'!A:A,'Cadastro-Estoque'!A:A,'PRODUTOS A PRODUZIR'!B:B,CONCATENATE("<=",$A$2))) -> 840 | S91: =R91*F91 -> 10080
A92: 060 | B92: AMIDO FRITZ E FRIDA 12 X 500 | C92: 12 | D92: 0.5 | E92: 0.509 | F92: =C92*D92 -> 6 | G92: =C92*E92 -> 6.108 | I92: =IF(ISBLANK($A$2),SUMIFS(Entradas!C:C,Entradas!A:A,'Cadastro-Estoque'!A:A),SUMIFS(Entradas!C:C,Entradas!A:A,'Cadastro-Estoque'!A:A,Entradas!B:B,CONCATENATE("<=",$A$2))) -> 0 | J92: =I92*G92 -> 0 | L92: =IF(ISBLANK($A$2),SUMIFS(Saidas!C:C,Saidas!A:A,'Cadastro-Estoque'!A:A),SUMIFS(Saidas!C:C,Saidas!A:A,'Cadastro-Estoque'!A:A,Saidas!B:B,CONCATENATE("<=",$A$2))) -> 0 | M92: =L92*F92 -> 0 | O92: =IF(ISBLANK($A$2),SUMIFS(Faturado!C:C,Faturado!A:A,'Cadastro-Estoque'!A:A),SUMIFS(Faturado!C:C,Faturado!A:A,'Cadastro-Estoque'!A:A,Faturado!B:B,CONCATENATE("<=",$A$2))) -> 0 | P92: =O92*F92 -> 0 | R92: =IF(ISBLANK($A$2),SUMIFS('PRODUTOS A PRODUZIR'!C:C,'PRODUTOS A PRODUZIR'!A:A,'Cadastro-Estoque'!A:A),SUMIFS('PRODUTOS A PRODUZIR'!C:C,'PRODUTOS A PRODUZIR'!A:A,'Cadastro-Estoque'!A:A,'PRODUTOS A PRODUZIR'!B:B,CONCATENATE("<=",$A$2))) -> 1092 | S92: =R92*F92 -> 6552
A93: 060 | B93: AMIDO FRITZ E FRIDA 12 X 200 | C93: 12 | D93: 0.2 | E93: 0.204 | F93: =C93*D93 -> 2.4 | G93: =C93*E93 -> 2.448 | I93: =IF(ISBLANK($A$2),SUMIFS(Entradas!C:C,Entradas!A:A,'Cadastro-Estoque'!A:A),SUMIFS(Entradas!C:C,Entradas!A:A,'Cadastro-Estoque'!A:A,Entradas!B:B,CONCATENATE("<=",$A$2))) -> 0 | J93: =I93*G93 -> 0 | L93: =IF(ISBLANK($A$2),SUMIFS(Saidas!C:C,Saidas!A:A,'Cadastro-Estoque'!A:A),SUMIFS(Saidas!C:C,Saidas!A:A,'Cadastro-Estoque'!A:A,Saidas!B:B,CONCATENATE("<=",$A$2))) -> 0 | M93: =L93*F93 -> 0 | O93: =IF(ISBLANK($A$2),SUMIFS(Faturado!C:C,Faturado!A:A,'Cadastro-Estoque'!A:A),SUMIFS(Faturado!C:C,Faturado!A:A,'Cadastro-Estoque'!A:A,Faturado!B:B,CONCATENATE("<=",$A$2))) -> 0 | P93: =O93*F93 -> 0 | R93: =IF(ISBLANK($A$2),SUMIFS('PRODUTOS A PRODUZIR'!C:C,'PRODUTOS A PRODUZIR'!A:A,'Cadastro-Estoque'!A:A),SUMIFS('PRODUTOS A PRODUZIR'!C:C,'PRODUTOS A PRODUZIR'!A:A,'Cadastro-Estoque'!A:A,'PRODUTOS A PRODUZIR'!B:B,CONCATENATE("<=",$A$2))) -> 1064 | S93: =R93*F93 -> 2553.6
A94: 070 | B94: AMIDO NUTRIVITA 12 X 1 | C94: 12 | D94: 1 | E94: 1.01 | F94: =C94*D94 -> 12 | G94: =C94*E94 -> 12.12 | I94: =IF(ISBLANK($A$2),SUMIFS(Entradas!C:C,Entradas!A:A,'Cadastro-Estoque'!A:A),SUMIFS(Entradas!C:C,Entradas!A:A,'Cadastro-Estoque'!A:A,Entradas!B:B,CONCATENATE("<=",$A$2))) -> 0 | J94: =I94*G94 -> 0 | L94: =IF(ISBLANK($A$2),SUMIFS(Saidas!C:C,Saidas!A:A,'Cadastro-Estoque'!A:A),SUMIFS(Saidas!C:C,Saidas!A:A,'Cadastro-Estoque'!A:A,Saidas!B:B,CONCATENATE("<=",$A$2))) -> 0 | M94: =L94*F94 -> 0 | O94: =IF(ISBLANK($A$2),SUMIFS(Faturado!C:C,Faturado!A:A,'Cadastro-Estoque'!A:A),SUMIFS(Faturado!C:C,Faturado!A:A,'Cadastro-Estoque'!A:A,Faturado!B:B,CONCATENATE("<=",$A$2))) -> 0 | P94: =O94*F94 -> 0 | R94: =IF(ISBLANK($A$2),SUMIFS('PRODUTOS A PRODUZIR'!C:C,'PRODUTOS A PRODUZIR'!A:A,'Cadastro-Estoque'!A:A),SUMIFS('PRODUTOS A PRODUZIR'!C:C,'PRODUTOS A PRODUZIR'!A:A,'Cadastro-Estoque'!A:A,'PRODUTOS A PRODUZIR'!B:B,CONCATENATE("<=",$A$2))) -> 0 | S94: =R94*F94 -> 0
A95: 070 | B95: AMIDO NUTRIVITA 24 X 500 G | C95: 24 | D95: 0.5 | E95: 0.509 | F95: =C95*D95 -> 12 | G95: =C95*E95 -> 12.216 | I95: =IF(ISBLANK($A$2),SUMIFS(Entradas!C:C,Entradas!A:A,'Cadastro-Estoque'!A:A),SUMIFS(Entradas!C:C,Entradas!A:A,'Cadastro-Estoque'!A:A,Entradas!B:B,CONCATENATE("<=",$A$2))) -> 0 | J95: =I95*G95 -> 0 | L95: =IF(ISBLANK($A$2),SUMIFS(Saidas!C:C,Saidas!A:A,'Cadastro-Estoque'!A:A),SUMIFS(Saidas!C:C,Saidas!A:A,'Cadastro-Estoque'!A:A,Saidas!B:B,CONCATENATE("<=",$A$2))) -> 0 | M95: =L95*F95 -> 0 | O95: =IF(ISBLANK($A$2),SUMIFS(Faturado!C:C,Faturado!A:A,'Cadastro-Estoque'!A:A),SUMIFS(Faturado!C:C,Faturado!A:A,'Cadastro-Estoque'!A:A,Faturado!B:B,CONCATENATE("<=",$A$2))) -> 0 | P95: =O95*F95 -> 0 | R95: =IF(ISBLANK($A$2),SUMIFS('PRODUTOS A PRODUZIR'!C:C,'PRODUTOS A PRODUZIR'!A:A,'Cadastro-Estoque'!A:A),SUMIFS('PRODUTOS A PRODUZIR'!C:C,'PRODUTOS A PRODUZIR'!A:A,'Cadastro-Estoque'!A:A,'PRODUTOS A PRODUZIR'!B:B,CONCATENATE("<=",$A$2))) -> 0 | S95: =R95*F95 -> 0
A96: 075 | B96: AMIDO KISABOR 12 X 500 G | C96: 12 | D96: 0.5 | E96: 0.509 | F96: =C96*D96 -> 6 | G96: =C96*E96 -> 6.108 | I96: =IF(ISBLANK($A$2),SUMIFS(Entradas!C:C,Entradas!A:A,'Cadastro-Estoque'!A:A),SUMIFS(Entradas!C:C,Entradas!A:A,'Cadastro-Estoque'!A:A,Entradas!B:B,CONCATENATE("<=",$A$2))) -> 0 | J96: =I96*G96 -> 0 | L96: =IF(ISBLANK($A$2),SUMIFS(Saidas!C:C,Saidas!A:A,'Cadastro-Estoque'!A:A),SUMIFS(Saidas!C:C,Saidas!A:A,'Cadastro-Estoque'!A:A,Saidas!B:B,CONCATENATE("<=",$A$2))) -> 0 | M96: =L96*F96 -> 0 | O96: =IF(ISBLANK($A$2),SUMIFS(Faturado!C:C,Faturado!A:A,'Cadastro-Estoque'!A:A),SUMIFS(Faturado!C:C,Faturado!A:A,'Cadastro-Estoque'!A:A,Faturado!B:B,CONCATENATE("<=",$A$2))) -> 0 | P96: =O96*F96 -> 0 | R96: =IF(ISBLANK($A$2),SUMIFS('PRODUTOS A PRODUZIR'!C:C,'PRODUTOS A PRODUZIR'!A:A,'Cadastro-Estoque'!A:A),SUMIFS('PRODUTOS A PRODUZIR'!C:C,'PRODUTOS A PRODUZIR'!A:A,'Cadastro-Estoque'!A:A,'PRODUTOS A PRODUZIR'!B:B,CONCATENATE("<=",$A$2))) -> 0 | S96: =R96*F96 -> 0
A97: 080 | B97: AMIDO CBS 12 X 200 G | C97: 12 | D97: 0.2 | E97: 0.204 | F97: =C97*D97 -> 2.4 | G97: =C97*E97 -> 2.448 | I97: =IF(ISBLANK($A$2),SUMIFS(Entradas!C:C,Entradas!A:A,'Cadastro-Estoque'!A:A),SUMIFS(Entradas!C:C,Entradas!A:A,'Cadastro-Estoque'!A:A,Entradas!B:B,CONCATENATE("<=",$A$2))) -> 0 | J97: =I97*G97 -> 0 | L97: =IF(ISBLANK($A$2),SUMIFS(Saidas!C:C,Saidas!A:A,'Cadastro-Estoque'!A:A),SUMIFS(Saidas!C:C,Saidas!A:A,'Cadastro-Estoque'!A:A,Saidas!B:B,CONCATENATE("<=",$A$2))) -> 0 | M97: =L97*F97 -> 0 | O97: =IF(ISBLANK($A$2),SUMIFS(Faturado!C:C,Faturado!A:A,'Cadastro-Estoque'!A:A),SUMIFS(Faturado!C:C,Faturado!A:A,'Cadastro-Estoque'!A:A,Faturado!B:B,CONCATENATE("<=",$A$2))) -> 0 | P97: =O97*F97 -> 0 | R97: =IF(ISBLANK($A$2),SUMIFS('PRODUTOS A PRODUZIR'!C:C,'PRODUTOS A PRODUZIR'!A:A,'Cadastro-Estoque'!A:A),SUMIFS('PRODUTOS A PRODUZIR'!C:C,'PRODUTOS A PRODUZIR'!A:A,'Cadastro-Estoque'!A:A,'PRODUTOS A PRODUZIR'!B:B,CONCATENATE("<=",$A$2))) -> 0 | S97: =R97*F97 -> 0
A98: 080 | B98: AMIDO CBS 12 X 500 G | C98: 12 | D98: 0.5 | E98: 0.509 | F98: =C98*D98 -> 6 | G98: =C98*E98 -> 6.108 | I98: =IF(ISBLANK($A$2),SUMIFS(Entradas!C:C,Entradas!A:A,'Cadastro-Estoque'!A:A),SUMIFS(Entradas!C:C,Entradas!A:A,'Cadastro-Estoque'!A:A,Entradas!B:B,CONCATENATE("<=",$A$2))) -> 0 | J98: =I98*G98 -> 0 | L98: =IF(ISBLANK($A$2),SUMIFS(Saidas!C:C,Saidas!A:A,'Cadastro-Estoque'!A:A),SUMIFS(Saidas!C:C,Saidas!A:A,'Cadastro-Estoque'!A:A,Saidas!B:B,CONCATENATE("<=",$A$2))) -> 0 | M98: =L98*F98 -> 0 | O98: =IF(ISBLANK($A$2),SUMIFS(Faturado!C:C,Faturado!A:A,'Cadastro-Estoque'!A:A),SUMIFS(Faturado!C:C,Faturado!A:A,'Cadastro-Estoque'!A:A,Faturado!B:B,CONCATENATE("<=",$A$2))) -> 0 | P98: =O98*F98 -> 0 | R98: =IF(ISBLANK($A$2),SUMIFS('PRODUTOS A PRODUZIR'!C:C,'PRODUTOS A PRODUZIR'!A:A,'Cadastro-Estoque'!A:A),SUMIFS('PRODUTOS A PRODUZIR'!C:C,'PRODUTOS A PRODUZIR'!A:A,'Cadastro-Estoque'!A:A,'PRODUTOS A PRODUZIR'!B:B,CONCATENATE("<=",$A$2))) -> 0 | S98: =R98*F98 -> 0
... A104: 225 | B104: AMIDO CINDERELA 12 X 1 | C104: 12 | D104: 1 | E104: 1.01 | F104: =C104*D104 -> 12 | G104: =C104*E104 -> 12.12 | I104: =IF(ISBLANK($A$2),SUMIFS(Entradas!C:C,Entradas!A:A,'Cadastro-Estoque'!A:A),SUMIFS(Entradas!C:C,Entradas!A:A,'Cadastro-Estoque'!A:A,Entradas!B:B,CONCATENATE("<=",$A$2))) -> 0 | J104: =I104*G104 -> 0 | L104: =IF(ISBLANK($A$2),SUMIFS(Saidas!C:C,Saidas!A:A,'Cadastro-Estoque'!A:A),SUMIFS(Saidas!C:C,Saidas!A:A,'Cadastro-Estoque'!A:A,Saidas!B:B,CONCATENATE("<=",$A$2))) -> 300 | M104: =L104*F104 -> 3600 | O104: =IF(ISBLANK($A$2),SUMIFS(Faturado!C:C,Faturado!A:A,'Cadastro-Estoque'!A:A),SUMIFS(Faturado!C:C,Faturado!A:A,'Cadastro-Estoque'!A:A,Faturado!B:B,CONCATENATE("<=",$A$2))) -> 0 | P104: =O104*F104 -> 0 | R104: =IF(ISBLANK($A$2),SUMIFS('PRODUTOS A PRODUZIR'!C:C,'PRODUTOS A PRODUZIR'!A:A,'Cadastro-Estoque'!A:A),SUMIFS('PRODUTOS A PRODUZIR'!C:C,'PRODUTOS A PRODUZIR'!A:A,'Cadastro-Estoque'!A:A,'PRODUTOS A PRODUZIR'!B:B,CONCATENATE("<=",$A$2))) -> 0 | S104: =R104*F104 -> 0
F105: =C105*D105 -> 0 | G105: =C105*E105 -> 0 | I105: =IF(ISBLANK($A$2),SUMIFS(Entradas!C:C,Entradas!A:A,'Cadastro-Estoque'!A:A),SUMIFS(Entradas!C:C,Entradas!A:A,'Cadastro-Estoque'!A:A,Entradas!B:B,CONCATENATE("<=",$A$2))) -> 0 | J105: =I105*G105 -> 0 | L105: =IF(ISBLANK($A$2),SUMIFS(Saidas!C:C,Saidas!A:A,'Cadastro-Estoque'!A:A),SUMIFS(Saidas!C:C,Saidas!A:A,'Cadastro-Estoque'!A:A,Saidas!B:B,CONCATENATE("<=",$A$2))) -> 0 | M105: =L105*F105 -> 0 | O105: =IF(ISBLANK($A$2),SUMIFS(Faturado!C:C,Faturado!A:A,'Cadastro-Estoque'!A:A),SUMIFS(Faturado!C:C,Faturado!A:A,'Cadastro-Estoque'!A:A,Faturado!B:B,CONCATENATE("<=",$A$2))) -> 0 | P105: =O105*F105 -> 0 | R105: =IF(ISBLANK($A$2),SUMIFS('PRODUTOS A PRODUZIR'!C:C,'PRODUTOS A PRODUZIR'!A:A,'Cadastro-Estoque'!A:A),SUMIFS('PRODUTOS A PRODUZIR'!C:C,'PRODUTOS A PRODUZIR'!A:A,'Cadastro-Estoque'!A:A,'PRODUTOS A PRODUZIR'!B:B,CONCATENATE("<=",$A$2))) -> 0 | S105: =R105*F105 -> 0
A106: 004 | B106: CANJICA MUNGUZÁ 40K | C106: 1 | D106: 40 | E106: 40.05 | F106: =C106*D106 -> 40 | G106: =C106*E106 -> 40.05 | I106: =IF(ISBLANK($A$2),SUMIFS(Entradas!C:C,Entradas!A:A,'Cadastro-Estoque'!A:A),SUMIFS(Entradas!C:C,Entradas!A:A,'Cadastro-Estoque'!A:A,Entradas!B:B,CONCATENATE("<=",$A$2))) -> 0 | J106: =I106*G106 -> 0 | L106: =IF(ISBLANK($A$2),SUMIFS(Saidas!C:C,Saidas!A:A,'Cadastro-Estoque'!A:A),SUMIFS(Saidas!C:C,Saidas!A:A,'Cadastro-Estoque'!A:A,Saidas!B:B,CONCATENATE("<=",$A$2))) -> 0 | M106: =L106*F106 -> 0 | O106: =IF(ISBLANK($A$2),SUMIFS(Faturado!C:C,Faturado!A:A,'Cadastro-Estoque'!A:A),SUMIFS(Faturado!C:C,Faturado!A:A,'Cadastro-Estoque'!A:A,Faturado!B:B,CONCATENATE("<=",$A$2))) -> 0 | P106: =O106*F106 -> 0 | R106: =IF(ISBLANK($A$2),SUMIFS('PRODUTOS A PRODUZIR'!C:C,'PRODUTOS A PRODUZIR'!A:A,'Cadastro-Estoque'!A:A),SUMIFS('PRODUTOS A PRODUZIR'!C:C,'PRODUTOS A PRODUZIR'!A:A,'Cadastro-Estoque'!A:A,'PRODUTOS A PRODUZIR'!B:B,CONCATENATE("<=",$A$2))) -> 0 | S106: =R106*F106 -> 0
A107: 004 | B107: CANJICA MUNGUZÁ 25K | C107: 1 | D107: 25 | E107: 25.05 | F107: =C107*D107 -> 25 | G107: =C107*E107 -> 25.05 | I107: =IF(ISBLANK($A$2),SUMIFS(Entradas!C:C,Entradas!A:A,'Cadastro-Estoque'!A:A),SUMIFS(Entradas!C:C,Entradas!A:A,'Cadastro-Estoque'!A:A,Entradas!B:B,CONCATENATE("<=",$A$2))) -> 0 | J107: =I107*G107 -> 0 | L107: =IF(ISBLANK($A$2),SUMIFS(Saidas!C:C,Saidas!A:A,'Cadastro-Estoque'!A:A),SUMIFS(Saidas!C:C,Saidas!A:A,'Cadastro-Estoque'!A:A,Saidas!B:B,CONCATENATE("<=",$A$2))) -> 0 | M107: =L107*F107 -> 0 | O107: =IF(ISBLANK($A$2),SUMIFS(Faturado!C:C,Faturado!A:A,'Cadastro-Estoque'!A:A),SUMIFS(Faturado!C:C,Faturado!A:A,'Cadastro-Estoque'!A:A,Faturado!B:B,CONCATENATE("<=",$A$2))) -> 0 | P107: =O107*F107 -> 0 | R107: =IF(ISBLANK($A$2),SUMIFS('PRODUTOS A PRODUZIR'!C:C,'PRODUTOS A PRODUZIR'!A:A,'Cadastro-Estoque'!A:A),SUMIFS('PRODUTOS A PRODUZIR'!C:C,'PRODUTOS A PRODUZIR'!A:A,'Cadastro-Estoque'!A:A,'PRODUTOS A PRODUZIR'!B:B,CONCATENATE("<=",$A$2))) -> 0 | S107: =R107*F107 -> 0
A108: 017 | B108: COLORÍFICO 25K | C108: 1 | D108: 25 | E108: 23.7975 | F108: =C108*D108 -> 25 | G108: =C108*E108 -> 23.7975 | I108: =IF(ISBLANK($A$2),SUMIFS(Entradas!C:C,Entradas!A:A,'Cadastro-Estoque'!A:A),SUMIFS(Entradas!C:C,Entradas!A:A,'Cadastro-Estoque'!A:A,Entradas!B:B,CONCATENATE("<=",$A$2))) -> 0 | J108: =I108*G108 -> 0 | L108: =IF(ISBLANK($A$2),SUMIFS(Saidas!C:C,Saidas!A:A,'Cadastro-Estoque'!A:A),SUMIFS(Saidas!C:C,Saidas!A:A,'Cadastro-Estoque'!A:A,Saidas!B:B,CONCATENATE("<=",$A$2))) -> 0 | M108: =L108*F108 -> 0 | O108: =IF(ISBLANK($A$2),SUMIFS(Faturado!C:C,Faturado!A:A,'Cadastro-Estoque'!A:A),SUMIFS(Faturado!C:C,Faturado!A:A,'Cadastro-Estoque'!A:A,Faturado!B:B,CONCATENATE("<=",$A$2))) -> 0 | P108: =O108*F108 -> 0 | R108: =IF(ISBLANK($A$2),SUMIFS('PRODUTOS A PRODUZIR'!C:C,'PRODUTOS A PRODUZIR'!A:A,'Cadastro-Estoque'!A:A),SUMIFS('PRODUTOS A PRODUZIR'!C:C,'PRODUTOS A PRODUZIR'!A:A,'Cadastro-Estoque'!A:A,'PRODUTOS A PRODUZIR'!B:B,CONCATENATE("<=",$A$2))) -> 0 | S108: =R108*F108 -> 0
A109: 023 | B109: CANJICA XERÉM 40K | C109: 1 | D109: 40 | E109: 40.05 | F109: =C109*D109 -> 40 | G109: =C109*E109 -> 40.05 | I109: =IF(ISBLANK($A$2),SUMIFS(Entradas!C:C,Entradas!A:A,'Cadastro-Estoque'!A:A),SUMIFS(Entradas!C:C,Entradas!A:A,'Cadastro-Estoque'!A:A,Entradas!B:B,CONCATENATE("<=",$A$2))) -> 0 | J109: =I109*G109 -> 0 | L109: =IF(ISBLANK($A$2),SUMIFS(Saidas!C:C,Saidas!A:A,'Cadastro-Estoque'!A:A),SUMIFS(Saidas!C:C,Saidas!A:A,'Cadastro-Estoque'!A:A,Saidas!B:B,CONCATENATE("<=",$A$2))) -> 0 | M109: =L109*F109 -> 0 | O109: =IF(ISBLANK($A$2),SUMIFS(Faturado!C:C,Faturado!A:A,'Cadastro-Estoque'!A:A),SUMIFS(Faturado!C:C,Faturado!A:A,'Cadastro-Estoque'!A:A,Faturado!B:B,CONCATENATE("<=",$A$2))) -> 0 | P109: =O109*F109 -> 0 | R109: =IF(ISBLANK($A$2),SUMIFS('PRODUTOS A PRODUZIR'!C:C,'PRODUTOS A PRODUZIR'!A:A,'Cadastro-Estoque'!A:A),SUMIFS('PRODUTOS A PRODUZIR'!C:C,'PRODUTOS A PRODUZIR'!A:A,'Cadastro-Estoque'!A:A,'PRODUTOS A PRODUZIR'!B:B,CONCATENATE("<=",$A$2))) -> 0 | S109: =R109*F109 -> 0
A110: 023 | B110: CANJICA XERÉM 25K | C110: 1 | D110: 25 | E110: 25.05 | F110: =C110*D110 -> 25 | G110: =C110*E110 -> 25.05 | I110: =IF(ISBLANK($A$2),SUMIFS(Entradas!C:C,Entradas!A:A,'Cadastro-Estoque'!A:A),SUMIFS(Entradas!C:C,Entradas!A:A,'Cadastro-Estoque'!A:A,Entradas!B:B,CONCATENATE("<=",$A$2))) -> 0 | J110: =I110*G110 -> 0 | L110: =IF(ISBLANK($A$2),SUMIFS(Saidas!C:C,Saidas!A:A,'Cadastro-Estoque'!A:A),SUMIFS(Saidas!C:C,Saidas!A:A,'Cadastro-Estoque'!A:A,Saidas!B:B,CONCATENATE("<=",$A$2))) -> 0 | M110: =L110*F110 -> 0 | O110: =IF(ISBLANK($A$2),SUMIFS(Faturado!C:C,Faturado!A:A,'Cadastro-Estoque'!A:A),SUMIFS(Faturado!C:C,Faturado!A:A,'Cadastro-Estoque'!A:A,Faturado!B:B,CONCATENATE("<=",$A$2))) -> 0 | P110: =O110*F110 -> 0 | R110: =IF(ISBLANK($A$2),SUMIFS('PRODUTOS A PRODUZIR'!C:C,'PRODUTOS A PRODUZIR'!A:A,'Cadastro-Estoque'!A:A),SUMIFS('PRODUTOS A PRODUZIR'!C:C,'PRODUTOS A PRODUZIR'!A:A,'Cadastro-Estoque'!A:A,'PRODUTOS A PRODUZIR'!B:B,CONCATENATE("<=",$A$2))) -> 0 | S110: =R110*F110 -> 0
...

Sheet Cadastro-Estoque
A1: Planilha de Controle de Estoque
A2: Data do estoque:
A3: Código | B3: Descrição | C3: Unidade | D3: Fornecedor | E3: Mínimo | F3: Saldo Inicial | G3: Estoque atual | H3: Média Entrada(R$) | I3: Média Saída(R$) | K3: ESTOQUE PAULO
A4: 011-12X500 | B4: FLOCADO NUTRIVITA 12 X 500 | C4: FARDOS | D4: ADRAM | F4: 0 | G4: =IF(ISBLANK($G$2),SUMIFS(Entradas!C:C,Entradas!A:A,'Cadastro-Estoque'!A:A)-SUMIFS(Saidas!C:C,Saidas!A:A,'Cadastro-Estoque'!A:A),SUMIFS(Entradas!C:C,Entradas!A:A,'Cadastro-Estoque'!A:A,Entradas!B:B,CONCATENATE("<=",$G$2))-SUMIFS(Saidas!C:C,Saidas!A:A,'Cadastro-Estoque'!A:A,Saidas!B:B,CONCATENATE("<=",$G$2)))+F4 -> 0 | H4: 0 | I4: =IF(ISBLANK($G$2),SUMIFS(Saidas!E:E,Saidas!A:A,'Cadastro-Estoque'!A:A),SUMIFS(Saidas!E:E,Saidas!A:A,'Cadastro-Estoque'!A:A,Saidas!B:B,CONCATENATE("<=",$G$2)))/IF(IF(ISBLANK($G$2),SUMIFS(Saidas!C:C,Saidas!A:A,'Cadastro-Estoque'!A:A),SUMIFS(Saidas!C:C,Saidas!A:A,'Cadastro-Estoque'!A:A,Saidas!B:B,CONCATENATE("<=",$G$2)))=0,1,IF(ISBLANK($G$2),SUMIFS(Saidas!C:C,Saidas!A:A,'Cadastro-Estoque'!A:A),SUMIFS(Saidas!C:C,Saidas!A:A,'Cadastro-Estoque'!A:A,Saidas!B:B,CONCATENATE("<=",$G$2)))) -> 0 | K4: =#REF! -> #REF!
A5: 011-30X500 | B5: FLOCADO NUTRIVITA 30 X 500 | C5: FARDOS | D5: ADRAM | F5: 38185 | G5: =IF(ISBLANK($G$2),SUMIFS(Entradas!C:C,Entradas!A:A,'Cadastro-Estoque'!A:A)-SUMIFS(Saidas!C:C,Saidas!A:A,'Cadastro-Estoque'!A:A),SUMIFS(Entradas!C:C,Entradas!A:A,'Cadastro-Estoque'!A:A,Entradas!B:B,CONCATENATE("<=",$G$2))-SUMIFS(Saidas!C:C,Saidas!A:A,'Cadastro-Estoque'!A:A,Saidas!B:B,CONCATENATE("<=",$G$2)))+F5 -> 34796 | H5: 24.3 | I5: =IF(ISBLANK($G$2),SUMIFS(Saidas!E:E,Saidas!A:A,'Cadastro-Estoque'!A:A),SUMIFS(Saidas!E:E,Saidas!A:A,'Cadastro-Estoque'!A:A,Saidas!B:B,CONCATENATE("<=",$G$2)))/IF(IF(ISBLANK($G$2),SUMIFS(Saidas!C:C,Saidas!A:A,'Cadastro-Estoque'!A:A),SUMIFS(Saidas!C:C,Saidas!A:A,'Cadastro-Estoque'!A:A,Saidas!B:B,CONCATENATE("<=",$G$2)))=0,1,IF(ISBLANK($G$2),SUMIFS(Saidas!C:C,Saidas!A:A,'Cadastro-Estoque'!A:A),SUMIFS(Saidas!C:C,Saidas!A:A,'Cadastro-Estoque'!A:A,Saidas!B:B,CONCATENATE("<=",$G$2)))) -> 0 | K5: =#REF! -> #REF!
A6: 012-30X500 | B6: FLOCADO VITABEM 30 X 500 | C6: FARDOS | D6: ADRAM | F6: 365 | G6: =IF(ISBLANK($G$2),SUMIFS(Entradas!C:C,Entradas!A:A,'Cadastro-Estoque'!A:A)-SUMIFS(Saidas!C:C,Saidas!A:A,'Cadastro-Estoque'!A:A),SUMIFS(Entradas!C:C,Entradas!A:A,'Cadastro-Estoque'!A:A,Entradas!B:B,CONCATENATE("<=",$G$2))-SUMIFS(Saidas!C:C,Saidas!A:A,'Cadastro-Estoque'!A:A,Saidas!B:B,CONCATENATE("<=",$G$2)))+F6 -> 365 | H6: 23.5 | I6: =IF(ISBLANK($G$2),SUMIFS(Saidas!E:E,Saidas!A:A,'Cadastro-Estoque'!A:A),SUMIFS(Saidas!E:E,Saidas!A:A,'Cadastro-Estoque'!A:A,Saidas!B:B,CONCATENATE("<=",$G$2)))/IF(IF(ISBLANK($G$2),SUMIFS(Saidas!C:C,Saidas!A:A,'Cadastro-Estoque'!A:A),SUMIFS(Saidas!C:C,Saidas!A:A,'Cadastro-Estoque'!A:A,Saidas!B:B,CONCATENATE("<=",$G$2)))=0,1,IF(ISBLANK($G$2),SUMIFS(Saidas!C:C,Saidas!A:A,'Cadastro-Estoque'!A:A),SUMIFS(Saidas!C:C,Saidas!A:A,'Cadastro-Estoque'!A:A,Saidas!B:B,CONCATENATE("<=",$G$2)))) -> 0 | K6: =#REF! -> #REF!
A7: 016-30X400 | B7: FLOCADO VITABRAS 30 X 400 | C7: FARDOS | D7: ADRAM | F7: 341 | G7: =IF(ISBLANK($G$2),SUMIFS(Entradas!C:C,Entradas!A:A,'Cadastro-Estoque'!A:A)-SUMIFS(Saidas!C:C,Saidas!A:A,'Cadastro-Estoque'!A:A),SUMIFS(Entradas!C:C,Entradas!A:A,'Cadastro-Estoque'!A:A,Entradas!B:B,CONCATENATE("<=",$G$2))-SUMIFS(Saidas!C:C,Saidas!A:A,'Cadastro-Estoque'!A:A,Saidas!B:B,CONCATENATE("<=",$G$2)))+F7 -> 341 | H7: 21 | I7: =IF(ISBLANK($G$2),SUMIFS(Saidas!E:E,Saidas!A:A,'Cadastro-Estoque'!A:A),SUMIFS(Saidas!E:E,Saidas!A:A,'Cadastro-Estoque'!A:A,Saidas!B:B,CONCATENATE("<=",$G$2)))/IF(IF(ISBLANK($G$2),SUMIFS(Saidas!C:C,Saidas!A:A,'Cadastro-Estoque'!A:A),SUMIFS(Saidas!C:C,Saidas!A:A,'Cadastro-Estoque'!A:A,Saidas!B:B,CONCATENATE("<=",$G$2)))=0,1,IF(ISBLANK($G$2),SUMIFS(Saidas!C:C,Saidas!A:A,'Cadastro-Estoque'!A:A),SUMIFS(Saidas!C:C,Saidas!A:A,'Cadastro-Estoque'!A:A,Saidas!B:B,CONCATENATE("<=",$G$2)))) -> 0 | K7: =#REF! -> #REF!
A8: 022-30X500 | B8: FLOCADO VITABRASIL 30 X 500 | C8: FARDOS | D8: ADRAM | F8: 0 | G8: =IF(ISBLANK($G$2),SUMIFS(Entradas!C:C,Entradas!A:A,'Cadastro-Estoque'!A:A)-SUMIFS(Saidas!C:C,Saidas!A:A,'Cadastro-Estoque'!A:A),SUMIFS(Entradas!C:C,Entradas!A:A,'Cadastro-Estoque'!A:A,Entradas!B:B,CONCATENATE("<=",$G$2))-SUMIFS(Saidas!C:C,Saidas!A:A,'Cadastro-Estoque'!A:A,Saidas!B:B,CONCATENATE("<=",$G$2)))+F8 -> 0 | H8: =IF(ISBLANK($G$2),SUMIFS(Entradas!E:E,Entradas!A:A,'Cadastro-Estoque'!A:A),SUMIFS(Entradas!E:E,Entradas!A:A,'Cadastro-Estoque'!A:A,Entradas!B:B,CONCATENATE("<=",$G$2)))/IF(IF(ISBLANK($G$2),SUMIFS(Entradas!C:C,Entradas!A:A,'Cadastro-Estoque'!A:A),SUMIFS(Entradas!C:C,Entradas!A:A,'Cadastro-Estoque'!A:A,Entradas!B:B,CONCATENATE("<=",$G$2)))=0,1,IF(ISBLANK($G$2),SUMIFS(Entradas!C:C,Entradas!A:A,'Cadastro-Estoque'!A:A),SUMIFS(Entradas!C:C,Entradas!A:A,'Cadastro-Estoque'!A:A,Entradas!B:B,CONCATENATE("<=",$G$2)))) -> 0 | I8: =IF(ISBLANK($G$2),SUMIFS(Saidas!E:E,Saidas!A:A,'Cadastro-Estoque'!A:A),SUMIFS(Saidas!E:E,Saidas!A:A,'Cadastro-Estoque'!A:A,Saidas!B:B,CONCATENATE("<=",$G$2)))/IF(IF(ISBLANK($G$2),SUMIFS(Saidas!C:C,Saidas!A:A,'Cadastro-Estoque'!A:A),SUMIFS(Saidas!C:C,Saidas!A:A,'Cadastro-Estoque'!A:A,Saidas!B:B,CONCATENATE("<=",$G$2)))=0,1,IF(ISBLANK($G$2),SUMIFS(Saidas!C:C,Saidas!A:A,'Cadastro-Estoque'!A:A),SUMIFS(Saidas!C:C,Saidas!A:A,'Cadastro-Estoque'!A:A,Saidas!B:B,CONCATENATE("<=",$G$2)))) -> 0 | K8: =#REF! -> #REF!
A9: 019-12X500 | B9: FLOCADO PURO MILHO 12 X 500 | C9: FARDOS | D9: ADRAM | F9: 0 | G9: =IF(ISBLANK($G$2),SUMIFS(Entradas!C:C,Entradas!A:A,'Cadastro-Estoque'!A:A)-SUMIFS(Saidas!C:C,Saidas!A:A,'Cadastro-Estoque'!A:A),SUMIFS(Entradas!C:C,Entradas!A:A,'Cadastro-Estoque'!A:A,Entradas!B:B,CONCATENATE("<=",$G$2))-SUMIFS(Saidas!C:C,Saidas!A:A,'Cadastro-Estoque'!A:A,Saidas!B:B,CONCATENATE("<=",$G$2)))+F9 -> 0 | H9: =IF(ISBLANK($G$2),SUMIFS(Entradas!E:E,Entradas!A:A,'Cadastro-Estoque'!A:A),SUMIFS(Entradas!E:E,Entradas!A:A,'Cadastro-Estoque'!A:A,Entradas!B:B,CONCATENATE("<=",$G$2)))/IF(IF(ISBLANK($G$2),SUMIFS(Entradas!C:C,Entradas!A:A,'Cadastro-Estoque'!A:A),SUMIFS(Entradas!C:C,Entradas!A:A,'Cadastro-Estoque'!A:A,Entradas!B:B,CONCATENATE("<=",$G$2)))=0,1,IF(ISBLANK($G$2),SUMIFS(Entradas!C:C,Entradas!A:A,'Cadastro-Estoque'!A:A),SUMIFS(Entradas!C:C,Entradas!A:A,'Cadastro-Estoque'!A:A,Entradas!B:B,CONCATENATE("<=",$G$2)))) -> 0 | I9: =IF(ISBLANK($G$2),SUMIFS(Saidas!E:E,Saidas!A:A,'Cadastro-Estoque'!A:A),SUMIFS(Saidas!E:E,Saidas!A:A,'Cadastro-Estoque'!A:A,Saidas!B:B,CONCATENATE("<=",$G$2)))/IF(IF(ISBLANK($G$2),SUMIFS(Saidas!C:C,Saidas!A:A,'Cadastro-Estoque'!A:A),SUMIFS(Saidas!C:C,Saidas!A:A,'Cadastro-Estoque'!A:A,Saidas!B:B,CONCATENATE("<=",$G$2)))=0,1,IF(ISBLANK($G$2),SUMIFS(Saidas!C:C,Saidas!A:A,'Cadastro-Estoque'!A:A),SUMIFS(Saidas!C:C,Saidas!A:A,'Cadastro-Estoque'!A:A,Saidas!B:B,CONCATENATE("<=",$G$2)))) -> 0 | K9: =#REF! -> #REF!
A10: 019-30X500 | B10: FLOCADO PURO MILHO 30 X 500 | C10: FARDOS | D10: ADRAM | F10: 2081 | G10: =IF(ISBLANK($G$2),SUMIFS(Entradas!C:C,Entradas!A:A,'Cadastro-Estoque'!A:A)-SUMIFS(Saidas!C:C,Saidas!A:A,'Cadastro-Estoque'!A:A),SUMIFS(Entradas!C:C,Entradas!A:A,'Cadastro-Estoque'!A:A,Entradas!B:B,CONCATENATE("<=",$G$2))-SUMIFS(Saidas!C:C,Saidas!A:A,'Cadastro-Estoque'!A:A,Saidas!B:B,CONCATENATE("<=",$G$2)))+F10 -> 2081 | H10: =IF(ISBLANK($G$2),SUMIFS(Entradas!E:E,Entradas!A:A,'Cadastro-Estoque'!A:A),SUMIFS(Entradas!E:E,Entradas!A:A,'Cadastro-Estoque'!A:A,Entradas!B:B,CONCATENATE("<=",$G$2)))/IF(IF(ISBLANK($G$2),SUMIFS(Entradas!C:C,Entradas!A:A,'Cadastro-Estoque'!A:A),SUMIFS(Entradas!C:C,Entradas!A:A,'Cadastro-Estoque'!A:A,Entradas!B:B,CONCATENATE("<=",$G$2)))=0,1,IF(ISBLANK($G$2),SUMIFS(Entradas!C:C,Entradas!A:A,'Cadastro-Estoque'!A:A),SUMIFS(Entradas!C:C,Entradas!A:A,'Cadastro-Estoque'!A:A,Entradas!B:B,CONCATENATE("<=",$G$2)))) -> 0 | I10: =IF(ISBLANK($G$2),SUMIFS(Saidas!E:E,Saidas!A:A,'Cadastro-Estoque'!A:A),SUMIFS(Saidas!E:E,Saidas!A:A,'Cadastro-Estoque'!A:A,Saidas!B:B,CONCATENATE("<=",$G$2)))/IF(IF(ISBLANK($G$2),SUMIFS(Saidas!C:C,Saidas!A:A,'Cadastro-Estoque'!A:A),SUMIFS(Saidas!C:C,Saidas!A:A,'Cadastro-Estoque'!A:A,Saidas!B:B,CONCATENATE("<=",$G$2)))=0,1,IF(ISBLANK($G$2),SUMIFS(Saidas!C:C,Saidas!A:A,'Cadastro-Estoque'!A:A),SUMIFS(Saidas!C:C,Saidas!A:A,'Cadastro-Estoque'!A:A,Saidas!B:B,CONCATENATE("<=",$G$2)))) -> 0 | K10: =#REF! -> #REF!
A11: 050-30X500 | B11: FLOCADO CORDEIRO 30 X 500 | C11: FARDOS | D11: ADRAM | F11: 0 | G11: =IF(ISBLANK($G$2),SUMIFS(Entradas!C:C,Entradas!A:A,'Cadastro-Estoque'!A:A)-SUMIFS(Saidas!C:C,Saidas!A:A,'Cadastro-Estoque'!A:A),SUMIFS(Entradas!C:C,Entradas!A:A,'Cadastro-Estoque'!A:A,Entradas!B:B,CONCATENATE("<=",$G$2))-SUMIFS(Saidas!C:C,Saidas!A:A,'Cadastro-Estoque'!A:A,Saidas!B:B,CONCATENATE("<=",$G$2)))+F11 -> 0 | H11: =IF(ISBLANK($G$2),SUMIFS(Entradas!E:E,Entradas!A:A,'Cadastro-Estoque'!A:A),SUMIFS(Entradas!E:E,Entradas!A:A,'Cadastro-Estoque'!A:A,Entradas!B:B,CONCATENATE("<=",$G$2)))/IF(IF(ISBLANK($G$2),SUMIFS(Entradas!C:C,Entradas!A:A,'Cadastro-Estoque'!A:A),SUMIFS(Entradas!C:C,Entradas!A:A,'Cadastro-Estoque'!A:A,Entradas!B:B,CONCATENATE("<=",$G$2)))=0,1,IF(ISBLANK($G$2),SUMIFS(Entradas!C:C,Entradas!A:A,'Cadastro-Estoque'!A:A),SUMIFS(Entradas!C:C,Entradas!A:A,'Cadastro-Estoque'!A:A,Entradas!B:B,CONCATENATE("<=",$G$2)))) -> 0 | I11: =IF(ISBLANK($G$2),SUMIFS(Saidas!E:E,Saidas!A:A,'Cadastro-Estoque'!A:A),SUMIFS(Saidas!E:E,Saidas!A:A,'Cadastro-Estoque'!A:A,Saidas!B:B,CONCATENATE("<=",$G$2)))/IF(IF(ISBLANK($G$2),SUMIFS(Saidas!C:C,Saidas!A:A,'Cadastro-Estoque'!A:A),SUMIFS(Saidas!C:C,Saidas!A:A,'Cadastro-Estoque'!A:A,Saidas!B:B,CONCATENATE("<=",$G$2)))=0,1,IF(ISBLANK($G$2),SUMIFS(Saidas!C:C,Saidas!A:A,'Cadastro-Estoque'!A:A),SUMIFS(Saidas!C:C,Saidas!A:A,'Cadastro-Estoque'!A:A,Saidas!B:B,CONCATENATE("<=",$G$2)))) -> 0 | K11: =#REF! -> #REF!
A12: 094-12X500 | B12: FLOCADO M & K 12 X 500 | C12: FARDOS | D12: ADRAM | F12: 0 | G12: =IF(ISBLANK($G$2),SUMIFS(Entradas!C:C,Entradas!A:A,'Cadastro-Estoque'!A:A)-SUMIFS(Saidas!C:C,Saidas!A:A,'Cadastro-Estoque'!A:A),SUMIFS(Entradas!C:C,Entradas!A:A,'Cadastro-Estoque'!A:A,Entradas!B:B,CONCATENATE("<=",$G$2))-SUMIFS(Saidas!C:C,Saidas!A:A,'Cadastro-Estoque'!A:A,Saidas!B:B,CONCATENATE("<=",$G$2)))+F12 -> 0 | H12: =IF(ISBLANK($G$2),SUMIFS(Entradas!E:E,Entradas!A:A,'Cadastro-Estoque'!A:A),SUMIFS(Entradas!E:E,Entradas!A:A,'Cadastro-Estoque'!A:A,Entradas!B:B,CONCATENATE("<=",$G$2)))/IF(IF(ISBLANK($G$2),SUMIFS(Entradas!C:C,Entradas!A:A,'Cadastro-Estoque'!A:A),SUMIFS(Entradas!C:C,Entradas!A:A,'Cadastro-Estoque'!A:A,Entradas!B:B,CONCATENATE("<=",$G$2)))=0,1,IF(ISBLANK($G$2),SUMIFS(Entradas!C:C,Entradas!A:A,'Cadastro-Estoque'!A:A),SUMIFS(Entradas!C:C,Entradas!A:A,'Cadastro-Estoque'!A:A,Entradas!B:B,CONCATENATE("<=",$G$2)))) -> 0 | I12: =IF(ISBLANK($G$2),SUMIFS(Saidas!E:E,Saidas!A:A,'Cadastro-Estoque'!A:A),SUMIFS(Saidas!E:E,Saidas!A:A,'Cadastro-Estoque'!A:A,Saidas!B:B,CONCATENATE("<=",$G$2)))/IF(IF(ISBLANK($G$2),SUMIFS(Saidas!C:C,Saidas!A:A,'Cadastro-Estoque'!A:A),SUMIFS(Saidas!C:C,Saidas!A:A,'Cadastro-Estoque'!A:A,Saidas!B:B,CONCATENATE("<=",$G$2)))=0,1,IF(ISBLANK($G$2),SUMIFS(Saidas!C:C,Saidas!A:A,'Cadastro-Estoque'!A:A),SUMIFS(Saidas!C:C,Saidas!A:A,'Cadastro-Estoque'!A:A,Saidas!B:B,CONCATENATE("<=",$G$2)))) -> 0 | K12: =#REF! -> #REF!
F13: 0 | G13: =IF(ISBLANK($G$2),SUMIFS(Entradas!C:C,Entradas!A:A,'Cadastro-Estoque'!A:A)-SUMIFS(Saidas!C:C,Saidas!A:A,'Cadastro-Estoque'!A:A),SUMIFS(Entradas!C:C,Entradas!A:A,'Cadastro-Estoque'!A:A,Entradas!B:B,CONCATENATE("<=",$G$2))-SUMIFS(Saidas!C:C,Saidas!A:A,'Cadastro-Estoque'!A:A,Saidas!B:B,CONCATENATE("<=",$G$2)))+F13 -> 0 | H13: =IF(ISBLANK($G$2),SUMIFS(Entradas!E:E,Entradas!A:A,'Cadastro-Estoque'!A:A),SUMIFS(Entradas!E:E,Entradas!A:A,'Cadastro-Estoque'!A:A,Entradas!B:B,CONCATENATE("<=",$G$2)))/IF(IF(ISBLANK($G$2),SUMIFS(Entradas!C:C,Entradas!A:A,'Cadastro-Estoque'!A:A),SUMIFS(Entradas!C:C,Entradas!A:A,'Cadastro-Estoque'!A:A,Entradas!B:B,CONCATENATE("<=",$G$2)))=0,1,IF(ISBLANK($G$2),SUMIFS(Entradas!C:C,Entradas!A:A,'Cadastro-Estoque'!A:A),SUMIFS(Entradas!C:C,Entradas!A:A,'Cadastro-Estoque'!A:A,Entradas!B:B,CONCATENATE("<=",$G$2)))) -> 0 | I13: =IF(ISBLANK($G$2),SUMIFS(Saidas!E:E,Saidas!A:A,'Cadastro-Estoque'!A:A),SUMIFS(Saidas!E:E,Saidas!A:A,'Cadastro-Estoque'!A:A,Saidas!B:B,CONCATENATE("<=",$G$2)))/IF(IF(ISBLANK($G$2),SUMIFS(Saidas!C:C,Saidas!A:A,'Cadastro-Estoque'!A:A),SUMIFS(Saidas!C:C,Saidas!A:A,'Cadastro-Estoque'!A:A,Saidas!B:B,CONCATENATE("<=",$G$2)))=0,1,IF(ISBLANK($G$2),SUMIFS(Saidas!C:C,Saidas!A:A,'Cadastro-Estoque'!A:A),SUMIFS(Saidas!C:C,Saidas!A:A,'Cadastro-Estoque'!A:A,Saidas!B:B,CONCATENATE("<=",$G$2)))) -> 0 | K13: 0
A14: 036-12X500 | B14: POLENTA KISABOR 12 X 500 | C14: FARDOS | D14: ADRAM | F14: 0 | G14: =IF(ISBLANK($G$2),SUMIFS(Entradas!C:C,Entradas!A:A,'Cadastro-Estoque'!A:A)-SUMIFS(Saidas!C:C,Saidas!A:A,'Cadastro-Estoque'!A:A),SUMIFS(Entradas!C:C,Entradas!A:A,'Cadastro-Estoque'!A:A,Entradas!B:B,CONCATENATE("<=",$G$2))-SUMIFS(Saidas!C:C,Saidas!A:A,'Cadastro-Estoque'!A:A,Saidas!B:B,CONCATENATE("<=",$G$2)))+F14 -> 0 | H14: =IF(ISBLANK($G$2),SUMIFS(Entradas!E:E,Entradas!A:A,'Cadastro-Estoque'!A:A),SUMIFS(Entradas!E:E,Entradas!A:A,'Cadastro-Estoque'!A:A,Entradas!B:B,CONCATENATE("<=",$G$2)))/IF(IF(ISBLANK($G$2),SUMIFS(Entradas!C:C,Entradas!A:A,'Cadastro-Estoque'!A:A),SUMIFS(Entradas!C:C,Entradas!A:A,'Cadastro-Estoque'!A:A,Entradas!B:B,CONCATENATE("<=",$G$2)))=0,1,IF(ISBLANK($G$2),SUMIFS(Entradas!C:C,Entradas!A:A,'Cadastro-Estoque'!A:A),SUMIFS(Entradas!C:C,Entradas!A:A,'Cadastro-Estoque'!A:A,Entradas!B:B,CONCATENATE("<=",$G$2)))) -> 0 | I14: =IF(ISBLANK($G$2),SUMIFS(Saidas!E:E,Saidas!A:A,'Cadastro-Estoque'!A:A),SUMIFS(Saidas!E:E,Saidas!A:A,'Cadastro-Estoque'!A:A,Saidas!B:B,CONCATENATE("<=",$G$2)))/IF(IF(ISBLANK($G$2),SUMIFS(Saidas!C:C,Saidas!A:A,'Cadastro-Estoque'!A:A),SUMIFS(Saidas!C:C,Saidas!A:A,'Cadastro-Estoque'!A:A,Saidas!B:B,CONCATENATE("<=",$G$2)))=0,1,IF(ISBLANK($G$2),SUMIFS(Saidas!C:C,Saidas!A:A,'Cadastro-Estoque'!A:A),SUMIFS(Saidas!C:C,Saidas!A:A,'Cadastro-Estoque'!A:A,Saidas!B:B,CONCATENATE("<=",$G$2)))) -> 0 | K14: =#REF! -> #REF!
A15: 036-30X500 | B15: POLENTA KISABOR 30 X 500 | C15: FARDOS | D15: ADRAM | F15: 0 | G15: =IF(ISBLANK($G$2),SUMIFS(Entradas!C:C,Entradas!A:A,'Cadastro-Estoque'!A:A)-SUMIFS(Saidas!C:C,Saidas!A:A,'Cadastro-Estoque'!A:A),SUMIFS(Entradas!C:C,Entradas!A:A,'Cadastro-Estoque'!A:A,Entradas!B:B,CONCATENATE("<=",$G$2))-SUMIFS(Saidas!C:C,Saidas!A:A,'Cadastro-Estoque'!A:A,Saidas!B:B,CONCATENATE("<=",$G$2)))+F15 -> 0 | H15: =IF(ISBLANK($G$2),SUMIFS(Entradas!E:E,Entradas!A:A,'Cadastro-Estoque'!A:A),SUMIFS(Entradas!E:E,Entradas!A:A,'Cadastro-Estoque'!A:A,Entradas!B:B,CONCATENATE("<=",$G$2)))/IF(IF(ISBLANK($G$2),SUMIFS(Entradas!C:C,Entradas!A:A,'Cadastro-Estoque'!A:A),SUMIFS(Entradas!C:C,Entradas!A:A,'Cadastro-Estoque'!A:A,Entradas!B:B,CONCATENATE("<=",$G$2)))=0,1,IF(ISBLANK($G$2),SUMIFS(Entradas!C:C,Entradas!A:A,'Cadastro-Estoque'!A:A),SUMIFS(Entradas!C:C,Entradas!A:A,'Cadastro-Estoque'!A:A,Entradas!B:B,CONCATENATE("<=",$G$2)))) -> 0 | I15: =IF(ISBLANK($G$2),SUMIFS(Saidas!E:E,Saidas!A:A,'Cadastro-Estoque'!A:A),SUMIFS(Saidas!E:E,Saidas!A:A,'Cadastro-Estoque'!A:A,Saidas!B:B,CONCATENATE("<=",$G$2)))/IF(IF(ISBLANK($G$2),SUMIFS(Saidas!C:C,Saidas!A:A,'Cadastro-Estoque'!A:A),SUMIFS(Saidas!C:C,Saidas!A:A,'Cadastro-Estoque'!A:A,Saidas!B:B,CONCATENATE("<=",$G$2)))=0,1,IF(ISBLANK($G$2),SUMIFS(Saidas!C:C,Saidas!A:A,'Cadastro-Estoque'!A:A),SUMIFS(Saidas!C:C,Saidas!A:A,'Cadastro-Estoque'!A:A,Saidas!B:B,CONCATENATE("<=",$G$2)))) -> 0 | K15: =#REF! -> #REF!
A16: 037-30X500 | B16: POLENTA NUTRIVITA 30 X 500 | C16: FARDOS | D16: ADRAM | F16: 239 | G16: =IF(ISBLANK($G$2),SUMIFS(Entradas!C:C,Entradas!A:A,'Cadastro-Estoque'!A:A)-SUMIFS(Saidas!C:C,Saidas!A:A,'Cadastro-Estoque'!A:A),SUMIFS(Entradas!C:C,Entradas!A:A,'Cadastro-Estoque'!A:A,Entradas!B:B,CONCATENATE("<=",$G$2))-SUMIFS(Saidas!C:C,Saidas!A:A,'Cadastro-Estoque'!A:A,Saidas!B:B,CONCATENATE("<=",$G$2)))+F16 -> 239 | H16: =IF(ISBLANK($G$2),SUMIFS(Entradas!E:E,Entradas!A:A,'Cadastro-Estoque'!A:A),SUMIFS(Entradas!E:E,Entradas!A:A,'Cadastro-Estoque'!A:A,Entradas!B:B,CONCATENATE("<=",$G$2)))/IF(IF(ISBLANK($G$2),SUMIFS(Entradas!C:C,Entradas!A:A,'Cadastro-Estoque'!A:A),SUMIFS(Entradas!C:C,Entradas!A:A,'Cadastro-Estoque'!A:A,Entradas!B:B,CONCATENATE("<=",$G$2)))=0,1,IF(ISBLANK($G$2),SUMIFS(Entradas!C:C,Entradas!A:A,'Cadastro-Estoque'!A:A),SUMIFS(Entradas!C:C,Entradas!A:A,'Cadastro-Estoque'!A:A,Entradas!B:B,CONCATENATE("<=",$G$2)))) -> 0 | I16: =IF(ISBLANK($G$2),SUMIFS(Saidas!E:E,Saidas!A:A,'Cadastro-Estoque'!A:A),SUMIFS(Saidas!E:E,Saidas!A:A,'Cadastro-Estoque'!A:A,Saidas!B:B,CONCATENATE("<=",$G$2)))/IF(IF(ISBLANK($G$2),SUMIFS(Saidas!C:C,Saidas!A:A,'Cadastro-Estoque'!A:A),SUMIFS(Saidas!C:C,Saidas!A:A,'Cadastro-Estoque'!A:A,Saidas!B:B,CONCATENATE("<=",$G$2)))=0,1,IF(ISBLANK($G$2),SUMIFS(Saidas!C:C,Saidas!A:A,'Cadastro-Estoque'!A:A),SUMIFS(Saidas!C:C,Saidas!A:A,'Cadastro-Estoque'!A:A,Saidas!B:B,CONCATENATE("<=",$G$2)))) -> 0 | K16: =#REF! -> #REF!
A17: 037-30X400 | B17: POLENTA NUTRIVITA 30 X 400 | C17: FARDOS | D17: ADRAM | F17: 2100 | G17: =IF(ISBLANK($G$2),SUMIFS(Entradas!C:C,Entradas!A:A,'Cadastro-Estoque'!A:A)-SUMIFS(Saidas!C:C,Saidas!A:A,'Cadastro-Estoque'!A:A),SUMIFS(Entradas!C:C,Entradas!A:A,'Cadastro-Estoque'!A:A,Entradas!B:B,CONCATENATE("<=",$G$2))-SUMIFS(Saidas!C:C,Saidas!A:A,'Cadastro-Estoque'!A:A,Saidas!B:B,CONCATENATE("<=",$G$2)))+F17 -> 2100 | I17: =IF(ISBLANK($G$2),SUMIFS(Saidas!E:E,Saidas!A:A,'Cadastro-Estoque'!A:A),SUMIFS(Saidas!E:E,Saidas!A:A,'Cadastro-Estoque'!A:A,Saidas!B:B,CONCATENATE("<=",$G$2)))/IF(IF(ISBLANK($G$2),SUMIFS(Saidas!C:C,Saidas!A:A,'Cadastro-Estoque'!A:A),SUMIFS(Saidas!C:C,Saidas!A:A,'Cadastro-Estoque'!A:A,Saidas!B:B,CONCATENATE("<=",$G$2)))=0,1,IF(ISBLANK($G$2),SUMIFS(Saidas!C:C,Saidas!A:A,'Cadastro-Estoque'!A:A),SUMIFS(Saidas!C:C,Saidas!A:A,'Cadastro-Estoque'!A:A,Saidas!B:B,CONCATENATE("<=",$G$2)))) -> 0
A18: 039-12X500 | B18: POLENTA CBS 12 X 500 | C18: FARDOS | D18: ADRAM | F18: 74 | G18: =IF(ISBLANK($G$2),SUMIFS(Entradas!C:C,Entradas!A:A,'Cadastro-Estoque'!A:A)-SUMIFS(Saidas!C:C,Saidas!A:A,'Cadastro-Estoque'!A:A),SUMIFS(Entradas!C:C,Entradas!A:A,'Cadastro-Estoque'!A:A,Entradas!B:B,CONCATENATE("<=",$G$2))-SUMIFS(Saidas!C:C,Saidas!A:A,'Cadastro-Estoque'!A:A,Saidas!B:B,CONCATENATE("<=",$G$2)))+F18 -> 74 | H18: =IF(ISBLANK($G$2),SUMIFS(Entradas!E:E,Entradas!A:A,'Cadastro-Estoque'!A:A),SUMIFS(Entradas!E:E,Entradas!A:A,'Cadastro-Estoque'!A:A,Entradas!B:B,CONCATENATE("<=",$G$2)))/IF(IF(ISBLANK($G$2),SUMIFS(Entradas!C:C,Entradas!A:A,'Cadastro-Estoque'!A:A),SUMIFS(Entradas!C:C,Entradas!A:A,'Cadastro-Estoque'!A:A,Entradas!B:B,CONCATENATE("<=",$G$2)))=0,1,IF(ISBLANK($G$2),SUMIFS(Entradas!C:C,Entradas!A:A,'Cadastro-Estoque'!A:A),SUMIFS(Entradas!C:C,Entradas!A:A,'Cadastro-Estoque'!A:A,Entradas!B:B,CONCATENATE("<=",$G$2)))) -> 0 | I18: =IF(ISBLANK($G$2),SUMIFS(Saidas!E:E,Saidas!A:A,'Cadastro-Estoque'!A:A),SUMIFS(Saidas!E:E,Saidas!A:A,'Cadastro-Estoque'!A:A,Saidas!B:B,CONCATENATE("<=",$G$2)))/IF(IF(ISBLANK($G$2),SUMIFS(Saidas!C:C,Saidas!A:A,'Cadastro-Estoque'!A:A),SUMIFS(Saidas!C:C,Saidas!A:A,'Cadastro-Estoque'!A:A,Saidas!B:B,CONCATENATE("<=",$G$2)))=0,1,IF(ISBLANK($G$2),SUMIFS(Saidas!C:C,Saidas!A:A,'Cadastro-Estoque'!A:A),SUMIFS(Saidas!C:C,Saidas!A:A,'Cadastro-Estoque'!A:A,Saidas!B:B,CONCATENATE("<=",$G$2)))) -> 0 | K18: =#REF! -> #REF!
A19: 052-12X500 | B19: POLENTA FRITZ E FRIDA 12 X 500 | C19: FARDOS | D19: ADRAM | F19: 0 | G19: =IF(ISBLANK($G$2),SUMIFS(Entradas!C:C,Entradas!A:A,'Cadastro-Estoque'!A:A)-SUMIFS(Saidas!C:C,Saidas!A:A,'Cadastro-Estoque'!A:A),SUMIFS(Entradas!C:C,Entradas!A:A,'Cadastro-Estoque'!A:A,Entradas!B:B,CONCATENATE("<=",$G$2))-SUMIFS(Saidas!C:C,Saidas!A:A,'Cadastro-Estoque'!A:A,Saidas!B:B,CONCATENATE("<=",$G$2)))+F19 -> 0 | H19: =IF(ISBLANK($G$2),SUMIFS(Entradas!E:E,Entradas!A:A,'Cadastro-Estoque'!A:A),SUMIFS(Entradas!E:E,Entradas!A:A,'Cadastro-Estoque'!A:A,Entradas!B:B,CONCATENATE("<=",$G$2)))/IF(IF(ISBLANK($G$2),SUMIFS(Entradas!C:C,Entradas!A:A,'Cadastro-Estoque'!A:A),SUMIFS(Entradas!C:C,Entradas!A:A,'Cadastro-Estoque'!A:A,Entradas!B:B,CONCATENATE("<=",$G$2)))=0,1,IF(ISBLANK($G$2),SUMIFS(Entradas!C:C,Entradas!A:A,'Cadastro-Estoque'!A:A),SUMIFS(Entradas!C:C,Entradas!A:A,'Cadastro-Estoque'!A:A,Entradas!B:B,CONCATENATE("<=",$G$2)))) -> 0 | I19: =IF(ISBLANK($G$2),SUMIFS(Saidas!E:E,Saidas!A:A,'Cadastro-Estoque'!A:A),SUMIFS(Saidas!E:E,Saidas!A:A,'Cadastro-Estoque'!A:A,Saidas!B:B,CONCATENATE("<=",$G$2)))/IF(IF(ISBLANK($G$2),SUMIFS(Saidas!C:C,Saidas!A:A,'Cadastro-Estoque'!A:A),SUMIFS(Saidas!C:C,Saidas!A:A,'Cadastro-Estoque'!A:A,Saidas!B:B,CONCATENATE("<=",$G$2)))=0,1,IF(ISBLANK($G$2),SUMIFS(Saidas!C:C,Saidas!A:A,'Cadastro-Estoque'!A:A),SUMIFS(Saidas!C:C,Saidas!A:A,'Cadastro-Estoque'!A:A,Saidas!B:B,CONCATENATE("<=",$G$2)))) -> 0 | K19: =#REF! -> #REF!
A20: 064-12X1 | B20: POLENTA PERDIZ 12 X 1K | C20: FARDOS | D20: ADRAM | F20: 0 | G20: =IF(ISBLANK($G$2),SUMIFS(Entradas!C:C,Entradas!A:A,'Cadastro-Estoque'!A:A)-SUMIFS(Saidas!C:C,Saidas!A:A,'Cadastro-Estoque'!A:A),SUMIFS(Entradas!C:C,Entradas!A:A,'Cadastro-Estoque'!A:A,Entradas!B:B,CONCATENATE("<=",$G$2))-SUMIFS(Saidas!C:C,Saidas!A:A,'Cadastro-Estoque'!A:A,Saidas!B:B,CONCATENATE("<=",$G$2)))+F20 -> 0 | H20: =IF(ISBLANK($G$2),SUMIFS(Entradas!E:E,Entradas!A:A,'Cadastro-Estoque'!A:A),SUMIFS(Entradas!E:E,Entradas!A:A,'Cadastro-Estoque'!A:A,Entradas!B:B,CONCATENATE("<=",$G$2)))/IF(IF(ISBLANK($G$2),SUMIFS(Entradas!C:C,Entradas!A:A,'Cadastro-Estoque'!A:A),SUMIFS(Entradas!C:C,Entradas!A:A,'Cadastro-Estoque'!A:A,Entradas!B:B,CONCATENATE("<=",$G$2)))=0,1,IF(ISBLANK($G$2),SUMIFS(Entradas!C:C,Entradas!A:A,'Cadastro-Estoque'!A:A),SUMIFS(Entradas!C:C,Entradas!A:A,'Cadastro-Estoque'!A:A,Entradas!B:B,CONCATENATE("<=",$G$2)))) -> 0 | I20: =IF(ISBLANK($G$2),SUMIFS(Saidas!E:E,Saidas!A:A,'Cadastro-Estoque'!A:A),SUMIFS(Saidas!E:E,Saidas!A:A,'Cadastro-Estoque'!A:A,Saidas!B:B,CONCATENATE("<=",$G$2)))/IF(IF(ISBLANK($G$2),SUMIFS(Saidas!C:C,Saidas!A:A,'Cadastro-Estoque'!A:A),SUMIFS(Saidas!C:C,Saidas!A:A,'Cadastro-Estoque'!A:A,Saidas!B:B,CONCATENATE("<=",$G$2)))=0,1,IF(ISBLANK($G$2),SUMIFS(Saidas!C:C,Saidas!A:A,'Cadastro-Estoque'!A:A),SUMIFS(Saidas!C:C,Saidas!A:A,'Cadastro-Estoque'!A:A,Saidas!B:B,CONCATENATE("<=",$G$2)))) -> 0 | K20: =#REF! -> #REF!
A21: 064-12X500 | B21: POLENTA PERDIZ 12 X 500 G | C21: FARDOS | D21: ADRAM | F21: 0 | G21: =IF(ISBLANK($G$2),SUMIFS(Entradas!C:C,Entradas!A:A,'Cadastro-Estoque'!A:A)-SUMIFS(Saidas!C:C,Saidas!A:A,'Cadastro-Estoque'!A:A),SUMIFS(Entradas!C:C,Entradas!A:A,'Cadastro-Estoque'!A:A,Entradas!B:B,CONCATENATE("<=",$G$2))-SUMIFS(Saidas!C:C,Saidas!A:A,'Cadastro-Estoque'!A:A,Saidas!B:B,CONCATENATE("<=",$G$2)))+F21 -> 0 | H21: =IF(ISBLANK($G$2),SUMIFS(Entradas!E:E,Entradas!A:A,'Cadastro-Estoque'!A:A),SUMIFS(Entradas!E:E,Entradas!A:A,'Cadastro-Estoque'!A:A,Entradas!B:B,CONCATENATE("<=",$G$2)))/IF(IF(ISBLANK($G$2),SUMIFS(Entradas!C:C,Entradas!A:A,'Cadastro-Estoque'!A:A),SUMIFS(Entradas!C:C,Entradas!A:A,'Cadastro-Estoque'!A:A,Entradas!B:B,CONCATENATE("<=",$G$2)))=0,1,IF(ISBLANK($G$2),SUMIFS(Entradas!C:C,Entradas!A:A,'Cadastro-Estoque'!A:A),SUMIFS(Entradas!C:C,Entradas!A:A,'Cadastro-Estoque'!A:A,Entradas!B:B,CONCATENATE("<=",$G$2)))) -> 0 | I21: =IF(ISBLANK($G$2),SUMIFS(Saidas!E:E,Saidas!A:A,'Cadastro-Estoque'!A:A),SUMIFS(Saidas!E:E,Saidas!A:A,'Cadastro-Estoque'!A:A,Saidas!B:B,CONCATENATE("<=",$G$2)))/IF(IF(ISBLANK($G$2),SUMIFS(Saidas!C:C,Saidas!A:A,'Cadastro-Estoque'!A:A),SUMIFS(Saidas!C:C,Saidas!A:A,'Cadastro-Estoque'!A:A,Saidas!B:B,CONCATENATE("<=",$G$2)))=0,1,IF(ISBLANK($G$2),SUMIFS(Saidas!C:C,Saidas!A:A,'Cadastro-Estoque'!A:A),SUMIFS(Saidas!C:C,Saidas!A:A,'Cadastro-Estoque'!A:A,Saidas!B:B,CONCATENATE("<=",$G$2)))) -> 0 | K21: =#REF! -> #REF!
A22: 078-12X500 | B22: POLENTA BEATRIZ 12 X 500 G | C22: FARDOS | D22: ADRAM | F22: 2203 | G22: =IF(ISBLANK($G$2),SUMIFS(Entradas!C:C,Entradas!A:A,'Cadastro-Estoque'!A:A)-SUMIFS(Saidas!C:C,Saidas!A:A,'Cadastro-Estoque'!A:A),SUMIFS(Entradas!C:C,Entradas!A:A,'Cadastro-Estoque'!A:A,Entradas!B:B,CONCATENATE("<=",$G$2))-SUMIFS(Saidas!C:C,Saidas!A:A,'Cadastro-Estoque'!A:A,Saidas!B:B,CONCATENATE("<=",$G$2)))+F22 -> 2203 | H22: =IF(ISBLANK($G$2),SUMIFS(Entradas!E:E,Entradas!A:A,'Cadastro-Estoque'!A:A),SUMIFS(Entradas!E:E,Entradas!A:A,'Cadastro-Estoque'!A:A,Entradas!B:B,CONCATENATE("<=",$G$2)))/IF(IF(ISBLANK($G$2),SUMIFS(Entradas!C:C,Entradas!A:A,'Cadastro-Estoque'!A:A),SUMIFS(Entradas!C:C,Entradas!A:A,'Cadastro-Estoque'!A:A,Entradas!B:B,CONCATENATE("<=",$G$2)))=0,1,IF(ISBLANK($G$2),SUMIFS(Entradas!C:C,Entradas!A:A,'Cadastro-Estoque'!A:A),SUMIFS(Entradas!C:C,Entradas!A:A,'Cadastro-Estoque'!A:A,Entradas!B:B,CONCATENATE("<=",$G$2)))) -> 0 | I22: =IF(ISBLANK($G$2),SUMIFS(Saidas!E:E,Saidas!A:A,'Cadastro-Estoque'!A:A),SUMIFS(Saidas!E:E,Saidas!A:A,'Cadastro-Estoque'!A:A,Saidas!B:B,CONCATENATE("<=",$G$2)))/IF(IF(ISBLANK($G$2),SUMIFS(Saidas!C:C,Saidas!A:A,'Cadastro-Estoque'!A:A),SUMIFS(Saidas!C:C,Saidas!A:A,'Cadastro-Estoque'!A:A,Saidas!B:B,CONCATENATE("<=",$G$2)))=0,1,IF(ISBLANK($G$2),SUMIFS(Saidas!C:C,Saidas!A:A,'Cadastro-Estoque'!A:A),SUMIFS(Saidas!C:C,Saidas!A:A,'Cadastro-Estoque'!A:A,Saidas!B:B,CONCATENATE("<=",$G$2)))) -> 0 | K22: =#REF! -> #REF!
A23: 079-24X500 | B23: POLENTA KISABOR PRÉ COZIDO 24 X 500 | C23: FARDOS | D23: ADRAM | F23: 0 | G23: =IF(ISBLANK($G$2),SUMIFS(Entradas!C:C,Entradas!A:A,'Cadastro-Estoque'!A:A)-SUMIFS(Saidas!C:C,Saidas!A:A,'Cadastro-Estoque'!A:A),SUMIFS(Entradas!C:C,Entradas!A:A,'Cadastro-Estoque'!A:A,Entradas!B:B,CONCATENATE("<=",$G$2))-SUMIFS(Saidas!C:C,Saidas!A:A,'Cadastro-Estoque'!A:A,Saidas!B:B,CONCATENATE("<=",$G$2)))+F23 -> 0 | H23: =IF(ISBLANK($G$2),SUMIFS(Entradas!E:E,Entradas!A:A,'Cadastro-Estoque'!A:A),SUMIFS(Entradas!E:E,Entradas!A:A,'Cadastro-Estoque'!A:A,Entradas!B:B,CONCATENATE("<=",$G$2)))/IF(IF(ISBLANK($G$2),SUMIFS(Entradas!C:C,Entradas!A:A,'Cadastro-Estoque'!A:A),SUMIFS(Entradas!C:C,Entradas!A:A,'Cadastro-Estoque'!A:A,Entradas!B:B,CONCATENATE("<=",$G$2)))=0,1,IF(ISBLANK($G$2),SUMIFS(Entradas!C:C,Entradas!A:A,'Cadastro-Estoque'!A:A),SUMIFS(Entradas!C:C,Entradas!A:A,'Cadastro-Estoque'!A:A,Entradas!B:B,CONCATENATE("<=",$G$2)))) -> 0 | I23: =IF(ISBLANK($G$2),SUMIFS(Saidas!E:E,Saidas!A:A,'Cadastro-Estoque'!A:A),SUMIFS(Saidas!E:E,Saidas!A:A,'Cadastro-Estoque'!A:A,Saidas!B:B,CONCATENATE("<=",$G$2)))/IF(IF(ISBLANK($G$2),SUMIFS(Saidas!C:C,Saidas!A:A,'Cadastro-Estoque'!A:A),SUMIFS(Saidas!C:C,Saidas!A:A,'Cadastro-Estoque'!A:A,Saidas!B:B,CONCATENATE("<=",$G$2)))=0,1,IF(ISBLANK($G$2),SUMIFS(Saidas!C:C,Saidas!A:A,'Cadastro-Estoque'!A:A),SUMIFS(Saidas!C:C,Saidas!A:A,'Cadastro-Estoque'!A:A,Saidas!B:B,CONCATENATE("<=",$G$2)))) -> 0
A24: 084-12X1 | B24: FUBÁ PRÉ COZIDO AREPA LAMPIONE | C24: FARDOS | D24: ADRAM | F24: 0 | G24: 0 | H24: =IF(ISBLANK($G$2),SUMIFS(Entradas!E:E,Entradas!A:A,'Cadastro-Estoque'!A:A),SUMIFS(Entradas!E:E,Entradas!A:A,'Cadastro-Estoque'!A:A,Entradas!B:B,CONCATENATE("<=",$G$2)))/IF(IF(ISBLANK($G$2),SUMIFS(Entradas!C:C,Entradas!A:A,'Cadastro-Estoque'!A:A),SUMIFS(Entradas!C:C,Entradas!A:A,'Cadastro-Estoque'!A:A,Entradas!B:B,CONCATENATE("<=",$G$2)))=0,1,IF(ISBLANK($G$2),SUMIFS(Entradas!C:C,Entradas!A:A,'Cadastro-Estoque'!A:A),SUMIFS(Entradas!C:C,Entradas!A:A,'Cadastro-Estoque'!A:A,Entradas!B:B,CONCATENATE("<=",$G$2)))) -> 0 | I24: =IF(ISBLANK($G$2),SUMIFS(Saidas!E:E,Saidas!A:A,'Cadastro-Estoque'!A:A),SUMIFS(Saidas!E:E,Saidas!A:A,'Cadastro-Estoque'!A:A,Saidas!B:B,CONCATENATE("<=",$G$2)))/IF(IF(ISBLANK($G$2),SUMIFS(Saidas!C:C,Saidas!A:A,'Cadastro-Estoque'!A:A),SUMIFS(Saidas!C:C,Saidas!A:A,'Cadastro-Estoque'!A:A,Saidas!B:B,CONCATENATE("<=",$G$2)))=0,1,IF(ISBLANK($G$2),SUMIFS(Saidas!C:C,Saidas!A:A,'Cadastro-Estoque'!A:A),SUMIFS(Saidas!C:C,Saidas!A:A,'Cadastro-Estoque'!A:A,Saidas!B:B,CONCATENATE("<=",$G$2)))) -> 0
A25: 092-12X1 | B25: FUBÁ PRÉ COZIDO AREPA NUTRIVITA | C25: FARDOS | D25: ADRAM | F25: 0 | G25: =IF(ISBLANK($G$2),SUMIFS(Entradas!C:C,Entradas!A:A,'Cadastro-Estoque'!A:A)-SUMIFS(Saidas!C:C,Saidas!A:A,'Cadastro-Estoque'!A:A),SUMIFS(Entradas!C:C,Entradas!A:A,'Cadastro-Estoque'!A:A,Entradas!B:B,CONCATENATE("<=",$G$2))-SUMIFS(Saidas!C:C,Saidas!A:A,'Cadastro-Estoque'!A:A,Saidas!B:B,CONCATENATE("<=",$G$2)))+F25 -> 0 | H25: =IF(ISBLANK($G$2),SUMIFS(Entradas!E:E,Entradas!A:A,'Cadastro-Estoque'!A:A),SUMIFS(Entradas!E:E,Entradas!A:A,'Cadastro-Estoque'!A:A,Entradas!B:B,CONCATENATE("<=",$G$2)))/IF(IF(ISBLANK($G$2),SUMIFS(Entradas!C:C,Entradas!A:A,'Cadastro-Estoque'!A:A),SUMIFS(Entradas!C:C,Entradas!A:A,'Cadastro-Estoque'!A:A,Entradas!B:B,CONCATENATE("<=",$G$2)))=0,1,IF(ISBLANK($G$2),SUMIFS(Entradas!C:C,Entradas!A:A,'Cadastro-Estoque'!A:A),SUMIFS(Entradas!C:C,Entradas!A:A,'Cadastro-Estoque'!A:A,Entradas!B:B,CONCATENATE("<=",$G$2)))) -> 0 | I25: =IF(ISBLANK($G$2),SUMIFS(Saidas!E:E,Saidas!A:A,'Cadastro-Estoque'!A:A),SUMIFS(Saidas!E:E,Saidas!A:A,'Cadastro-Estoque'!A:A,Saidas!B:B,CONCATENATE("<=",$G$2)))/IF(IF(ISBLANK($G$2),SUMIFS(Saidas!C:C,Saidas!A:A,'Cadastro-Estoque'!A:A),SUMIFS(Saidas!C:C,Saidas!A:A,'Cadastro-Estoque'!A:A,Saidas!B:B,CONCATENATE("<=",$G$2)))=0,1,IF(ISBLANK($G$2),SUMIFS(Saidas!C:C,Saidas!A:A,'Cadastro-Estoque'!A:A),SUMIFS(Saidas!C:C,Saidas!A:A,'Cadastro-Estoque'!A:A,Saidas!B:B,CONCATENATE("<=",$G$2)))) -> 0 | K25: =#REF! -> #REF!
A26: 092-30x500 | B26: FUBÁ PRÉ COZIDO AREPA NUTRIVITA | C26: FARDOS | D26: ADRAM | F26: 0 | G26: =IF(ISBLANK($G$2),SUMIFS(Entradas!C:C,Entradas!A:A,'Cadastro-Estoque'!A:A)-SUMIFS(Saidas!C:C,Saidas!A:A,'Cadastro-Estoque'!A:A),SUMIFS(Entradas!C:C,Entradas!A:A,'Cadastro-Estoque'!A:A,Entradas!B:B,CONCATENATE("<=",$G$2))-SUMIFS(Saidas!C:C,Saidas!A:A,'Cadastro-Estoque'!A:A,Saidas!B:B,CONCATENATE("<=",$G$2)))+F26 -> 0 | H26: =IF(ISBLANK($G$2),SUMIFS(Entradas!E:E,Entradas!A:A,'Cadastro-Estoque'!A:A),SUMIFS(Entradas!E:E,Entradas!A:A,'Cadastro-Estoque'!A:A,Entradas!B:B,CONCATENATE("<=",$G$2)))/IF(IF(ISBLANK($G$2),SUMIFS(Entradas!C:C,Entradas!A:A,'Cadastro-Estoque'!A:A),SUMIFS(Entradas!C:C,Entradas!A:A,'Cadastro-Estoque'!A:A,Entradas!B:B,CONCATENATE("<=",$G$2)))=0,1,IF(ISBLANK($G$2),SUMIFS(Entradas!C:C,Entradas!A:A,'Cadastro-Estoque'!A:A),SUMIFS(Entradas!C:C,Entradas!A:A,'Cadastro-Estoque'!A:A,Entradas!B:B,CONCATENATE("<=",$G$2)))) -> 0 | I26: =IF(ISBLANK($G$2),SUMIFS(Saidas!E:E,Saidas!A:A,'Cadastro-Estoque'!A:A),SUMIFS(Saidas!E:E,Saidas!A:A,'Cadastro-Estoque'!A:A,Saidas!B:B,CONCATENATE("<=",$G$2)))/IF(IF(ISBLANK($G$2),SUMIFS(Saidas!C:C,Saidas!A:A,'Cadastro-Estoque'!A:A),SUMIFS(Saidas!C:C,Saidas!A:A,'Cadastro-Estoque'!A:A,Saidas!B:B,CONCATENATE("<=",$G$2)))=0,1,IF(ISBLANK($G$2),SUMIFS(Saidas!C:C,Saidas!A:A,'Cadastro-Estoque'!A:A),SUMIFS(Saidas!C:C,Saidas!A:A,'Cadastro-Estoque'!A:A,Saidas!B:B,CONCATENATE("<=",$G$2)))) -> 0 | K26: =#REF! -> #REF!
A27: 095-30X500 | B27: FUBÁ PRÉ COZIDO BOA NOVA | C27: FARDOS | D27: ADRAM | F27: 0 | G27: =IF(ISBLANK($G$2),SUMIFS(Entradas!C:C,Entradas!A:A,'Cadastro-Estoque'!A:A)-SUMIFS(Saidas!C:C,Saidas!A:A,'Cadastro-Estoque'!A:A),SUMIFS(Entradas!C:C,Entradas!A:A,'Cadastro-Estoque'!A:A,Entradas!B:B,CONCATENATE("<=",$G$2))-SUMIFS(Saidas!C:C,Saidas!A:A,'Cadastro-Estoque'!A:A,Saidas!B:B,CONCATENATE("<=",$G$2)))+F27 -> 0 | H27: =IF(ISBLANK($G$2),SUMIFS(Entradas!E:E,Entradas!A:A,'Cadastro-Estoque'!A:A),SUMIFS(Entradas!E:E,Entradas!A:A,'Cadastro-Estoque'!A:A,Entradas!B:B,CONCATENATE("<=",$G$2)))/IF(IF(ISBLANK($G$2),SUMIFS(Entradas!C:C,Entradas!A:A,'Cadastro-Estoque'!A:A),SUMIFS(Entradas!C:C,Entradas!A:A,'Cadastro-Estoque'!A:A,Entradas!B:B,CONCATENATE("<=",$G$2)))=0,1,IF(ISBLANK($G$2),SUMIFS(Entradas!C:C,Entradas!A:A,'Cadastro-Estoque'!A:A),SUMIFS(Entradas!C:C,Entradas!A:A,'Cadastro-Estoque'!A:A,Entradas!B:B,CONCATENATE("<=",$G$2)))) -> 0 | I27: =IF(ISBLANK($G$2),SUMIFS(Saidas!E:E,Saidas!A:A,'Cadastro-Estoque'!A:A),SUMIFS(Saidas!E:E,Saidas!A:A,'Cadastro-Estoque'!A:A,Saidas!B:B,CONCATENATE("<=",$G$2)))/IF(IF(ISBLANK($G$2),SUMIFS(Saidas!C:C,Saidas!A:A,'Cadastro-Estoque'!A:A),SUMIFS(Saidas!C:C,Saidas!A:A,'Cadastro-Estoque'!A:A,Saidas!B:B,CONCATENATE("<=",$G$2)))=0,1,IF(ISBLANK($G$2),SUMIFS(Saidas!C:C,Saidas!A:A,'Cadastro-Estoque'!A:A),SUMIFS(Saidas!C:C,Saidas!A:A,'Cadastro-Estoque'!A:A,Saidas!B:B,CONCATENATE("<=",$G$2)))) -> 0 | K27: =#REF! -> #REF!
A28: 098-12X1 | B28: FUBÁ PRÉ COZIDO AREPA REINAREPA 12 X 1 | C28: FARDOS | D28: ADRAM | F28: 0 | G28: =IF(ISBLANK($G$2),SUMIFS(Entradas!C:C,Entradas!A:A,'Cadastro-Estoque'!A:A)-SUMIFS(Saidas!C:C,Saidas!A:A,'Cadastro-Estoque'!A:A),SUMIFS(Entradas!C:C,Entradas!A:A,'Cadastro-Estoque'!A:A,Entradas!B:B,CONCATENATE("<=",$G$2))-SUMIFS(Saidas!C:C,Saidas!A:A,'Cadastro-Estoque'!A:A,Saidas!B:B,CONCATENATE("<=",$G$2)))+F28 -> 0 | H28: =IF(ISBLANK($G$2),SUMIFS(Entradas!E:E,Entradas!A:A,'Cadastro-Estoque'!A:A),SUMIFS(Entradas!E:E,Entradas!A:A,'Cadastro-Estoque'!A:A,Entradas!B:B,CONCATENATE("<=",$G$2)))/IF(IF(ISBLANK($G$2),SUMIFS(Entradas!C:C,Entradas!A:A,'Cadastro-Estoque'!A:A),SUMIFS(Entradas!C:C,Entradas!A:A,'Cadastro-Estoque'!A:A,Entradas!B:B,CONCATENATE("<=",$G$2)))=0,1,IF(ISBLANK($G$2),SUMIFS(Entradas!C:C,Entradas!A:A,'Cadastro-Estoque'!A:A),SUMIFS(Entradas!C:C,Entradas!A:A,'Cadastro-Estoque'!A:A,Entradas!B:B,CONCATENATE("<=",$G$2)))) -> 0 | I28: =IF(ISBLANK($G$2),SUMIFS(Saidas!E:E,Saidas!A:A,'Cadastro-Estoque'!A:A),SUMIFS(Saidas!E:E,Saidas!A:A,'Cadastro-Estoque'!A:A,Saidas!B:B,CONCATENATE("<=",$G$2)))/IF(IF(ISBLANK($G$2),SUMIFS(Saidas!C:C,Saidas!A:A,'Cadastro-Estoque'!A:A),SUMIFS(Saidas!C:C,Saidas!A:A,'Cadastro-Estoque'!A:A,Saidas!B:B,CONCATENATE("<=",$G$2)))=0,1,IF(ISBLANK($G$2),SUMIFS(Saidas!C:C,Saidas!A:A,'Cadastro-Estoque'!A:A),SUMIFS(Saidas!C:C,Saidas!A:A,'Cadastro-Estoque'!A:A,Saidas!B:B,CONCATENATE("<=",$G$2)))) -> 0 | K28: =#REF! -> #REF!
A29: 098-30X500 | B29: FUBÁ PRÉ COZIDO AREPA REINAREPA 30 X 500 | C29: FARDOS | D29: ADRAM | F29: 0 | G29: =IF(ISBLANK($G$2),SUMIFS(Entradas!C:C,Entradas!A:A,'Cadastro-Estoque'!A:A)-SUMIFS(Saidas!C:C,Saidas!A:A,'Cadastro-Estoque'!A:A),SUMIFS(Entradas!C:C,Entradas!A:A,'Cadastro-Estoque'!A:A,Entradas!B:B,CONCATENATE("<=",$G$2))-SUMIFS(Saidas!C:C,Saidas!A:A,'Cadastro-Estoque'!A:A,Saidas!B:B,CONCATENATE("<=",$G$2)))+F29 -> 0 | H29: =IF(ISBLANK($G$2),SUMIFS(Entradas!E:E,Entradas!A:A,'Cadastro-Estoque'!A:A),SUMIFS(Entradas!E:E,Entradas!A:A,'Cadastro-Estoque'!A:A,Entradas!B:B,CONCATENATE("<=",$G$2)))/IF(IF(ISBLANK($G$2),SUMIFS(Entradas!C:C,Entradas!A:A,'Cadastro-Estoque'!A:A),SUMIFS(Entradas!C:C,Entradas!A:A,'Cadastro-Estoque'!A:A,Entradas!B:B,CONCATENATE("<=",$G$2)))=0,1,IF(ISBLANK($G$2),SUMIFS(Entradas!C:C,Entradas!A:A,'Cadastro-Estoque'!A:A),SUMIFS(Entradas!C:C,Entradas!A:A,'Cadastro-Estoque'!A:A,Entradas!B:B,CONCATENATE("<=",$G$2)))) -> 0 | I29: =IF(ISBLANK($G$2),SUMIFS(Saidas!E:E,Saidas!A:A,'Cadastro-Estoque'!A:A),SUMIFS(Saidas!E:E,Saidas!A:A,'Cadastro-Estoque'!A:A,Saidas!B:B,CONCATENATE("<=",$G$2)))/IF(IF(ISBLANK($G$2),SUMIFS(Saidas!C:C,Saidas!A:A,'Cadastro-Estoque'!A:A),SUMIFS(Saidas!C:C,Saidas!A:A,'Cadastro-Estoque'!A:A,Saidas!B:B,CONCATENATE("<=",$G$2)))=0,1,IF(ISBLANK($G$2),SUMIFS(Saidas!C:C,Saidas!A:A,'Cadastro-Estoque'!A:A),SUMIFS(Saidas!C:C,Saidas!A:A,'Cadastro-Estoque'!A:A,Saidas!B:B,CONCATENATE("<=",$G$2)))) -> 0 | K29: =#REF! -> #REF!
A30: 100-30x500 | B30: POLENTA TUPÃ PRE COZIDO 30 X 500 | C30: FARDOS | D30: ADRAM | F30: 0 | G30: =IF(ISBLANK($G$2),SUMIFS(Entradas!C:C,Entradas!A:A,'Cadastro-Estoque'!A:A)-SUMIFS(Saidas!C:C,Saidas!A:A,'Cadastro-Estoque'!A:A),SUMIFS(Entradas!C:C,Entradas!A:A,'Cadastro-Estoque'!A:A,Entradas!B:B,CONCATENATE("<=",$G$2))-SUMIFS(Saidas!C:C,Saidas!A:A,'Cadastro-Estoque'!A:A,Saidas!B:B,CONCATENATE("<=",$G$2)))+F30 -> 0 | H30: =IF(ISBLANK($G$2),SUMIFS(Entradas!E:E,Entradas!A:A,'Cadastro-Estoque'!A:A),SUMIFS(Entradas!E:E,Entradas!A:A,'Cadastro-Estoque'!A:A,Entradas!B:B,CONCATENATE("<=",$G$2)))/IF(IF(ISBLANK($G$2),SUMIFS(Entradas!C:C,Entradas!A:A,'Cadastro-Estoque'!A:A),SUMIFS(Entradas!C:C,Entradas!A:A,'Cadastro-Estoque'!A:A,Entradas!B:B,CONCATENATE("<=",$G$2)))=0,1,IF(ISBLANK($G$2),SUMIFS(Entradas!C:C,Entradas!A:A,'Cadastro-Estoque'!A:A),SUMIFS(Entradas!C:C,Entradas!A:A,'Cadastro-Estoque'!A:A,Entradas!B:B,CONCATENATE("<=",$G$2)))) -> 0 | I30: =IF(ISBLANK($G$2),SUMIFS(Saidas!E:E,Saidas!A:A,'Cadastro-Estoque'!A:A),SUMIFS(Saidas!E:E,Saidas!A:A,'Cadastro-Estoque'!A:A,Saidas!B:B,CONCATENATE("<=",$G$2)))/IF(IF(ISBLANK($G$2),SUMIFS(Saidas!C:C,Saidas!A:A,'Cadastro-Estoque'!A:A),SUMIFS(Saidas!C:C,Saidas!A:A,'Cadastro-Estoque'!A:A,Saidas!B:B,CONCATENATE("<=",$G$2)))=0,1,IF(ISBLANK($G$2),SUMIFS(Saidas!C:C,Saidas!A:A,'Cadastro-Estoque'!A:A),SUMIFS(Saidas!C:C,Saidas!A:A,'Cadastro-Estoque'!A:A,Saidas!B:B,CONCATENATE("<=",$G$2)))) -> 0
A31: 105-30X500 | B31: FUBÁ PRÉ COZIDO AREPITA CARIBE 30 X 500 | C31: FARDOS | D31: ADRAM | F31: 0 | G31: =IF(ISBLANK($G$2),SUMIFS(Entradas!C:C,Entradas!A:A,'Cadastro-Estoque'!A:A)-SUMIFS(Saidas!C:C,Saidas!A:A,'Cadastro-Estoque'!A:A),SUMIFS(Entradas!C:C,Entradas!A:A,'Cadastro-Estoque'!A:A,Entradas!B:B,CONCATENATE("<=",$G$2))-SUMIFS(Saidas!C:C,Saidas!A:A,'Cadastro-Estoque'!A:A,Saidas!B:B,CONCATENATE("<=",$G$2)))+F31 -> 0 | H31: =IF(ISBLANK($G$2),SUMIFS(Entradas!E:E,Entradas!A:A,'Cadastro-Estoque'!A:A),SUMIFS(Entradas!E:E,Entradas!A:A,'Cadastro-Estoque'!A:A,Entradas!B:B,CONCATENATE("<=",$G$2)))/IF(IF(ISBLANK($G$2),SUMIFS(Entradas!C:C,Entradas!A:A,'Cadastro-Estoque'!A:A),SUMIFS(Entradas!C:C,Entradas!A:A,'Cadastro-Estoque'!A:A,Entradas!B:B,CONCATENATE("<=",$G$2)))=0,1,IF(ISBLANK($G$2),SUMIFS(Entradas!C:C,Entradas!A:A,'Cadastro-Estoque'!A:A),SUMIFS(Entradas!C:C,Entradas!A:A,'Cadastro-Estoque'!A:A,Entradas!B:B,CONCATENATE("<=",$G$2)))) -> 0 | I31: =IF(ISBLANK($G$2),SUMIFS(Saidas!E:E,Saidas!A:A,'Cadastro-Estoque'!A:A),SUMIFS(Saidas!E:E,Saidas!A:A,'Cadastro-Estoque'!A:A,Saidas!B:B,CONCATENATE("<=",$G$2)))/IF(IF(ISBLANK($G$2),SUMIFS(Saidas!C:C,Saidas!A:A,'Cadastro-Estoque'!A:A),SUMIFS(Saidas!C:C,Saidas!A:A,'Cadastro-Estoque'!A:A,Saidas!B:B,CONCATENATE("<=",$G$2)))=0,1,IF(ISBLANK($G$2),SUMIFS(Saidas!C:C,Saidas!A:A,'Cadastro-Estoque'!A:A),SUMIFS(Saidas!C:C,Saidas!A:A,'Cadastro-Estoque'!A:A,Saidas!B:B,CONCATENATE("<=",$G$2)))) -> 0 | K31: =#REF! -> #REF!
F32: 0 | G32: =IF(ISBLANK($G$2),SUMIFS(Entradas!C:C,Entradas!A:A,'Cadastro-Estoque'!A:A)-SUMIFS(Saidas!C:C,Saidas!A:A,'Cadastro-Estoque'!A:A),SUMIFS(Entradas!C:C,Entradas!A:A,'Cadastro-Estoque'!A:A,Entradas!B:B,CONCATENATE("<=",$G$2))-SUMIFS(Saidas!C:C,Saidas!A:A,'Cadastro-Estoque'!A:A,Saidas!B:B,CONCATENATE("<=",$G$2)))+F32 -> 0 | H32: =IF(ISBLANK($G$2),SUMIFS(Entradas!E:E,Entradas!A:A,'Cadastro-Estoque'!A:A),SUMIFS(Entradas!E:E,Entradas!A:A,'Cadastro-Estoque'!A:A,Entradas!B:B,CONCATENATE("<=",$G$2)))/IF(IF(ISBLANK($G$2),SUMIFS(Entradas!C:C,Entradas!A:A,'Cadastro-Estoque'!A:A),SUMIFS(Entradas!C:C,Entradas!A:A,'Cadastro-Estoque'!A:A,Entradas!B:B,CONCATENATE("<=",$G$2)))=0,1,IF(ISBLANK($G$2),SUMIFS(Entradas!C:C,Entradas!A:A,'Cadastro-Estoque'!A:A),SUMIFS(Entradas!C:C,Entradas!A:A,'Cadastro-Estoque'!A:A,Entradas!B:B,CONCATENATE("<=",$G$2)))) -> 0 | I32: =IF(ISBLANK($G$2),SUMIFS(Saidas!E:E,Saidas!A:A,'Cadastro-Estoque'!A:A),SUMIFS(Saidas!E:E,Saidas!A:A,'Cadastro-Estoque'!A:A,Saidas!B:B,CONCATENATE("<=",$G$2)))/IF(IF(ISBLANK($G$2),SUMIFS(Saidas!C:C,Saidas!A:A,'Cadastro-Estoque'!A:A),SUMIFS(Saidas!C:C,Saidas!A:A,'Cadastro-Estoque'!A:A,Saidas!B:B,CONCATENATE("<=",$G$2)))=0,1,IF(ISBLANK($G$2),SUMIFS(Saidas!C:C,Saidas!A:A,'Cadastro-Estoque'!A:A),SUMIFS(Saidas!C:C,Saidas!A:A,'Cadastro-Estoque'!A:A,Saidas!B:B,CONCATENATE("<=",$G$2)))) -> 0 | K32: 0
A33: 201-20X500 | B33: FLOCÃO MILHO NUTRIVITA 20 X 500 | C33: FARDOS | D33: ADRAM | F33: 6984 | G33: =IF(ISBLANK($G$2),SUMIFS(Entradas!C:C,Entradas!A:A,'Cadastro-Estoque'!A:A)-SUMIFS(Saidas!C:C,Saidas!A:A,'Cadastro-Estoque'!A:A),SUMIFS(Entradas!C:C,Entradas!A:A,'Cadastro-Estoque'!A:A,Entradas!B:B,CONCATENATE("<=",$G$2))-SUMIFS(Saidas!C:C,Saidas!A:A,'Cadastro-Estoque'!A:A,Saidas!B:B,CONCATENATE("<=",$G$2)))+F33 -> 7157 | H33: =IF(ISBLANK($G$2),SUMIFS(Entradas!E:E,Entradas!A:A,'Cadastro-Estoque'!A:A),SUMIFS(Entradas!E:E,Entradas!A:A,'Cadastro-Estoque'!A:A,Entradas!B:B,CONCATENATE("<=",$G$2)))/IF(IF(ISBLANK($G$2),SUMIFS(Entradas!C:C,Entradas!A:A,'Cadastro-Estoque'!A:A),SUMIFS(Entradas!C:C,Entradas!A:A,'Cadastro-Estoque'!A:A,Entradas!B:B,CONCATENATE("<=",$G$2)))=0,1,IF(ISBLANK($G$2),SUMIFS(Entradas!C:C,Entradas!A:A,'Cadastro-Estoque'!A:A),SUMIFS(Entradas!C:C,Entradas!A:A,'Cadastro-Estoque'!A:A,Entradas!B:B,CONCATENATE("<=",$G$2)))) -> 0 | I33: =IF(ISBLANK($G$2),SUMIFS(Saidas!E:E,Saidas!A:A,'Cadastro-Estoque'!A:A),SUMIFS(Saidas!E:E,Saidas!A:A,'Cadastro-Estoque'!A:A,Saidas!B:B,CONCATENATE("<=",$G$2)))/IF(IF(ISBLANK($G$2),SUMIFS(Saidas!C:C,Saidas!A:A,'Cadastro-Estoque'!A:A),SUMIFS(Saidas!C:C,Saidas!A:A,'Cadastro-Estoque'!A:A,Saidas!B:B,CONCATENATE("<=",$G$2)))=0,1,IF(ISBLANK($G$2),SUMIFS(Saidas!C:C,Saidas!A:A,'Cadastro-Estoque'!A:A),SUMIFS(Saidas!C:C,Saidas!A:A,'Cadastro-Estoque'!A:A,Saidas!B:B,CONCATENATE("<=",$G$2)))) -> 0 | K33: =#REF! -> #REF!
A34: 201-10X500 | B34: FLOCÃO MILHO NUTRIVITA 10 X 500 | C34: FARDOS | D34: ADRAM | F34: 0 | G34: =IF(ISBLANK($G$2),SUMIFS(Entradas!C:C,Entradas!A:A,'Cadastro-Estoque'!A:A)-SUMIFS(Saidas!C:C,Saidas!A:A,'Cadastro-Estoque'!A:A),SUMIFS(Entradas!C:C,Entradas!A:A,'Cadastro-Estoque'!A:A,Entradas!B:B,CONCATENATE("<=",$G$2))-SUMIFS(Saidas!C:C,Saidas!A:A,'Cadastro-Estoque'!A:A,Saidas!B:B,CONCATENATE("<=",$G$2)))+F34 -> 0 | H34: =IF(ISBLANK($G$2),SUMIFS(Entradas!E:E,Entradas!A:A,'Cadastro-Estoque'!A:A),SUMIFS(Entradas!E:E,Entradas!A:A,'Cadastro-Estoque'!A:A,Entradas!B:B,CONCATENATE("<=",$G$2)))/IF(IF(ISBLANK($G$2),SUMIFS(Entradas!C:C,Entradas!A:A,'Cadastro-Estoque'!A:A),SUMIFS(Entradas!C:C,Entradas!A:A,'Cadastro-Estoque'!A:A,Entradas!B:B,CONCATENATE("<=",$G$2)))=0,1,IF(ISBLANK($G$2),SUMIFS(Entradas!C:C,Entradas!A:A,'Cadastro-Estoque'!A:A),SUMIFS(Entradas!C:C,Entradas!A:A,'Cadastro-Estoque'!A:A,Entradas!B:B,CONCATENATE("<=",$G$2)))) -> 0 | I34: =IF(ISBLANK($G$2),SUMIFS(Saidas!E:E,Saidas!A:A,'Cadastro-Estoque'!A:A),SUMIFS(Saidas!E:E,Saidas!A:A,'Cadastro-Estoque'!A:A,Saidas!B:B,CONCATENATE("<=",$G$2)))/IF(IF(ISBLANK($G$2),SUMIFS(Saidas!C:C,Saidas!A:A,'Cadastro-Estoque'!A:A),SUMIFS(Saidas!C:C,Saidas!A:A,'Cadastro-Estoque'!A:A,Saidas!B:B,CONCATENATE("<=",$G$2)))=0,1,IF(ISBLANK($G$2),SUMIFS(Saidas!C:C,Saidas!A:A,'Cadastro-Estoque'!A:A),SUMIFS(Saidas!C:C,Saidas!A:A,'Cadastro-Estoque'!A:A,Saidas!B:B,CONCATENATE("<=",$G$2)))) -> 0 | K34: =#REF! -> #REF!
A35: 205-20X500 | B35: FLOCÃO MILHO VITABEM 20 X 500 | C35: FARDOS | D35: ADRAM | F35: 322 | G35: =IF(ISBLANK($G$2),SUMIFS(Entradas!C:C,Entradas!A:A,'Cadastro-Estoque'!A:A)-SUMIFS(Saidas!C:C,Saidas!A:A,'Cadastro-Estoque'!A:A),SUMIFS(Entradas!C:C,Entradas!A:A,'Cadastro-Estoque'!A:A,Entradas!B:B,CONCATENATE("<=",$G$2))-SUMIFS(Saidas!C:C,Saidas!A:A,'Cadastro-Estoque'!A:A,Saidas!B:B,CONCATENATE("<=",$G$2)))+F35 -> 322 | H35: =IF(ISBLANK($G$2),SUMIFS(Entradas!E:E,Entradas!A:A,'Cadastro-Estoque'!A:A),SUMIFS(Entradas!E:E,Entradas!A:A,'Cadastro-Estoque'!A:A,Entradas!B:B,CONCATENATE("<=",$G$2)))/IF(IF(ISBLANK($G$2),SUMIFS(Entradas!C:C,Entradas!A:A,'Cadastro-Estoque'!A:A),SUMIFS(Entradas!C:C,Entradas!A:A,'Cadastro-Estoque'!A:A,Entradas!B:B,CONCATENATE("<=",$G$2)))=0,1,IF(ISBLANK($G$2),SUMIFS(Entradas!C:C,Entradas!A:A,'Cadastro-Estoque'!A:A),SUMIFS(Entradas!C:C,Entradas!A:A,'Cadastro-Estoque'!A:A,Entradas!B:B,CONCATENATE("<=",$G$2)))) -> 0 | I35: =IF(ISBLANK($G$2),SUMIFS(Saidas!E:E,Saidas!A:A,'Cadastro-Estoque'!A:A),SUMIFS(Saidas!E:E,Saidas!A:A,'Cadastro-Estoque'!A:A,Saidas!B:B,CONCATENATE("<=",$G$2)))/IF(IF(ISBLANK($G$2),SUMIFS(Saidas!C:C,Saidas!A:A,'Cadastro-Estoque'!A:A),SUMIFS(Saidas!C:C,Saidas!A:A,'Cadastro-Estoque'!A:A,Saidas!B:B,CONCATENATE("<=",$G$2)))=0,1,IF(ISBLANK($G$2),SUMIFS(Saidas!C:C,Saidas!A:A,'Cadastro-Estoque'!A:A),SUMIFS(Saidas!C:C,Saidas!A:A,'Cadastro-Estoque'!A:A,Saidas!B:B,CONCATENATE("<=",$G$2)))) -> 0 | K35: =#REF! -> #REF!
A36: 207-20X400 | B36: FLOCÃO MILHO VITABRAS 20 X 400 | C36: FARDOS | D36: ADRAM | F36: 11 | G36: =IF(ISBLANK($G$2),SUMIFS(Entradas!C:C,Entradas!A:A,'Cadastro-Estoque'!A:A)-SUMIFS(Saidas!C:C,Saidas!A:A,'Cadastro-Estoque'!A:A),SUMIFS(Entradas!C:C,Entradas!A:A,'Cadastro-Estoque'!A:A,Entradas!B:B,CONCATENATE("<=",$G$2))-SUMIFS(Saidas!C:C,Saidas!A:A,'Cadastro-Estoque'!A:A,Saidas!B:B,CONCATENATE("<=",$G$2)))+F36 -> 11 | H36: =IF(ISBLANK($G$2),SUMIFS(Entradas!E:E,Entradas!A:A,'Cadastro-Estoque'!A:A),SUMIFS(Entradas!E:E,Entradas!A:A,'Cadastro-Estoque'!A:A,Entradas!B:B,CONCATENATE("<=",$G$2)))/IF(IF(ISBLANK($G$2),SUMIFS(Entradas!C:C,Entradas!A:A,'Cadastro-Estoque'!A:A),SUMIFS(Entradas!C:C,Entradas!A:A,'Cadastro-Estoque'!A:A,Entradas!B:B,CONCATENATE("<=",$G$2)))=0,1,IF(ISBLANK($G$2),SUMIFS(Entradas!C:C,Entradas!A:A,'Cadastro-Estoque'!A:A),SUMIFS(Entradas!C:C,Entradas!A:A,'Cadastro-Estoque'!A:A,Entradas!B:B,CONCATENATE("<=",$G$2)))) -> 0 | I36: =IF(ISBLANK($G$2),SUMIFS(Saidas!E:E,Saidas!A:A,'Cadastro-Estoque'!A:A),SUMIFS(Saidas!E:E,Saidas!A:A,'Cadastro-Estoque'!A:A,Saidas!B:B,CONCATENATE("<=",$G$2)))/IF(IF(ISBLANK($G$2),SUMIFS(Saidas!C:C,Saidas!A:A,'Cadastro-Estoque'!A:A),SUMIFS(Saidas!C:C,Saidas!A:A,'Cadastro-Estoque'!A:A,Saidas!B:B,CONCATENATE("<=",$G$2)))=0,1,IF(ISBLANK($G$2),SUMIFS(Saidas!C:C,Saidas!A:A,'Cadastro-Estoque'!A:A),SUMIFS(Saidas!C:C,Saidas!A:A,'Cadastro-Estoque'!A:A,Saidas!B:B,CONCATENATE("<=",$G$2)))) -> 0 | K36: =#REF! -> #REF!
A37: 208-12X500 | B37: FLOCÃO MILHO PURO MILHO 12 X 500 | C37: FARDOS | D37: ADRAM | F37: 3 | G37: =IF(ISBLANK($G$2),SUMIFS(Entradas!C:C,Entradas!A:A,'Cadastro-Estoque'!A:A)-SUMIFS(Saidas!C:C,Saidas!A:A,'Cadastro-Estoque'!A:A),SUMIFS(Entradas!C:C,Entradas!A:A,'Cadastro-Estoque'!A:A,Entradas!B:B,CONCATENATE("<=",$G$2))-SUMIFS(Saidas!C:C,Saidas!A:A,'Cadastro-Estoque'!A:A,Saidas!B:B,CONCATENATE("<=",$G$2)))+F37 -> -10397 | H37: =IF(ISBLANK($G$2),SUMIFS(Entradas!E:E,Entradas!A:A,'Cadastro-Estoque'!A:A),SUMIFS(Entradas!E:E,Entradas!A:A,'Cadastro-Estoque'!A:A,Entradas!B:B,CONCATENATE("<=",$G$2)))/IF(IF(ISBLANK($G$2),SUMIFS(Entradas!C:C,Entradas!A:A,'Cadastro-Estoque'!A:A),SUMIFS(Entradas!C:C,Entradas!A:A,'Cadastro-Estoque'!A:A,Entradas!B:B,CONCATENATE("<=",$G$2)))=0,1,IF(ISBLANK($G$2),SUMIFS(Entradas!C:C,Entradas!A:A,'Cadastro-Estoque'!A:A),SUMIFS(Entradas!C:C,Entradas!A:A,'Cadastro-Estoque'!A:A,Entradas!B:B,CONCATENATE("<=",$G$2)))) -> 0 | I37: =IF(ISBLANK($G$2),SUMIFS(Saidas!E:E,Saidas!A:A,'Cadastro-Estoque'!A:A),SUMIFS(Saidas!E:E,Saidas!A:A,'Cadastro-Estoque'!A:A,Saidas!B:B,CONCATENATE("<=",$G$2)))/IF(IF(ISBLANK($G$2),SUMIFS(Saidas!C:C,Saidas!A:A,'Cadastro-Estoque'!A:A),SUMIFS(Saidas!C:C,Saidas!A:A,'Cadastro-Estoque'!A:A,Saidas!B:B,CONCATENATE("<=",$G$2)))=0,1,IF(ISBLANK($G$2),SUMIFS(Saidas!C:C,Saidas!A:A,'Cadastro-Estoque'!A:A),SUMIFS(Saidas!C:C,Saidas!A:A,'Cadastro-Estoque'!A:A,Saidas!B:B,CONCATENATE("<=",$G$2)))) -> 0 | K37: =#REF! -> #REF!
A38: 209-12X500 | B38: FLOCÃO DE MILHO QUALITÁ 12 X 500 | C38: FARDOS | D38: ADRAM | F38: 3 | G38: =IF(ISBLANK($G$2),SUMIFS(Entradas!C:C,Entradas!A:A,'Cadastro-Estoque'!A:A)-SUMIFS(Saidas!C:C,Saidas!A:A,'Cadastro-Estoque'!A:A),SUMIFS(Entradas!C:C,Entradas!A:A,'Cadastro-Estoque'!A:A,Entradas!B:B,CONCATENATE("<=",$G$2))-SUMIFS(Saidas!C:C,Saidas!A:A,'Cadastro-Estoque'!A:A,Saidas!B:B,CONCATENATE("<=",$G$2)))+F38 -> 3 | H38: =IF(ISBLANK($G$2),SUMIFS(Entradas!E:E,Entradas!A:A,'Cadastro-Estoque'!A:A),SUMIFS(Entradas!E:E,Entradas!A:A,'Cadastro-Estoque'!A:A,Entradas!B:B,CONCATENATE("<=",$G$2)))/IF(IF(ISBLANK($G$2),SUMIFS(Entradas!C:C,Entradas!A:A,'Cadastro-Estoque'!A:A),SUMIFS(Entradas!C:C,Entradas!A:A,'Cadastro-Estoque'!A:A,Entradas!B:B,CONCATENATE("<=",$G$2)))=0,1,IF(ISBLANK($G$2),SUMIFS(Entradas!C:C,Entradas!A:A,'Cadastro-Estoque'!A:A),SUMIFS(Entradas!C:C,Entradas!A:A,'Cadastro-Estoque'!A:A,Entradas!B:B,CONCATENATE("<=",$G$2)))) -> 0 | I38: =IF(ISBLANK($G$2),SUMIFS(Saidas!E:E,Saidas!A:A,'Cadastro-Estoque'!A:A),SUMIFS(Saidas!E:E,Saidas!A:A,'Cadastro-Estoque'!A:A,Saidas!B:B,CONCATENATE("<=",$G$2)))/IF(IF(ISBLANK($G$2),SUMIFS(Saidas!C:C,Saidas!A:A,'Cadastro-Estoque'!A:A),SUMIFS(Saidas!C:C,Saidas!A:A,'Cadastro-Estoque'!A:A,Saidas!B:B,CONCATENATE("<=",$G$2)))=0,1,IF(ISBLANK($G$2),SUMIFS(Saidas!C:C,Saidas!A:A,'Cadastro-Estoque'!A:A),SUMIFS(Saidas!C:C,Saidas!A:A,'Cadastro-Estoque'!A:A,Saidas!B:B,CONCATENATE("<=",$G$2)))) -> 0 | K38: =#REF! -> #REF!
A39: 212-20X500 | B39: FLOCAO DE MILHO LESTE 20 X 500 | C39: FARDOS | D39: ADRAM | F39: 0 | G39: 0 | H39: =IF(ISBLANK($G$2),SUMIFS(Entradas!E:E,Entradas!A:A,'Cadastro-Estoque'!A:A),SUMIFS(Entradas!E:E,Entradas!A:A,'Cadastro-Estoque'!A:A,Entradas!B:B,CONCATENATE("<=",$G$2)))/IF(IF(ISBLANK($G$2),SUMIFS(Entradas!C:C,Entradas!A:A,'Cadastro-Estoque'!A:A),SUMIFS(Entradas!C:C,Entradas!A:A,'Cadastro-Estoque'!A:A,Entradas!B:B,CONCATENATE("<=",$G$2)))=0,1,IF(ISBLANK($G$2),SUMIFS(Entradas!C:C,Entradas!A:A,'Cadastro-Estoque'!A:A),SUMIFS(Entradas!C:C,Entradas!A:A,'Cadastro-Estoque'!A:A,Entradas!B:B,CONCATENATE("<=",$G$2)))) -> 0 | I39: =IF(ISBLANK($G$2),SUMIFS(Saidas!E:E,Saidas!A:A,'Cadastro-Estoque'!A:A),SUMIFS(Saidas!E:E,Saidas!A:A,'Cadastro-Estoque'!A:A,Saidas!B:B,CONCATENATE("<=",$G$2)))/IF(IF(ISBLANK($G$2),SUMIFS(Saidas!C:C,Saidas!A:A,'Cadastro-Estoque'!A:A),SUMIFS(Saidas!C:C,Saidas!A:A,'Cadastro-Estoque'!A:A,Saidas!B:B,CONCATENATE("<=",$G$2)))=0,1,IF(ISBLANK($G$2),SUMIFS(Saidas!C:C,Saidas!A:A,'Cadastro-Estoque'!A:A),SUMIFS(Saidas!C:C,Saidas!A:A,'Cadastro-Estoque'!A:A,Saidas!B:B,CONCATENATE("<=",$G$2)))) -> 0 | K39: =#REF! -> #REF!
A40: 216-12X500 | B40: FLOCÃO MILHO M & K 12 X 500 | C40: FARDOS | D40: ADRAM | F40: 0 | G40: =IF(ISBLANK($G$2),SUMIFS(Entradas!C:C,Entradas!A:A,'Cadastro-Estoque'!A:A)-SUMIFS(Saidas!C:C,Saidas!A:A,'Cadastro-Estoque'!A:A),SUMIFS(Entradas!C:C,Entradas!A:A,'Cadastro-Estoque'!A:A,Entradas!B:B,CONCATENATE("<=",$G$2))-SUMIFS(Saidas!C:C,Saidas!A:A,'Cadastro-Estoque'!A:A,Saidas!B:B,CONCATENATE("<=",$G$2)))+F40 -> 0 | H40: =IF(ISBLANK($G$2),SUMIFS(Entradas!E:E,Entradas!A:A,'Cadastro-Estoque'!A:A),SUMIFS(Entradas!E:E,Entradas!A:A,'Cadastro-Estoque'!A:A,Entradas!B:B,CONCATENATE("<=",$G$2)))/IF(IF(ISBLANK($G$2),SUMIFS(Entradas!C:C,Entradas!A:A,'Cadastro-Estoque'!A:A),SUMIFS(Entradas!C:C,Entradas!A:A,'Cadastro-Estoque'!A:A,Entradas!B:B,CONCATENATE("<=",$G$2)))=0,1,IF(ISBLANK($G$2),SUMIFS(Entradas!C:C,Entradas!A:A,'Cadastro-Estoque'!A:A),SUMIFS(Entradas!C:C,Entradas!A:A,'Cadastro-Estoque'!A:A,Entradas!B:B,CONCATENATE("<=",$G$2)))) -> 0 | I40: =IF(ISBLANK($G$2),SUMIFS(Saidas!E:E,Saidas!A:A,'Cadastro-Estoque'!A:A),SUMIFS(Saidas!E:E,Saidas!A:A,'Cadastro-Estoque'!A:A,Saidas!B:B,CONCATENATE("<=",$G$2)))/IF(IF(ISBLANK($G$2),SUMIFS(Saidas!C:C,Saidas!A:A,'Cadastro-Estoque'!A:A),SUMIFS(Saidas!C:C,Saidas!A:A,'Cadastro-Estoque'!A:A,Saidas!B:B,CONCATENATE("<=",$G$2)))=0,1,IF(ISBLANK($G$2),SUMIFS(Saidas!C:C,Saidas!A:A,'Cadastro-Estoque'!A:A),SUMIFS(Saidas!C:C,Saidas!A:A,'Cadastro-Estoque'!A:A,Saidas!B:B,CONCATENATE("<=",$G$2)))) -> 0 | K40: =#REF! -> #REF!
A41: 218-12X500 | B41: FLOCÃO MILHO CBS 12 X 500 | C41: FARDOS | D41: ADRAM | F41: 0 | G41: =IF(ISBLANK($G$2),SUMIFS(Entradas!C:C,Entradas!A:A,'Cadastro-Estoque'!A:A)-SUMIFS(Saidas!C:C,Saidas!A:A,'Cadastro-Estoque'!A:A),SUMIFS(Entradas!C:C,Entradas!A:A,'Cadastro-Estoque'!A:A,Entradas!B:B,CONCATENATE("<=",$G$2))-SUMIFS(Saidas!C:C,Saidas!A:A,'Cadastro-Estoque'!A:A,Saidas!B:B,CONCATENATE("<=",$G$2)))+F41 -> 0 | H41: =IF(ISBLANK($G$2),SUMIFS(Entradas!E:E,Entradas!A:A,'Cadastro-Estoque'!A:A),SUMIFS(Entradas!E:E,Entradas!A:A,'Cadastro-Estoque'!A:A,Entradas!B:B,CONCATENATE("<=",$G$2)))/IF(IF(ISBLANK($G$2),SUMIFS(Entradas!C:C,Entradas!A:A,'Cadastro-Estoque'!A:A),SUMIFS(Entradas!C:C,Entradas!A:A,'Cadastro-Estoque'!A:A,Entradas!B:B,CONCATENATE("<=",$G$2)))=0,1,IF(ISBLANK($G$2),SUMIFS(Entradas!C:C,Entradas!A:A,'Cadastro-Estoque'!A:A),SUMIFS(Entradas!C:C,Entradas!A:A,'Cadastro-Estoque'!A:A,Entradas!B:B,CONCATENATE("<=",$G$2)))) -> 0 | I41: =IF(ISBLANK($G$2),SUMIFS(Saidas!E:E,Saidas!A:A,'Cadastro-Estoque'!A:A),SUMIFS(Saidas!E:E,Saidas!A:A,'Cadastro-Estoque'!A:A,Saidas!B:B,CONCATENATE("<=",$G$2)))/IF(IF(ISBLANK($G$2),SUMIFS(Saidas!C:C,Saidas!A:A,'Cadastro-Estoque'!A:A),SUMIFS(Saidas!C:C,Saidas!A:A,'Cadastro-Estoque'!A:A,Saidas!B:B,CONCATENATE("<=",$G$2)))=0,1,IF(ISBLANK($G$2),SUMIFS(Saidas!C:C,Saidas!A:A,'Cadastro-Estoque'!A:A),SUMIFS(Saidas!C:C,Saidas!A:A,'Cadastro-Estoque'!A:A,Saidas!B:B,CONCATENATE("<=",$G$2)))) -> 0 | K41: =#REF! -> #REF!
A42: 220-20X500 | B42: FLOCÃO MILHO CORDEIRO 20 X 500 | C42: FARDOS | D42: ADRAM | F42: 0 | G42: =IF(ISBLANK($G$2),SUMIFS(Entradas!C:C,Entradas!A:A,'Cadastro-Estoque'!A:A)-SUMIFS(Saidas!C:C,Saidas!A:A,'Cadastro-Estoque'!A:A),SUMIFS(Entradas!C:C,Entradas!A:A,'Cadastro-Estoque'!A:A,Entradas!B:B,CONCATENATE("<=",$G$2))-SUMIFS(Saidas!C:C,Saidas!A:A,'Cadastro-Estoque'!A:A,Saidas!B:B,CONCATENATE("<=",$G$2)))+F42 -> 0 | H42: =IF(ISBLANK($G$2),SUMIFS(Entradas!E:E,Entradas!A:A,'Cadastro-Estoque'!A:A),SUMIFS(Entradas!E:E,Entradas!A:A,'Cadastro-Estoque'!A:A,Entradas!B:B,CONCATENATE("<=",$G$2)))/IF(IF(ISBLANK($G$2),SUMIFS(Entradas!C:C,Entradas!A:A,'Cadastro-Estoque'!A:A),SUMIFS(Entradas!C:C,Entradas!A:A,'Cadastro-Estoque'!A:A,Entradas!B:B,CONCATENATE("<=",$G$2)))=0,1,IF(ISBLANK($G$2),SUMIFS(Entradas!C:C,Entradas!A:A,'Cadastro-Estoque'!A:A),SUMIFS(Entradas!C:C,Entradas!A:A,'Cadastro-Estoque'!A:A,Entradas!B:B,CONCATENATE("<=",$G$2)))) -> 0 | I42: =IF(ISBLANK($G$2),SUMIFS(Saidas!E:E,Saidas!A:A,'Cadastro-Estoque'!A:A),SUMIFS(Saidas!E:E,Saidas!A:A,'Cadastro-Estoque'!A:A,Saidas!B:B,CONCATENATE("<=",$G$2)))/IF(IF(ISBLANK($G$2),SUMIFS(Saidas!C:C,Saidas!A:A,'Cadastro-Estoque'!A:A),SUMIFS(Saidas!C:C,Saidas!A:A,'Cadastro-Estoque'!A:A,Saidas!B:B,CONCATENATE("<=",$G$2)))=0,1,IF(ISBLANK($G$2),SUMIFS(Saidas!C:C,Saidas!A:A,'Cadastro-Estoque'!A:A),SUMIFS(Saidas!C:C,Saidas!A:A,'Cadastro-Estoque'!A:A,Saidas!B:B,CONCATENATE("<=",$G$2)))) -> 0 | K42: =#REF! -> #REF!
A43: 221-24X500 | B43: FLOCÃO MILHO PUBLIC 24 X 500 | C43: FARDOS | D43: ADRAM | F43: 0 | G43: =IF(ISBLANK($G$2),SUMIFS(Entradas!C:C,Entradas!A:A,'Cadastro-Estoque'!A:A)-SUMIFS(Saidas!C:C,Saidas!A:A,'Cadastro-Estoque'!A:A),SUMIFS(Entradas!C:C,Entradas!A:A,'Cadastro-Estoque'!A:A,Entradas!B:B,CONCATENATE("<=",$G$2))-SUMIFS(Saidas!C:C,Saidas!A:A,'Cadastro-Estoque'!A:A,Saidas!B:B,CONCATENATE("<=",$G$2)))+F43 -> 0 | H43: =IF(ISBLANK($G$2),SUMIFS(Entradas!E:E,Entradas!A:A,'Cadastro-Estoque'!A:A),SUMIFS(Entradas!E:E,Entradas!A:A,'Cadastro-Estoque'!A:A,Entradas!B:B,CONCATENATE("<=",$G$2)))/IF(IF(ISBLANK($G$2),SUMIFS(Entradas!C:C,Entradas!A:A,'Cadastro-Estoque'!A:A),SUMIFS(Entradas!C:C,Entradas!A:A,'Cadastro-Estoque'!A:A,Entradas!B:B,CONCATENATE("<=",$G$2)))=0,1,IF(ISBLANK($G$2),SUMIFS(Entradas!C:C,Entradas!A:A,'Cadastro-Estoque'!A:A),SUMIFS(Entradas!C:C,Entradas!A:A,'Cadastro-Estoque'!A:A,Entradas!B:B,CONCATENATE("<=",$G$2)))) -> 0 | I43: =IF(ISBLANK($G$2),SUMIFS(Saidas!E:E,Saidas!A:A,'Cadastro-Estoque'!A:A),SUMIFS(Saidas!E:E,Saidas!A:A,'Cadastro-Estoque'!A:A,Saidas!B:B,CONCATENATE("<=",$G$2)))/IF(IF(ISBLANK($G$2),SUMIFS(Saidas!C:C,Saidas!A:A,'Cadastro-Estoque'!A:A),SUMIFS(Saidas!C:C,Saidas!A:A,'Cadastro-Estoque'!A:A,Saidas!B:B,CONCATENATE("<=",$G$2)))=0,1,IF(ISBLANK($G$2),SUMIFS(Saidas!C:C,Saidas!A:A,'Cadastro-Estoque'!A:A),SUMIFS(Saidas!C:C,Saidas!A:A,'Cadastro-Estoque'!A:A,Saidas!B:B,CONCATENATE("<=",$G$2)))) -> 0 | K43: =#REF! -> #REF!
A44: 222-12X500 | B44: FLOCÃO MILHO PANAMERICAN 12 X 500 | C44: FARDOS | D44: ADRAM | F44: 0 | G44: =IF(ISBLANK($G$2),SUMIFS(Entradas!C:C,Entradas!A:A,'Cadastro-Estoque'!A:A)-SUMIFS(Saidas!C:C,Saidas!A:A,'Cadastro-Estoque'!A:A),SUMIFS(Entradas!C:C,Entradas!A:A,'Cadastro-Estoque'!A:A,Entradas!B:B,CONCATENATE("<=",$G$2))-SUMIFS(Saidas!C:C,Saidas!A:A,'Cadastro-Estoque'!A:A,Saidas!B:B,CONCATENATE("<=",$G$2)))+F44 -> 0 | H44: =IF(ISBLANK($G$2),SUMIFS(Entradas!E:E,Entradas!A:A,'Cadastro-Estoque'!A:A),SUMIFS(Entradas!E:E,Entradas!A:A,'Cadastro-Estoque'!A:A,Entradas!B:B,CONCATENATE("<=",$G$2)))/IF(IF(ISBLANK($G$2),SUMIFS(Entradas!C:C,Entradas!A:A,'Cadastro-Estoque'!A:A),SUMIFS(Entradas!C:C,Entradas!A:A,'Cadastro-Estoque'!A:A,Entradas!B:B,CONCATENATE("<=",$G$2)))=0,1,IF(ISBLANK($G$2),SUMIFS(Entradas!C:C,Entradas!A:A,'Cadastro-Estoque'!A:A),SUMIFS(Entradas!C:C,Entradas!A:A,'Cadastro-Estoque'!A:A,Entradas!B:B,CONCATENATE("<=",$G$2)))) -> 0 | I44: =IF(ISBLANK($G$2),SUMIFS(Saidas!E:E,Saidas!A:A,'Cadastro-Estoque'!A:A),SUMIFS(Saidas!E:E,Saidas!A:A,'Cadastro-Estoque'!A:A,Saidas!B:B,CONCATENATE("<=",$G$2)))/IF(IF(ISBLANK($G$2),SUMIFS(Saidas!C:C,Saidas!A:A,'Cadastro-Estoque'!A:A),SUMIFS(Saidas!C:C,Saidas!A:A,'Cadastro-Estoque'!A:A,Saidas!B:B,CONCATENATE("<=",$G$2)))=0,1,IF(ISBLANK($G$2),SUMIFS(Saidas!C:C,Saidas!A:A,'Cadastro-Estoque'!A:A),SUMIFS(Saidas!C:C,Saidas!A:A,'Cadastro-Estoque'!A:A,Saidas!B:B,CONCATENATE("<=",$G$2)))) -> 0 | K44: =#REF! -> #REF!
A45: 223-12X500 | B45: FLOCÃO MILHO BEATRIZ 12 X 500 | C45: FARDOS | D45: ADRAM | F45: 0 | G45: =IF(ISBLANK($G$2),SUMIFS(Entradas!C:C,Entradas!A:A,'Cadastro-Estoque'!A:A)-SUMIFS(Saidas!C:C,Saidas!A:A,'Cadastro-Estoque'!A:A),SUMIFS(Entradas!C:C,Entradas!A:A,'Cadastro-Estoque'!A:A,Entradas!B:B,CONCATENATE("<=",$G$2))-SUMIFS(Saidas!C:C,Saidas!A:A,'Cadastro-Estoque'!A:A,Saidas!B:B,CONCATENATE("<=",$G$2)))+F45 -> 2805 | H45: =IF(ISBLANK($G$2),SUMIFS(Entradas!E:E,Entradas!A:A,'Cadastro-Estoque'!A:A),SUMIFS(Entradas!E:E,Entradas!A:A,'Cadastro-Estoque'!A:A,Entradas!B:B,CONCATENATE("<=",$G$2)))/IF(IF(ISBLANK($G$2),SUMIFS(Entradas!C:C,Entradas!A:A,'Cadastro-Estoque'!A:A),SUMIFS(Entradas!C:C,Entradas!A:A,'Cadastro-Estoque'!A:A,Entradas!B:B,CONCATENATE("<=",$G$2)))=0,1,IF(ISBLANK($G$2),SUMIFS(Entradas!C:C,Entradas!A:A,'Cadastro-Estoque'!A:A),SUMIFS(Entradas!C:C,Entradas!A:A,'Cadastro-Estoque'!A:A,Entradas!B:B,CONCATENATE("<=",$G$2)))) -> 0 | I45: =IF(ISBLANK($G$2),SUMIFS(Saidas!E:E,Saidas!A:A,'Cadastro-Estoque'!A:A),SUMIFS(Saidas!E:E,Saidas!A:A,'Cadastro-Estoque'!A:A,Saidas!B:B,CONCATENATE("<=",$G$2)))/IF(IF(ISBLANK($G$2),SUMIFS(Saidas!C:C,Saidas!A:A,'Cadastro-Estoque'!A:A),SUMIFS(Saidas!C:C,Saidas!A:A,'Cadastro-Estoque'!A:A,Saidas!B:B,CONCATENATE("<=",$G$2)))=0,1,IF(ISBLANK($G$2),SUMIFS(Saidas!C:C,Saidas!A:A,'Cadastro-Estoque'!A:A),SUMIFS(Saidas!C:C,Saidas!A:A,'Cadastro-Estoque'!A:A,Saidas!B:B,CONCATENATE("<=",$G$2)))) -> 0 | K45: =#REF! -> #REF!
A46: 224-20X500 | B46: FLOCÃO MILHO CINDERELA 20 X 500 | C46: FARDOS | D46: ADRAM | F46: 1 | G46: =IF(ISBLANK($G$2),SUMIFS(Entradas!C:C,Entradas!A:A,'Cadastro-Estoque'!A:A)-SUMIFS(Saidas!C:C,Saidas!A:A,'Cadastro-Estoque'!A:A),SUMIFS(Entradas!C:C,Entradas!A:A,'Cadastro-Estoque'!A:A,Entradas!B:B,CONCATENATE("<=",$G$2))-SUMIFS(Saidas!C:C,Saidas!A:A,'Cadastro-Estoque'!A:A,Saidas!B:B,CONCATENATE("<=",$G$2)))+F46 -> -199 | H46: =IF(ISBLANK($G$2),SUMIFS(Entradas!E:E,Entradas!A:A,'Cadastro-Estoque'!A:A),SUMIFS(Entradas!E:E,Entradas!A:A,'Cadastro-Estoque'!A:A,Entradas!B:B,CONCATENATE("<=",$G$2)))/IF(IF(ISBLANK($G$2),SUMIFS(Entradas!C:C,Entradas!A:A,'Cadastro-Estoque'!A:A),SUMIFS(Entradas!C:C,Entradas!A:A,'Cadastro-Estoque'!A:A,Entradas!B:B,CONCATENATE("<=",$G$2)))=0,1,IF(ISBLANK($G$2),SUMIFS(Entradas!C:C,Entradas!A:A,'Cadastro-Estoque'!A:A),SUMIFS(Entradas!C:C,Entradas!A:A,'Cadastro-Estoque'!A:A,Entradas!B:B,CONCATENATE("<=",$G$2)))) -> 0 | I46: =IF(ISBLANK($G$2),SUMIFS(Saidas!E:E,Saidas!A:A,'Cadastro-Estoque'!A:A),SUMIFS(Saidas!E:E,Saidas!A:A,'Cadastro-Estoque'!A:A,Saidas!B:B,CONCATENATE("<=",$G$2)))/IF(IF(ISBLANK($G$2),SUMIFS(Saidas!C:C,Saidas!A:A,'Cadastro-Estoque'!A:A),SUMIFS(Saidas!C:C,Saidas!A:A,'Cadastro-Estoque'!A:A,Saidas!B:B,CONCATENATE("<=",$G$2)))=0,1,IF(ISBLANK($G$2),SUMIFS(Saidas!C:C,Saidas!A:A,'Cadastro-Estoque'!A:A),SUMIFS(Saidas!C:C,Saidas!A:A,'Cadastro-Estoque'!A:A,Saidas!B:B,CONCATENATE("<=",$G$2)))) -> 0 | K46: =#REF! -> #REF!
A47: 226-20X500 | B47: FLOCÃO MILHO ATALAIA 20 X 500 | C47: FARDOS | D47: ADRAM | F47: 0 | G47: =IF(ISBLANK($G$2),SUMIFS(Entradas!C:C,Entradas!A:A,'Cadastro-Estoque'!A:A)-SUMIFS(Saidas!C:C,Saidas!A:A,'Cadastro-Estoque'!A:A),SUMIFS(Entradas!C:C,Entradas!A:A,'Cadastro-Estoque'!A:A,Entradas!B:B,CONCATENATE("<=",$G$2))-SUMIFS(Saidas!C:C,Saidas!A:A,'Cadastro-Estoque'!A:A,Saidas!B:B,CONCATENATE("<=",$G$2)))+F47 -> 0 | H47: =IF(ISBLANK($G$2),SUMIFS(Entradas!E:E,Entradas!A:A,'Cadastro-Estoque'!A:A),SUMIFS(Entradas!E:E,Entradas!A:A,'Cadastro-Estoque'!A:A,Entradas!B:B,CONCATENATE("<=",$G$2)))/IF(IF(ISBLANK($G$2),SUMIFS(Entradas!C:C,Entradas!A:A,'Cadastro-Estoque'!A:A),SUMIFS(Entradas!C:C,Entradas!A:A,'Cadastro-Estoque'!A:A,Entradas!B:B,CONCATENATE("<=",$G$2)))=0,1,IF(ISBLANK($G$2),SUMIFS(Entradas!C:C,Entradas!A:A,'Cadastro-Estoque'!A:A),SUMIFS(Entradas!C:C,Entradas!A:A,'Cadastro-Estoque'!A:A,Entradas!B:B,CONCATENATE("<=",$G$2)))) -> 0 | I47: =IF(ISBLANK($G$2),SUMIFS(Saidas!E:E,Saidas!A:A,'Cadastro-Estoque'!A:A),SUMIFS(Saidas!E:E,Saidas!A:A,'Cadastro-Estoque'!A:A,Saidas!B:B,CONCATENATE("<=",$G$2)))/IF(IF(ISBLANK($G$2),SUMIFS(Saidas!C:C,Saidas!A:A,'Cadastro-Estoque'!A:A),SUMIFS(Saidas!C:C,Saidas!A:A,'Cadastro-Estoque'!A:A,Saidas!B:B,CONCATENATE("<=",$G$2)))=0,1,IF(ISBLANK($G$2),SUMIFS(Saidas!C:C,Saidas!A:A,'Cadastro-Estoque'!A:A),SUMIFS(Saidas!C:C,Saidas!A:A,'Cadastro-Estoque'!A:A,Saidas!B:B,CONCATENATE("<=",$G$2)))) -> 0 | K47: =#REF! -> #REF!
A48: 227-20x500 | B48: FLOCÃO MILHO FRITZ E FRIDA 20 X 500 | C48: FARDOS | D48: ADRAM | F48: 0 | G48: =IF(ISBLANK($G$2),SUMIFS(Entradas!C:C,Entradas!A:A,'Cadastro-Estoque'!A:A)-SUMIFS(Saidas!C:C,Saidas!A:A,'Cadastro-Estoque'!A:A),SUMIFS(Entradas!C:C,Entradas!A:A,'Cadastro-Estoque'!A:A,Entradas!B:B,CONCATENATE("<=",$G$2))-SUMIFS(Saidas!C:C,Saidas!A:A,'Cadastro-Estoque'!A:A,Saidas!B:B,CONCATENATE("<=",$G$2)))+F48 -> 0 | H48: =IF(ISBLANK($G$2),SUMIFS(Entradas!E:E,Entradas!A:A,'Cadastro-Estoque'!A:A),SUMIFS(Entradas!E:E,Entradas!A:A,'Cadastro-Estoque'!A:A,Entradas!B:B,CONCATENATE("<=",$G$2)))/IF(IF(ISBLANK($G$2),SUMIFS(Entradas!C:C,Entradas!A:A,'Cadastro-Estoque'!A:A),SUMIFS(Entradas!C:C,Entradas!A:A,'Cadastro-Estoque'!A:A,Entradas!B:B,CONCATENATE("<=",$G$2)))=0,1,IF(ISBLANK($G$2),SUMIFS(Entradas!C:C,Entradas!A:A,'Cadastro-Estoque'!A:A),SUMIFS(Entradas!C:C,Entradas!A:A,'Cadastro-Estoque'!A:A,Entradas!B:B,CONCATENATE("<=",$G$2)))) -> 0 | I48: =IF(ISBLANK($G$2),SUMIFS(Saidas!E:E,Saidas!A:A,'Cadastro-Estoque'!A:A),SUMIFS(Saidas!E:E,Saidas!A:A,'Cadastro-Estoque'!A:A,Saidas!B:B,CONCATENATE("<=",$G$2)))/IF(IF(ISBLANK($G$2),SUMIFS(Saidas!C:C,Saidas!A:A,'Cadastro-Estoque'!A:A),SUMIFS(Saidas!C:C,Saidas!A:A,'Cadastro-Estoque'!A:A,Saidas!B:B,CONCATENATE("<=",$G$2)))=0,1,IF(ISBLANK($G$2),SUMIFS(Saidas!C:C,Saidas!A:A,'Cadastro-Estoque'!A:A),SUMIFS(Saidas!C:C,Saidas!A:A,'Cadastro-Estoque'!A:A,Saidas!B:B,CONCATENATE("<=",$G$2)))) -> 0 | K48: =#REF! -> #REF!
A49: 229-20x500 | B49: FLOCÃO DE MILHO LAMPIONE 20 X 500 | C49: FARDOS | D49: ADRAM | F49: 0 | G49: =IF(ISBLANK($G$2),SUMIFS(Entradas!C:C,Entradas!A:A,'Cadastro-Estoque'!A:A)-SUMIFS(Saidas!C:C,Saidas!A:A,'Cadastro-Estoque'!A:A),SUMIFS(Entradas!C:C,Entradas!A:A,'Cadastro-Estoque'!A:A,Entradas!B:B,CONCATENATE("<=",$G$2))-SUMIFS(Saidas!C:C,Saidas!A:A,'Cadastro-Estoque'!A:A,Saidas!B:B,CONCATENATE("<=",$G$2)))+F49 -> 0 | H49: =IF(ISBLANK($G$2),SUMIFS(Entradas!E:E,Entradas!A:A,'Cadastro-Estoque'!A:A),SUMIFS(Entradas!E:E,Entradas!A:A,'Cadastro-Estoque'!A:A,Entradas!B:B,CONCATENATE("<=",$G$2)))/IF(IF(ISBLANK($G$2),SUMIFS(Entradas!C:C,Entradas!A:A,'Cadastro-Estoque'!A:A),SUMIFS(Entradas!C:C,Entradas!A:A,'Cadastro-Estoque'!A:A,Entradas!B:B,CONCATENATE("<=",$G$2)))=0,1,IF(ISBLANK($G$2),SUMIFS(Entradas!C:C,Entradas!A:A,'Cadastro-Estoque'!A:A),SUMIFS(Entradas!C:C,Entradas!A:A,'Cadastro-Estoque'!A:A,Entradas!B:B,CONCATENATE("<=",$G$2)))) -> 0 | I49: =IF(ISBLANK($G$2),SUMIFS(Saidas!E:E,Saidas!A:A,'Cadastro-Estoque'!A:A),SUMIFS(Saidas!E:E,Saidas!A:A,'Cadastro-Estoque'!A:A,Saidas!B:B,CONCATENATE("<=",$G$2)))/IF(IF(ISBLANK($G$2),SUMIFS(Saidas!C:C,Saidas!A:A,'Cadastro-Estoque'!A:A),SUMIFS(Saidas!C:C,Saidas!A:A,'Cadastro-Estoque'!A:A,Saidas!B:B,CONCATENATE("<=",$G$2)))=0,1,IF(ISBLANK($G$2),SUMIFS(Saidas!C:C,Saidas!A:A,'Cadastro-Estoque'!A:A),SUMIFS(Saidas!C:C,Saidas!A:A,'Cadastro-Estoque'!A:A,Saidas!B:B,CONCATENATE("<=",$G$2)))) -> 0 | K49: =#REF! -> #REF!
F50: 0 | G50: =IF(ISBLANK($G$2),SUMIFS(Entradas!C:C,Entradas!A:A,'Cadastro-Estoque'!A:A)-SUMIFS(Saidas!C:C,Saidas!A:A,'Cadastro-Estoque'!A:A),SUMIFS(Entradas!C:C,Entradas!A:A,'Cadastro-Estoque'!A:A,Entradas!B:B,CONCATENATE("<=",$G$2))-SUMIFS(Saidas!C:C,Saidas!A:A,'Cadastro-Estoque'!A:A,Saidas!B:B,CONCATENATE("<=",$G$2)))+F50 -> 0 | H50: =IF(ISBLANK($G$2),SUMIFS(Entradas!E:E,Entradas!A:A,'Cadastro-Estoque'!A:A),SUMIFS(Entradas!E:E,Entradas!A:A,'Cadastro-Estoque'!A:A,Entradas!B:B,CONCATENATE("<=",$G$2)))/IF(IF(ISBLANK($G$2),SUMIFS(Entradas!C:C,Entradas!A:A,'Cadastro-Estoque'!A:A),SUMIFS(Entradas!C:C,Entradas!A:A,'Cadastro-Estoque'!A:A,Entradas!B:B,CONCATENATE("<=",$G$2)))=0,1,IF(ISBLANK($G$2),SUMIFS(Entradas!C:C,Entradas!A:A,'Cadastro-Estoque'!A:A),SUMIFS(Entradas!C:C,Entradas!A:A,'Cadastro-Estoque'!A:A,Entradas!B:B,CONCATENATE("<=",$G$2)))) -> 0 | I50: =IF(ISBLANK($G$2),SUMIFS(Saidas!E:E,Saidas!A:A,'Cadastro-Estoque'!A:A),SUMIFS(Saidas!E:E,Saidas!A:A,'Cadastro-Estoque'!A:A,Saidas!B:B,CONCATENATE("<=",$G$2)))/IF(IF(ISBLANK($G$2),SUMIFS(Saidas!C:C,Saidas!A:A,'Cadastro-Estoque'!A:A),SUMIFS(Saidas!C:C,Saidas!A:A,'Cadastro-Estoque'!A:A,Saidas!B:B,CONCATENATE("<=",$G$2)))=0,1,IF(ISBLANK($G$2),SUMIFS(Saidas!C:C,Saidas!A:A,'Cadastro-Estoque'!A:A),SUMIFS(Saidas!C:C,Saidas!A:A,'Cadastro-Estoque'!A:A,Saidas!B:B,CONCATENATE("<=",$G$2)))) -> 0 | K50: =#REF! -> #REF!
A51: 204-20X500 | B51: FLOCÃO ARROZ NUTRIVITA 20 X 500 | C51: FARDOS | D51: ADRAM | F51: 1569 | G51: =IF(ISBLANK($G$2),SUMIFS(Entradas!C:C,Entradas!A:A,'Cadastro-Estoque'!A:A)-SUMIFS(Saidas!C:C,Saidas!A:A,'Cadastro-Estoque'!A:A),SUMIFS(Entradas!C:C,Entradas!A:A,'Cadastro-Estoque'!A:A,Entradas!B:B,CONCATENATE("<=",$G$2))-SUMIFS(Saidas!C:C,Saidas!A:A,'Cadastro-Estoque'!A:A,Saidas!B:B,CONCATENATE("<=",$G$2)))+F51 -> 1200 | H51: =IF(ISBLANK($G$2),SUMIFS(Entradas!E:E,Entradas!A:A,'Cadastro-Estoque'!A:A),SUMIFS(Entradas!E:E,Entradas!A:A,'Cadastro-Estoque'!A:A,Entradas!B:B,CONCATENATE("<=",$G$2)))/IF(IF(ISBLANK($G$2),SUMIFS(Entradas!C:C,Entradas!A:A,'Cadastro-Estoque'!A:A),SUMIFS(Entradas!C:C,Entradas!A:A,'Cadastro-Estoque'!A:A,Entradas!B:B,CONCATENATE("<=",$G$2)))=0,1,IF(ISBLANK($G$2),SUMIFS(Entradas!C:C,Entradas!A:A,'Cadastro-Estoque'!A:A),SUMIFS(Entradas!C:C,Entradas!A:A,'Cadastro-Estoque'!A:A,Entradas!B:B,CONCATENATE("<=",$G$2)))) -> 0 | I51: =IF(ISBLANK($G$2),SUMIFS(Saidas!E:E,Saidas!A:A,'Cadastro-Estoque'!A:A),SUMIFS(Saidas!E:E,Saidas!A:A,'Cadastro-Estoque'!A:A,Saidas!B:B,CONCATENATE("<=",$G$2)))/IF(IF(ISBLANK($G$2),SUMIFS(Saidas!C:C,Saidas!A:A,'Cadastro-Estoque'!A:A),SUMIFS(Saidas!C:C,Saidas!A:A,'Cadastro-Estoque'!A:A,Saidas!B:B,CONCATENATE("<=",$G$2)))=0,1,IF(ISBLANK($G$2),SUMIFS(Saidas!C:C,Saidas!A:A,'Cadastro-Estoque'!A:A),SUMIFS(Saidas!C:C,Saidas!A:A,'Cadastro-Estoque'!A:A,Saidas!B:B,CONCATENATE("<=",$G$2)))) -> 0 | K51: =#REF! -> #REF!
A52: 204-10X500 | B52: FLOCÃO ARROZ NUTRIVITA 10 X 500 | C52: FARDOS | D52: ADRAM | F52: 0 | G52: =IF(ISBLANK($G$2),SUMIFS(Entradas!C:C,Entradas!A:A,'Cadastro-Estoque'!A:A)-SUMIFS(Saidas!C:C,Saidas!A:A,'Cadastro-Estoque'!A:A),SUMIFS(Entradas!C:C,Entradas!A:A,'Cadastro-Estoque'!A:A,Entradas!B:B,CONCATENATE("<=",$G$2))-SUMIFS(Saidas!C:C,Saidas!A:A,'Cadastro-Estoque'!A:A,Saidas!B:B,CONCATENATE("<=",$G$2)))+F52 -> 0 | H52: =IF(ISBLANK($G$2),SUMIFS(Entradas!E:E,Entradas!A:A,'Cadastro-Estoque'!A:A),SUMIFS(Entradas!E:E,Entradas!A:A,'Cadastro-Estoque'!A:A,Entradas!B:B,CONCATENATE("<=",$G$2)))/IF(IF(ISBLANK($G$2),SUMIFS(Entradas!C:C,Entradas!A:A,'Cadastro-Estoque'!A:A),SUMIFS(Entradas!C:C,Entradas!A:A,'Cadastro-Estoque'!A:A,Entradas!B:B,CONCATENATE("<=",$G$2)))=0,1,IF(ISBLANK($G$2),SUMIFS(Entradas!C:C,Entradas!A:A,'Cadastro-Estoque'!A:A),SUMIFS(Entradas!C:C,Entradas!A:A,'Cadastro-Estoque'!A:A,Entradas!B:B,CONCATENATE("<=",$G$2)))) -> 0 | I52: =IF(ISBLANK($G$2),SUMIFS(Saidas!E:E,Saidas!A:A,'Cadastro-Estoque'!A:A),SUMIFS(Saidas!E:E,Saidas!A:A,'Cadastro-Estoque'!A:A,Saidas!B:B,CONCATENATE("<=",$G$2)))/IF(IF(ISBLANK($G$2),SUMIFS(Saidas!C:C,Saidas!A:A,'Cadastro-Estoque'!A:A),SUMIFS(Saidas!C:C,Saidas!A:A,'Cadastro-Estoque'!A:A,Saidas!B:B,CONCATENATE("<=",$G$2)))=0,1,IF(ISBLANK($G$2),SUMIFS(Saidas!C:C,Saidas!A:A,'Cadastro-Estoque'!A:A),SUMIFS(Saidas!C:C,Saidas!A:A,'Cadastro-Estoque'!A:A,Saidas!B:B,CONCATENATE("<=",$G$2)))) -> 0 | K52: =#REF! -> #REF!
F53: 0 | G53: =IF(ISBLANK($G$2),SUMIFS(Entradas!C:C,Entradas!A:A,'Cadastro-Estoque'!A:A)-SUMIFS(Saidas!C:C,Saidas!A:A,'Cadastro-Estoque'!A:A),SUMIFS(Entradas!C:C,Entradas!A:A,'Cadastro-Estoque'!A:A,Entradas!B:B,CONCATENATE("<=",$G$2))-SUMIFS(Saidas!C:C,Saidas!A:A,'Cadastro-Estoque'!A:A,Saidas!B:B,CONCATENATE("<=",$G$2)))+F53 -> 0 | H53: =IF(ISBLANK($G$2),SUMIFS(Entradas!E:E,Entradas!A:A,'Cadastro-Estoque'!A:A),SUMIFS(Entradas!E:E,Entradas!A:A,'Cadastro-Estoque'!A:A,Entradas!B:B,CONCATENATE("<=",$G$2)))/IF(IF(ISBLANK($G$2),SUMIFS(Entradas!C:C,Entradas!A:A,'Cadastro-Estoque'!A:A),SUMIFS(Entradas!C:C,Entradas!A:A,'Cadastro-Estoque'!A:A,Entradas!B:B,CONCATENATE("<=",$G$2)))=0,1,IF(ISBLANK($G$2),SUMIFS(Entradas!C:C,Entradas!A:A,'Cadastro-Estoque'!A:A),SUMIFS(Entradas!C:C,Entradas!A:A,'Cadastro-Estoque'!A:A,Entradas!B:B,CONCATENATE("<=",$G$2)))) -> 0 | I53: =IF(ISBLANK($G$2),SUMIFS(Saidas!E:E,Saidas!A:A,'Cadastro-Estoque'!A:A),SUMIFS(Saidas!E:E,Saidas!A:A,'Cadastro-Estoque'!A:A,Saidas!B:B,CONCATENATE("<=",$G$2)))/IF(IF(ISBLANK($G$2),SUMIFS(Saidas!C:C,Saidas!A:A,'Cadastro-Estoque'!A:A),SUMIFS(Saidas!C:C,Saidas!A:A,'Cadastro-Estoque'!A:A,Saidas!B:B,CONCATENATE("<=",$G$2)))=0,1,IF(ISBLANK($G$2),SUMIFS(Saidas!C:C,Saidas!A:A,'Cadastro-Estoque'!A:A),SUMIFS(Saidas!C:C,Saidas!A:A,'Cadastro-Estoque'!A:A,Saidas!B:B,CONCATENATE("<=",$G$2)))) -> 0 | K53: =#REF! -> #REF!
A54: 057-12X1 | B54: FUBÁ KISABOR 12 X 1 K | C54: FARDOS | D54: ADRAM | F54: 0 | G54: =IF(ISBLANK($G$2),SUMIFS(Entradas!C:C,Entradas!A:A,'Cadastro-Estoque'!A:A)-SUMIFS(Saidas!C:C,Saidas!A:A,'Cadastro-Estoque'!A:A),SUMIFS(Entradas!C:C,Entradas!A:A,'Cadastro-Estoque'!A:A,Entradas!B:B,CONCATENATE("<=",$G$2))-SUMIFS(Saidas!C:C,Saidas!A:A,'Cadastro-Estoque'!A:A,Saidas!B:B,CONCATENATE("<=",$G$2)))+F54 -> 0 | H54: =IF(ISBLANK($G$2),SUMIFS(Entradas!E:E,Entradas!A:A,'Cadastro-Estoque'!A:A),SUMIFS(Entradas!E:E,Entradas!A:A,'Cadastro-Estoque'!A:A,Entradas!B:B,CONCATENATE("<=",$G$2)))/IF(IF(ISBLANK($G$2),SUMIFS(Entradas!C:C,Entradas!A:A,'Cadastro-Estoque'!A:A),SUMIFS(Entradas!C:C,Entradas!A:A,'Cadastro-Estoque'!A:A,Entradas!B:B,CONCATENATE("<=",$G$2)))=0,1,IF(ISBLANK($G$2),SUMIFS(Entradas!C:C,Entradas!A:A,'Cadastro-Estoque'!A:A),SUMIFS(Entradas!C:C,Entradas!A:A,'Cadastro-Estoque'!A:A,Entradas!B:B,CONCATENATE("<=",$G$2)))) -> 0 | I54: =IF(ISBLANK($G$2),SUMIFS(Saidas!E:E,Saidas!A:A,'Cadastro-Estoque'!A:A),SUMIFS(Saidas!E:E,Saidas!A:A,'Cadastro-Estoque'!A:A,Saidas!B:B,CONCATENATE("<=",$G$2)))/IF(IF(ISBLANK($G$2),SUMIFS(Saidas!C:C,Saidas!A:A,'Cadastro-Estoque'!A:A),SUMIFS(Saidas!C:C,Saidas!A:A,'Cadastro-Estoque'!A:A,Saidas!B:B,CONCATENATE("<=",$G$2)))=0,1,IF(ISBLANK($G$2),SUMIFS(Saidas!C:C,Saidas!A:A,'Cadastro-Estoque'!A:A),SUMIFS(Saidas!C:C,Saidas!A:A,'Cadastro-Estoque'!A:A,Saidas!B:B,CONCATENATE("<=",$G$2)))) -> 0 | K54: =#REF! -> #REF!
A55: 057-12X500 | B55: FUBÁ KISABOR 12 X 500 G | C55: FARDOS | D55: ADRAM | F55: 0 | G55: =IF(ISBLANK($G$2),SUMIFS(Entradas!C:C,Entradas!A:A,'Cadastro-Estoque'!A:A)-SUMIFS(Saidas!C:C,Saidas!A:A,'Cadastro-Estoque'!A:A),SUMIFS(Entradas!C:C,Entradas!A:A,'Cadastro-Estoque'!A:A,Entradas!B:B,CONCATENATE("<=",$G$2))-SUMIFS(Saidas!C:C,Saidas!A:A,'Cadastro-Estoque'!A:A,Saidas!B:B,CONCATENATE("<=",$G$2)))+F55 -> 0 | H55: =IF(ISBLANK($G$2),SUMIFS(Entradas!E:E,Entradas!A:A,'Cadastro-Estoque'!A:A),SUMIFS(Entradas!E:E,Entradas!A:A,'Cadastro-Estoque'!A:A,Entradas!B:B,CONCATENATE("<=",$G$2)))/IF(IF(ISBLANK($G$2),SUMIFS(Entradas!C:C,Entradas!A:A,'Cadastro-Estoque'!A:A),SUMIFS(Entradas!C:C,Entradas!A:A,'Cadastro-Estoque'!A:A,Entradas!B:B,CONCATENATE("<=",$G$2)))=0,1,IF(ISBLANK($G$2),SUMIFS(Entradas!C:C,Entradas!A:A,'Cadastro-Estoque'!A:A),SUMIFS(Entradas!C:C,Entradas!A:A,'Cadastro-Estoque'!A:A,Entradas!B:B,CONCATENATE("<=",$G$2)))) -> 0 | I55: =IF(ISBLANK($G$2),SUMIFS(Saidas!E:E,Saidas!A:A,'Cadastro-Estoque'!A:A),SUMIFS(Saidas!E:E,Saidas!A:A,'Cadastro-Estoque'!A:A,Saidas!B:B,CONCATENATE("<=",$G$2)))/IF(IF(ISBLANK($G$2),SUMIFS(Saidas!C:C,Saidas!A:A,'Cadastro-Estoque'!A:A),SUMIFS(Saidas!C:C,Saidas!A:A,'Cadastro-Estoque'!A:A,Saidas!B:B,CONCATENATE("<=",$G$2)))=0,1,IF(ISBLANK($G$2),SUMIFS(Saidas!C:C,Saidas!A:A,'Cadastro-Estoque'!A:A),SUMIFS(Saidas!C:C,Saidas!A:A,'Cadastro-Estoque'!A:A,Saidas!B:B,CONCATENATE("<=",$G$2)))) -> 0 | K55: =#REF! -> #REF!
A56: 057-24X500 | B56: FUBÁ KISABOR 24 X 500 G | C56: FARDOS | D56: ADRAM | F56: 0 | G56: =IF(ISBLANK($G$2),SUMIFS(Entradas!C:C,Entradas!A:A,'Cadastro-Estoque'!A:A)-SUMIFS(Saidas!C:C,Saidas!A:A,'Cadastro-Estoque'!A:A),SUMIFS(Entradas!C:C,Entradas!A:A,'Cadastro-Estoque'!A:A,Entradas!B:B,CONCATENATE("<=",$G$2))-SUMIFS(Saidas!C:C,Saidas!A:A,'Cadastro-Estoque'!A:A,Saidas!B:B,CONCATENATE("<=",$G$2)))+F56 -> 0 | H56: =IF(ISBLANK($G$2),SUMIFS(Entradas!E:E,Entradas!A:A,'Cadastro-Estoque'!A:A),SUMIFS(Entradas!E:E,Entradas!A:A,'Cadastro-Estoque'!A:A,Entradas!B:B,CONCATENATE("<=",$G$2)))/IF(IF(ISBLANK($G$2),SUMIFS(Entradas!C:C,Entradas!A:A,'Cadastro-Estoque'!A:A),SUMIFS(Entradas!C:C,Entradas!A:A,'Cadastro-Estoque'!A:A,Entradas!B:B,CONCATENATE("<=",$G$2)))=0,1,IF(ISBLANK($G$2),SUMIFS(Entradas!C:C,Entradas!A:A,'Cadastro-Estoque'!A:A),SUMIFS(Entradas!C:C,Entradas!A:A,'Cadastro-Estoque'!A:A,Entradas!B:B,CONCATENATE("<=",$G$2)))) -> 0 | I56: =IF(ISBLANK($G$2),SUMIFS(Saidas!E:E,Saidas!A:A,'Cadastro-Estoque'!A:A),SUMIFS(Saidas!E:E,Saidas!A:A,'Cadastro-Estoque'!A:A,Saidas!B:B,CONCATENATE("<=",$G$2)))/IF(IF(ISBLANK($G$2),SUMIFS(Saidas!C:C,Saidas!A:A,'Cadastro-Estoque'!A:A),SUMIFS(Saidas!C:C,Saidas!A:A,'Cadastro-Estoque'!A:A,Saidas!B:B,CONCATENATE("<=",$G$2)))=0,1,IF(ISBLANK($G$2),SUMIFS(Saidas!C:C,Saidas!A:A,'Cadastro-Estoque'!A:A),SUMIFS(Saidas!C:C,Saidas!A:A,'Cadastro-Estoque'!A:A,Saidas!B:B,CONCATENATE("<=",$G$2)))) -> 0 | K56: =#REF! -> #REF!
A57: 063-12X1 | B57: FUBÁ NUTRIVITA 12 X 1 K | C57: FARDOS | D57: ADRAM | F57: 345 | G57: =IF(ISBLANK($G$2),SUMIFS(Entradas!C:C,Entradas!A:A,'Cadastro-Estoque'!A:A)-SUMIFS(Saidas!C:C,Saidas!A:A,'Cadastro-Estoque'!A:A),SUMIFS(Entradas!C:C,Entradas!A:A,'Cadastro-Estoque'!A:A,Entradas!B:B,CONCATENATE("<=",$G$2))-SUMIFS(Saidas!C:C,Saidas!A:A,'Cadastro-Estoque'!A:A,Saidas!B:B,CONCATENATE("<=",$G$2)))+F57 -> 345 | H57: =IF(ISBLANK($G$2),SUMIFS(Entradas!E:E,Entradas!A:A,'Cadastro-Estoque'!A:A),SUMIFS(Entradas!E:E,Entradas!A:A,'Cadastro-Estoque'!A:A,Entradas!B:B,CONCATENATE("<=",$G$2)))/IF(IF(ISBLANK($G$2),SUMIFS(Entradas!C:C,Entradas!A:A,'Cadastro-Estoque'!A:A),SUMIFS(Entradas!C:C,Entradas!A:A,'Cadastro-Estoque'!A:A,Entradas!B:B,CONCATENATE("<=",$G$2)))=0,1,IF(ISBLANK($G$2),SUMIFS(Entradas!C:C,Entradas!A:A,'Cadastro-Estoque'!A:A),SUMIFS(Entradas!C:C,Entradas!A:A,'Cadastro-Estoque'!A:A,Entradas!B:B,CONCATENATE("<=",$G$2)))) -> 0 | I57: =IF(ISBLANK($G$2),SUMIFS(Saidas!E:E,Saidas!A:A,'Cadastro-Estoque'!A:A),SUMIFS(Saidas!E:E,Saidas!A:A,'Cadastro-Estoque'!A:A,Saidas!B:B,CONCATENATE("<=",$G$2)))/IF(IF(ISBLANK($G$2),SUMIFS(Saidas!C:C,Saidas!A:A,'Cadastro-Estoque'!A:A),SUMIFS(Saidas!C:C,Saidas!A:A,'Cadastro-Estoque'!A:A,Saidas!B:B,CONCATENATE("<=",$G$2)))=0,1,IF(ISBLANK($G$2),SUMIFS(Saidas!C:C,Saidas!A:A,'Cadastro-Estoque'!A:A),SUMIFS(Saidas!C:C,Saidas!A:A,'Cadastro-Estoque'!A:A,Saidas!B:B,CONCATENATE("<=",$G$2)))) -> 0 | K57: =#REF! -> #REF!
A58: 063-12X500 | B58: FUBÁ NUTRIVITA 12 X 500 G | C58: FARDOS | D58: ADRAM | F58: 0 | G58: =IF(ISBLANK($G$2),SUMIFS(Entradas!C:C,Entradas!A:A,'Cadastro-Estoque'!A:A)-SUMIFS(Saidas!C:C,Saidas!A:A,'Cadastro-Estoque'!A:A),SUMIFS(Entradas!C:C,Entradas!A:A,'Cadastro-Estoque'!A:A,Entradas!B:B,CONCATENATE("<=",$G$2))-SUMIFS(Saidas!C:C,Saidas!A:A,'Cadastro-Estoque'!A:A,Saidas!B:B,CONCATENATE("<=",$G$2)))+F58 -> 0 | H58: =IF(ISBLANK($G$2),SUMIFS(Entradas!E:E,Entradas!A:A,'Cadastro-Estoque'!A:A),SUMIFS(Entradas!E:E,Entradas!A:A,'Cadastro-Estoque'!A:A,Entradas!B:B,CONCATENATE("<=",$G$2)))/IF(IF(ISBLANK($G$2),SUMIFS(Entradas!C:C,Entradas!A:A,'Cadastro-Estoque'!A:A),SUMIFS(Entradas!C:C,Entradas!A:A,'Cadastro-Estoque'!A:A,Entradas!B:B,CONCATENATE("<=",$G$2)))=0,1,IF(ISBLANK($G$2),SUMIFS(Entradas!C:C,Entradas!A:A,'Cadastro-Estoque'!A:A),SUMIFS(Entradas!C:C,Entradas!A:A,'Cadastro-Estoque'!A:A,Entradas!B:B,CONCATENATE("<=",$G$2)))) -> 0 | I58: =IF(ISBLANK($G$2),SUMIFS(Saidas!E:E,Saidas!A:A,'Cadastro-Estoque'!A:A),SUMIFS(Saidas!E:E,Saidas!A:A,'Cadastro-Estoque'!A:A,Saidas!B:B,CONCATENATE("<=",$G$2)))/IF(IF(ISBLANK($G$2),SUMIFS(Saidas!C:C,Saidas!A:A,'Cadastro-Estoque'!A:A),SUMIFS(Saidas!C:C,Saidas!A:A,'Cadastro-Estoque'!A:A,Saidas!B:B,CONCATENATE("<=",$G$2)))=0,1,IF(ISBLANK($G$2),SUMIFS(Saidas!C:C,Saidas!A:A,'Cadastro-Estoque'!A:A),SUMIFS(Saidas!C:C,Saidas!A:A,'Cadastro-Estoque'!A:A,Saidas!B:B,CONCATENATE("<=",$G$2)))) -> 0 | K58: =#REF! -> #REF!
A59: 063-24X500 | B59: FUBÁ NUTRIVITA 24 X 500 G | C59: FARDOS | D59: ADRAM | F59: 136 | G59: =IF(ISBLANK($G$2),SUMIFS(Entradas!C:C,Entradas!A:A,'Cadastro-Estoque'!A:A)-SUMIFS(Saidas!C:C,Saidas!A:A,'Cadastro-Estoque'!A:A),SUMIFS(Entradas!C:C,Entradas!A:A,'Cadastro-Estoque'!A:A,Entradas!B:B,CONCATENATE("<=",$G$2))-SUMIFS(Saidas!C:C,Saidas!A:A,'Cadastro-Estoque'!A:A,Saidas!B:B,CONCATENATE("<=",$G$2)))+F59 -> 136 | H59: =IF(ISBLANK($G$2),SUMIFS(Entradas!E:E,Entradas!A:A,'Cadastro-Estoque'!A:A),SUMIFS(Entradas!E:E,Entradas!A:A,'Cadastro-Estoque'!A:A,Entradas!B:B,CONCATENATE("<=",$G$2)))/IF(IF(ISBLANK($G$2),SUMIFS(Entradas!C:C,Entradas!A:A,'Cadastro-Estoque'!A:A),SUMIFS(Entradas!C:C,Entradas!A:A,'Cadastro-Estoque'!A:A,Entradas!B:B,CONCATENATE("<=",$G$2)))=0,1,IF(ISBLANK($G$2),SUMIFS(Entradas!C:C,Entradas!A:A,'Cadastro-Estoque'!A:A),SUMIFS(Entradas!C:C,Entradas!A:A,'Cadastro-Estoque'!A:A,Entradas!B:B,CONCATENATE("<=",$G$2)))) -> 0 | I59: =IF(ISBLANK($G$2),SUMIFS(Saidas!E:E,Saidas!A:A,'Cadastro-Estoque'!A:A),SUMIFS(Saidas!E:E,Saidas!A:A,'Cadastro-Estoque'!A:A,Saidas!B:B,CONCATENATE("<=",$G$2)))/IF(IF(ISBLANK($G$2),SUMIFS(Saidas!C:C,Saidas!A:A,'Cadastro-Estoque'!A:A),SUMIFS(Saidas!C:C,Saidas!A:A,'Cadastro-Estoque'!A:A,Saidas!B:B,CONCATENATE("<=",$G$2)))=0,1,IF(ISBLANK($G$2),SUMIFS(Saidas!C:C,Saidas!A:A,'Cadastro-Estoque'!A:A),SUMIFS(Saidas!C:C,Saidas!A:A,'Cadastro-Estoque'!A:A,Saidas!B:B,CONCATENATE("<=",$G$2)))) -> 0 | K59: =#REF! -> #REF!
A60: 065-12X1 | B60: FARINHA FINA NUTRIVITA 12 X 1 K | C60: FARDOS | D60: ADRAM | F60: 0 | G60: =IF(ISBLANK($G$2),SUMIFS(Entradas!C:C,Entradas!A:A,'Cadastro-Estoque'!A:A)-SUMIFS(Saidas!C:C,Saidas!A:A,'Cadastro-Estoque'!A:A),SUMIFS(Entradas!C:C,Entradas!A:A,'Cadastro-Estoque'!A:A,Entradas!B:B,CONCATENATE("<=",$G$2))-SUMIFS(Saidas!C:C,Saidas!A:A,'Cadastro-Estoque'!A:A,Saidas!B:B,CONCATENATE("<=",$G$2)))+F60 -> 0 | H60: =IF(ISBLANK($G$2),SUMIFS(Entradas!E:E,Entradas!A:A,'Cadastro-Estoque'!A:A),SUMIFS(Entradas!E:E,Entradas!A:A,'Cadastro-Estoque'!A:A,Entradas!B:B,CONCATENATE("<=",$G$2)))/IF(IF(ISBLANK($G$2),SUMIFS(Entradas!C:C,Entradas!A:A,'Cadastro-Estoque'!A:A),SUMIFS(Entradas!C:C,Entradas!A:A,'Cadastro-Estoque'!A:A,Entradas!B:B,CONCATENATE("<=",$G$2)))=0,1,IF(ISBLANK($G$2),SUMIFS(Entradas!C:C,Entradas!A:A,'Cadastro-Estoque'!A:A),SUMIFS(Entradas!C:C,Entradas!A:A,'Cadastro-Estoque'!A:A,Entradas!B:B,CONCATENATE("<=",$G$2)))) -> 0 | I60: =IF(ISBLANK($G$2),SUMIFS(Saidas!E:E,Saidas!A:A,'Cadastro-Estoque'!A:A),SUMIFS(Saidas!E:E,Saidas!A:A,'Cadastro-Estoque'!A:A,Saidas!B:B,CONCATENATE("<=",$G$2)))/IF(IF(ISBLANK($G$2),SUMIFS(Saidas!C:C,Saidas!A:A,'Cadastro-Estoque'!A:A),SUMIFS(Saidas!C:C,Saidas!A:A,'Cadastro-Estoque'!A:A,Saidas!B:B,CONCATENATE("<=",$G$2)))=0,1,IF(ISBLANK($G$2),SUMIFS(Saidas!C:C,Saidas!A:A,'Cadastro-Estoque'!A:A),SUMIFS(Saidas!C:C,Saidas!A:A,'Cadastro-Estoque'!A:A,Saidas!B:B,CONCATENATE("<=",$G$2)))) -> 0 | K60: =#REF! -> #REF!
A61: 076-10X1 | B61: FARINHA FINA FRITZ E FRIDA 10 X 1 K | C61: FARDOS | D61: ADRAM | F61: 0 | G61: =IF(ISBLANK($G$2),SUMIFS(Entradas!C:C,Entradas!A:A,'Cadastro-Estoque'!A:A)-SUMIFS(Saidas!C:C,Saidas!A:A,'Cadastro-Estoque'!A:A),SUMIFS(Entradas!C:C,Entradas!A:A,'Cadastro-Estoque'!A:A,Entradas!B:B,CONCATENATE("<=",$G$2))-SUMIFS(Saidas!C:C,Saidas!A:A,'Cadastro-Estoque'!A:A,Saidas!B:B,CONCATENATE("<=",$G$2)))+F61 -> 0 | H61: =IF(ISBLANK($G$2),SUMIFS(Entradas!E:E,Entradas!A:A,'Cadastro-Estoque'!A:A),SUMIFS(Entradas!E:E,Entradas!A:A,'Cadastro-Estoque'!A:A,Entradas!B:B,CONCATENATE("<=",$G$2)))/IF(IF(ISBLANK($G$2),SUMIFS(Entradas!C:C,Entradas!A:A,'Cadastro-Estoque'!A:A),SUMIFS(Entradas!C:C,Entradas!A:A,'Cadastro-Estoque'!A:A,Entradas!B:B,CONCATENATE("<=",$G$2)))=0,1,IF(ISBLANK($G$2),SUMIFS(Entradas!C:C,Entradas!A:A,'Cadastro-Estoque'!A:A),SUMIFS(Entradas!C:C,Entradas!A:A,'Cadastro-Estoque'!A:A,Entradas!B:B,CONCATENATE("<=",$G$2)))) -> 0 | I61: =IF(ISBLANK($G$2),SUMIFS(Saidas!E:E,Saidas!A:A,'Cadastro-Estoque'!A:A),SUMIFS(Saidas!E:E,Saidas!A:A,'Cadastro-Estoque'!A:A,Saidas!B:B,CONCATENATE("<=",$G$2)))/IF(IF(ISBLANK($G$2),SUMIFS(Saidas!C:C,Saidas!A:A,'Cadastro-Estoque'!A:A),SUMIFS(Saidas!C:C,Saidas!A:A,'Cadastro-Estoque'!A:A,Saidas!B:B,CONCATENATE("<=",$G$2)))=0,1,IF(ISBLANK($G$2),SUMIFS(Saidas!C:C,Saidas!A:A,'Cadastro-Estoque'!A:A),SUMIFS(Saidas!C:C,Saidas!A:A,'Cadastro-Estoque'!A:A,Saidas!B:B,CONCATENATE("<=",$G$2)))) -> 0 | K61: =#REF! -> #REF!
F62: 0 | G62: =IF(ISBLANK($G$2),SUMIFS(Entradas!C:C,Entradas!A:A,'Cadastro-Estoque'!A:A)-SUMIFS(Saidas!C:C,Saidas!A:A,'Cadastro-Estoque'!A:A),SUMIFS(Entradas!C:C,Entradas!A:A,'Cadastro-Estoque'!A:A,Entradas!B:B,CONCATENATE("<=",$G$2))-SUMIFS(Saidas!C:C,Saidas!A:A,'Cadastro-Estoque'!A:A,Saidas!B:B,CONCATENATE("<=",$G$2)))+F62 -> 0 | H62: =IF(ISBLANK($G$2),SUMIFS(Entradas!E:E,Entradas!A:A,'Cadastro-Estoque'!A:A),SUMIFS(Entradas!E:E,Entradas!A:A,'Cadastro-Estoque'!A:A,Entradas!B:B,CONCATENATE("<=",$G$2)))/IF(IF(ISBLANK($G$2),SUMIFS(Entradas!C:C,Entradas!A:A,'Cadastro-Estoque'!A:A),SUMIFS(Entradas!C:C,Entradas!A:A,'Cadastro-Estoque'!A:A,Entradas!B:B,CONCATENATE("<=",$G$2)))=0,1,IF(ISBLANK($G$2),SUMIFS(Entradas!C:C,Entradas!A:A,'Cadastro-Estoque'!A:A),SUMIFS(Entradas!C:C,Entradas!A:A,'Cadastro-Estoque'!A:A,Entradas!B:B,CONCATENATE("<=",$G$2)))) -> 0 | I62: =IF(ISBLANK($G$2),SUMIFS(Saidas!E:E,Saidas!A:A,'Cadastro-Estoque'!A:A),SUMIFS(Saidas!E:E,Saidas!A:A,'Cadastro-Estoque'!A:A,Saidas!B:B,CONCATENATE("<=",$G$2)))/IF(IF(ISBLANK($G$2),SUMIFS(Saidas!C:C,Saidas!A:A,'Cadastro-Estoque'!A:A),SUMIFS(Saidas!C:C,Saidas!A:A,'Cadastro-Estoque'!A:A,Saidas!B:B,CONCATENATE("<=",$G$2)))=0,1,IF(ISBLANK($G$2),SUMIFS(Saidas!C:C,Saidas!A:A,'Cadastro-Estoque'!A:A),SUMIFS(Saidas!C:C,Saidas!A:A,'Cadastro-Estoque'!A:A,Saidas!B:B,CONCATENATE("<=",$G$2)))) -> 0 | K62: 0
A63: 066-12X1 | B63: FARINHA MÉDIA NUTRIVITA 12 X 1 K | C63: FARDOS | D63: ADRAM | F63: 0 | G63: =IF(ISBLANK($G$2),SUMIFS(Entradas!C:C,Entradas!A:A,'Cadastro-Estoque'!A:A)-SUMIFS(Saidas!C:C,Saidas!A:A,'Cadastro-Estoque'!A:A),SUMIFS(Entradas!C:C,Entradas!A:A,'Cadastro-Estoque'!A:A,Entradas!B:B,CONCATENATE("<=",$G$2))-SUMIFS(Saidas!C:C,Saidas!A:A,'Cadastro-Estoque'!A:A,Saidas!B:B,CONCATENATE("<=",$G$2)))+F63 -> 0 | H63: =IF(ISBLANK($G$2),SUMIFS(Entradas!E:E,Entradas!A:A,'Cadastro-Estoque'!A:A),SUMIFS(Entradas!E:E,Entradas!A:A,'Cadastro-Estoque'!A:A,Entradas!B:B,CONCATENATE("<=",$G$2)))/IF(IF(ISBLANK($G$2),SUMIFS(Entradas!C:C,Entradas!A:A,'Cadastro-Estoque'!A:A),SUMIFS(Entradas!C:C,Entradas!A:A,'Cadastro-Estoque'!A:A,Entradas!B:B,CONCATENATE("<=",$G$2)))=0,1,IF(ISBLANK($G$2),SUMIFS(Entradas!C:C,Entradas!A:A,'Cadastro-Estoque'!A:A),SUMIFS(Entradas!C:C,Entradas!A:A,'Cadastro-Estoque'!A:A,Entradas!B:B,CONCATENATE("<=",$G$2)))) -> 0 | I63: =IF(ISBLANK($G$2),SUMIFS(Saidas!E:E,Saidas!A:A,'Cadastro-Estoque'!A:A),SUMIFS(Saidas!E:E,Saidas!A:A,'Cadastro-Estoque'!A:A,Saidas!B:B,CONCATENATE("<=",$G$2)))/IF(IF(ISBLANK($G$2),SUMIFS(Saidas!C:C,Saidas!A:A,'Cadastro-Estoque'!A:A),SUMIFS(Saidas!C:C,Saidas!A:A,'Cadastro-Estoque'!A:A,Saidas!B:B,CONCATENATE("<=",$G$2)))=0,1,IF(ISBLANK($G$2),SUMIFS(Saidas!C:C,Saidas!A:A,'Cadastro-Estoque'!A:A),SUMIFS(Saidas!C:C,Saidas!A:A,'Cadastro-Estoque'!A:A,Saidas!B:B,CONCATENATE("<=",$G$2)))) -> 0 | K63: =#REF! -> #REF!
A64: 068-12X1 | B64: FARINHA MÉDIA PERDIZ 12 X 1 K | C64: FARDOS | D64: ADRAM | F64: 0 | G64: =IF(ISBLANK($G$2),SUMIFS(Entradas!C:C,Entradas!A:A,'Cadastro-Estoque'!A:A)-SUMIFS(Saidas!C:C,Saidas!A:A,'Cadastro-Estoque'!A:A),SUMIFS(Entradas!C:C,Entradas!A:A,'Cadastro-Estoque'!A:A,Entradas!B:B,CONCATENATE("<=",$G$2))-SUMIFS(Saidas!C:C,Saidas!A:A,'Cadastro-Estoque'!A:A,Saidas!B:B,CONCATENATE("<=",$G$2)))+F64 -> 0 | H64: =IF(ISBLANK($G$2),SUMIFS(Entradas!E:E,Entradas!A:A,'Cadastro-Estoque'!A:A),SUMIFS(Entradas!E:E,Entradas!A:A,'Cadastro-Estoque'!A:A,Entradas!B:B,CONCATENATE("<=",$G$2)))/IF(IF(ISBLANK($G$2),SUMIFS(Entradas!C:C,Entradas!A:A,'Cadastro-Estoque'!A:A),SUMIFS(Entradas!C:C,Entradas!A:A,'Cadastro-Estoque'!A:A,Entradas!B:B,CONCATENATE("<=",$G$2)))=0,1,IF(ISBLANK($G$2),SUMIFS(Entradas!C:C,Entradas!A:A,'Cadastro-Estoque'!A:A),SUMIFS(Entradas!C:C,Entradas!A:A,'Cadastro-Estoque'!A:A,Entradas!B:B,CONCATENATE("<=",$G$2)))) -> 0 | I64: =IF(ISBLANK($G$2),SUMIFS(Saidas!E:E,Saidas!A:A,'Cadastro-Estoque'!A:A),SUMIFS(Saidas!E:E,Saidas!A:A,'Cadastro-Estoque'!A:A,Saidas!B:B,CONCATENATE("<=",$G$2)))/IF(IF(ISBLANK($G$2),SUMIFS(Saidas!C:C,Saidas!A:A,'Cadastro-Estoque'!A:A),SUMIFS(Saidas!C:C,Saidas!A:A,'Cadastro-Estoque'!A:A,Saidas!B:B,CONCATENATE("<=",$G$2)))=0,1,IF(ISBLANK($G$2),SUMIFS(Saidas!C:C,Saidas!A:A,'Cadastro-Estoque'!A:A),SUMIFS(Saidas!C:C,Saidas!A:A,'Cadastro-Estoque'!A:A,Saidas!B:B,CONCATENATE("<=",$G$2)))) -> 0 | K64: =#REF! -> #REF!
A65: 068-12X500 | B65: FARINHA MÉDIA PERDIZ 12 X 500G | C65: FARDOS | D65: ADRAM | F65: 0 | G65: =IF(ISBLANK($G$2),SUMIFS(Entradas!C:C,Entradas!A:A,'Cadastro-Estoque'!A:A)-SUMIFS(Saidas!C:C,Saidas!A:A,'Cadastro-Estoque'!A:A),SUMIFS(Entradas!C:C,Entradas!A:A,'Cadastro-Estoque'!A:A,Entradas!B:B,CONCATENATE("<=",$G$2))-SUMIFS(Saidas!C:C,Saidas!A:A,'Cadastro-Estoque'!A:A,Saidas!B:B,CONCATENATE("<=",$G$2)))+F65 -> 0 | H65: =IF(ISBLANK($G$2),SUMIFS(Entradas!E:E,Entradas!A:A,'Cadastro-Estoque'!A:A),SUMIFS(Entradas!E:E,Entradas!A:A,'Cadastro-Estoque'!A:A,Entradas!B:B,CONCATENATE("<=",$G$2)))/IF(IF(ISBLANK($G$2),SUMIFS(Entradas!C:C,Entradas!A:A,'Cadastro-Estoque'!A:A),SUMIFS(Entradas!C:C,Entradas!A:A,'Cadastro-Estoque'!A:A,Entradas!B:B,CONCATENATE("<=",$G$2)))=0,1,IF(ISBLANK($G$2),SUMIFS(Entradas!C:C,Entradas!A:A,'Cadastro-Estoque'!A:A),SUMIFS(Entradas!C:C,Entradas!A:A,'Cadastro-Estoque'!A:A,Entradas!B:B,CONCATENATE("<=",$G$2)))) -> 0 | I65: =IF(ISBLANK($G$2),SUMIFS(Saidas!E:E,Saidas!A:A,'Cadastro-Estoque'!A:A),SUMIFS(Saidas!E:E,Saidas!A:A,'Cadastro-Estoque'!A:A,Saidas!B:B,CONCATENATE("<=",$G$2)))/IF(IF(ISBLANK($G$2),SUMIFS(Saidas!C:C,Saidas!A:A,'Cadastro-Estoque'!A:A),SUMIFS(Saidas!C:C,Saidas!A:A,'Cadastro-Estoque'!A:A,Saidas!B:B,CONCATENATE("<=",$G$2)))=0,1,IF(ISBLANK($G$2),SUMIFS(Saidas!C:C,Saidas!A:A,'Cadastro-Estoque'!A:A),SUMIFS(Saidas!C:C,Saidas!A:A,'Cadastro-Estoque'!A:A,Saidas!B:B,CONCATENATE("<=",$G$2)))) -> 0 | K65: =#REF! -> #REF!
A66: 068-6X1 | B66: FARINHA MÉDIA PERDIZ 06 X 1 K | C66: FARDOS | D66: ADRAM | F66: 0 | G66: =IF(ISBLANK($G$2),SUMIFS(Entradas!C:C,Entradas!A:A,'Cadastro-Estoque'!A:A)-SUMIFS(Saidas!C:C,Saidas!A:A,'Cadastro-Estoque'!A:A),SUMIFS(Entradas!C:C,Entradas!A:A,'Cadastro-Estoque'!A:A,Entradas!B:B,CONCATENATE("<=",$G$2))-SUMIFS(Saidas!C:C,Saidas!A:A,'Cadastro-Estoque'!A:A,Saidas!B:B,CONCATENATE("<=",$G$2)))+F66 -> 0 | H66: =IF(ISBLANK($G$2),SUMIFS(Entradas!E:E,Entradas!A:A,'Cadastro-Estoque'!A:A),SUMIFS(Entradas!E:E,Entradas!A:A,'Cadastro-Estoque'!A:A,Entradas!B:B,CONCATENATE("<=",$G$2)))/IF(IF(ISBLANK($G$2),SUMIFS(Entradas!C:C,Entradas!A:A,'Cadastro-Estoque'!A:A),SUMIFS(Entradas!C:C,Entradas!A:A,'Cadastro-Estoque'!A:A,Entradas!B:B,CONCATENATE("<=",$G$2)))=0,1,IF(ISBLANK($G$2),SUMIFS(Entradas!C:C,Entradas!A:A,'Cadastro-Estoque'!A:A),SUMIFS(Entradas!C:C,Entradas!A:A,'Cadastro-Estoque'!A:A,Entradas!B:B,CONCATENATE("<=",$G$2)))) -> 0 | I66: =IF(ISBLANK($G$2),SUMIFS(Saidas!E:E,Saidas!A:A,'Cadastro-Estoque'!A:A),SUMIFS(Saidas!E:E,Saidas!A:A,'Cadastro-Estoque'!A:A,Saidas!B:B,CONCATENATE("<=",$G$2)))/IF(IF(ISBLANK($G$2),SUMIFS(Saidas!C:C,Saidas!A:A,'Cadastro-Estoque'!A:A),SUMIFS(Saidas!C:C,Saidas!A:A,'Cadastro-Estoque'!A:A,Saidas!B:B,CONCATENATE("<=",$G$2)))=0,1,IF(ISBLANK($G$2),SUMIFS(Saidas!C:C,Saidas!A:A,'Cadastro-Estoque'!A:A),SUMIFS(Saidas!C:C,Saidas!A:A,'Cadastro-Estoque'!A:A,Saidas!B:B,CONCATENATE("<=",$G$2)))) -> 0 | K66: =#REF! -> #REF!
A67: 073-10X1 | B67: FARINHA MÉDIA FRITZ E FRIDA 10 X 1 K | C67: FARDOS | D67: ADRAM | F67: 0 | G67: =IF(ISBLANK($G$2),SUMIFS(Entradas!C:C,Entradas!A:A,'Cadastro-Estoque'!A:A)-SUMIFS(Saidas!C:C,Saidas!A:A,'Cadastro-Estoque'!A:A),SUMIFS(Entradas!C:C,Entradas!A:A,'Cadastro-Estoque'!A:A,Entradas!B:B,CONCATENATE("<=",$G$2))-SUMIFS(Saidas!C:C,Saidas!A:A,'Cadastro-Estoque'!A:A,Saidas!B:B,CONCATENATE("<=",$G$2)))+F67 -> 0 | H67: =IF(ISBLANK($G$2),SUMIFS(Entradas!E:E,Entradas!A:A,'Cadastro-Estoque'!A:A),SUMIFS(Entradas!E:E,Entradas!A:A,'Cadastro-Estoque'!A:A,Entradas!B:B,CONCATENATE("<=",$G$2)))/IF(IF(ISBLANK($G$2),SUMIFS(Entradas!C:C,Entradas!A:A,'Cadastro-Estoque'!A:A),SUMIFS(Entradas!C:C,Entradas!A:A,'Cadastro-Estoque'!A:A,Entradas!B:B,CONCATENATE("<=",$G$2)))=0,1,IF(ISBLANK($G$2),SUMIFS(Entradas!C:C,Entradas!A:A,'Cadastro-Estoque'!A:A),SUMIFS(Entradas!C:C,Entradas!A:A,'Cadastro-Estoque'!A:A,Entradas!B:B,CONCATENATE("<=",$G$2)))) -> 0 | I67: =IF(ISBLANK($G$2),SUMIFS(Saidas!E:E,Saidas!A:A,'Cadastro-Estoque'!A:A),SUMIFS(Saidas!E:E,Saidas!A:A,'Cadastro-Estoque'!A:A,Saidas!B:B,CONCATENATE("<=",$G$2)))/IF(IF(ISBLANK($G$2),SUMIFS(Saidas!C:C,Saidas!A:A,'Cadastro-Estoque'!A:A),SUMIFS(Saidas!C:C,Saidas!A:A,'Cadastro-Estoque'!A:A,Saidas!B:B,CONCATENATE("<=",$G$2)))=0,1,IF(ISBLANK($G$2),SUMIFS(Saidas!C:C,Saidas!A:A,'Cadastro-Estoque'!A:A),SUMIFS(Saidas!C:C,Saidas!A:A,'Cadastro-Estoque'!A:A,Saidas!B:B,CONCATENATE("<=",$G$2)))) -> 0 | K67: =#REF! -> #REF!
F68: 0 | G68: =IF(ISBLANK($G$2),SUMIFS(Entradas!C:C,Entradas!A:A,'Cadastro-Estoque'!A:A)-SUMIFS(Saidas!C:C,Saidas!A:A,'Cadastro-Estoque'!A:A),SUMIFS(Entradas!C:C,Entradas!A:A,'Cadastro-Estoque'!A:A,Entradas!B:B,CONCATENATE("<=",$G$2))-SUMIFS(Saidas!C:C,Saidas!A:A,'Cadastro-Estoque'!A:A,Saidas!B:B,CONCATENATE("<=",$G$2)))+F68 -> 0 | H68: =IF(ISBLANK($G$2),SUMIFS(Entradas!E:E,Entradas!A:A,'Cadastro-Estoque'!A:A),SUMIFS(Entradas!E:E,Entradas!A:A,'Cadastro-Estoque'!A:A,Entradas!B:B,CONCATENATE("<=",$G$2)))/IF(IF(ISBLANK($G$2),SUMIFS(Entradas!C:C,Entradas!A:A,'Cadastro-Estoque'!A:A),SUMIFS(Entradas!C:C,Entradas!A:A,'Cadastro-Estoque'!A:A,Entradas!B:B,CONCATENATE("<=",$G$2)))=0,1,IF(ISBLANK($G$2),SUMIFS(Entradas!C:C,Entradas!A:A,'Cadastro-Estoque'!A:A),SUMIFS(Entradas!C:C,Entradas!A:A,'Cadastro-Estoque'!A:A,Entradas!B:B,CONCATENATE("<=",$G$2)))) -> 0 | I68: =IF(ISBLANK($G$2),SUMIFS(Saidas!E:E,Saidas!A:A,'Cadastro-Estoque'!A:A),SUMIFS(Saidas!E:E,Saidas!A:A,'Cadastro-Estoque'!A:A,Saidas!B:B,CONCATENATE("<=",$G$2)))/IF(IF(ISBLANK($G$2),SUMIFS(Saidas!C:C,Saidas!A:A,'Cadastro-Estoque'!A:A),SUMIFS(Saidas!C:C,Saidas!A:A,'Cadastro-Estoque'!A:A,Saidas!B:B,CONCATENATE("<=",$G$2)))=0,1,IF(ISBLANK($G$2),SUMIFS(Saidas!C:C,Saidas!A:A,'Cadastro-Estoque'!A:A),SUMIFS(Saidas!C:C,Saidas!A:A,'Cadastro-Estoque'!A:A,Saidas!B:B,CONCATENATE("<=",$G$2)))) -> 0 | K68: 0
A69: 067-12X1 | B69: FARINHA GROSSA NUTRIVITA 12 X 1 K | C69: FARDOS | D69: ADRAM | F69: 0 | G69: =IF(ISBLANK($G$2),SUMIFS(Entradas!C:C,Entradas!A:A,'Cadastro-Estoque'!A:A)-SUMIFS(Saidas!C:C,Saidas!A:A,'Cadastro-Estoque'!A:A),SUMIFS(Entradas!C:C,Entradas!A:A,'Cadastro-Estoque'!A:A,Entradas!B:B,CONCATENATE("<=",$G$2))-SUMIFS(Saidas!C:C,Saidas!A:A,'Cadastro-Estoque'!A:A,Saidas!B:B,CONCATENATE("<=",$G$2)))+F69 -> 0 | H69: =IF(ISBLANK($G$2),SUMIFS(Entradas!E:E,Entradas!A:A,'Cadastro-Estoque'!A:A),SUMIFS(Entradas!E:E,Entradas!A:A,'Cadastro-Estoque'!A:A,Entradas!B:B,CONCATENATE("<=",$G$2)))/IF(IF(ISBLANK($G$2),SUMIFS(Entradas!C:C,Entradas!A:A,'Cadastro-Estoque'!A:A),SUMIFS(Entradas!C:C,Entradas!A:A,'Cadastro-Estoque'!A:A,Entradas!B:B,CONCATENATE("<=",$G$2)))=0,1,IF(ISBLANK($G$2),SUMIFS(Entradas!C:C,Entradas!A:A,'Cadastro-Estoque'!A:A),SUMIFS(Entradas!C:C,Entradas!A:A,'Cadastro-Estoque'!A:A,Entradas!B:B,CONCATENATE("<=",$G$2)))) -> 0 | I69: =IF(ISBLANK($G$2),SUMIFS(Saidas!E:E,Saidas!A:A,'Cadastro-Estoque'!A:A),SUMIFS(Saidas!E:E,Saidas!A:A,'Cadastro-Estoque'!A:A,Saidas!B:B,CONCATENATE("<=",$G$2)))/IF(IF(ISBLANK($G$2),SUMIFS(Saidas!C:C,Saidas!A:A,'Cadastro-Estoque'!A:A),SUMIFS(Saidas!C:C,Saidas!A:A,'Cadastro-Estoque'!A:A,Saidas!B:B,CONCATENATE("<=",$G$2)))=0,1,IF(ISBLANK($G$2),SUMIFS(Saidas!C:C,Saidas!A:A,'Cadastro-Estoque'!A:A),SUMIFS(Saidas!C:C,Saidas!A:A,'Cadastro-Estoque'!A:A,Saidas!B:B,CONCATENATE("<=",$G$2)))) -> 0 | K69: =#REF! -> #REF!
A70: 069-12X1 | B70: FARINHA GROSSA PERDIZ 12 X 1 K | C70: FARDOS | D70: ADRAM | F70: 0 | G70: =IF(ISBLANK($G$2),SUMIFS(Entradas!C:C,Entradas!A:A,'Cadastro-Estoque'!A:A)-SUMIFS(Saidas!C:C,Saidas!A:A,'Cadastro-Estoque'!A:A),SUMIFS(Entradas!C:C,Entradas!A:A,'Cadastro-Estoque'!A:A,Entradas!B:B,CONCATENATE("<=",$G$2))-SUMIFS(Saidas!C:C,Saidas!A:A,'Cadastro-Estoque'!A:A,Saidas!B:B,CONCATENATE("<=",$G$2)))+F70 -> 0 | H70: =IF(ISBLANK($G$2),SUMIFS(Entradas!E:E,Entradas!A:A,'Cadastro-Estoque'!A:A),SUMIFS(Entradas!E:E,Entradas!A:A,'Cadastro-Estoque'!A:A,Entradas!B:B,CONCATENATE("<=",$G$2)))/IF(IF(ISBLANK($G$2),SUMIFS(Entradas!C:C,Entradas!A:A,'Cadastro-Estoque'!A:A),SUMIFS(Entradas!C:C,Entradas!A:A,'Cadastro-Estoque'!A:A,Entradas!B:B,CONCATENATE("<=",$G$2)))=0,1,IF(ISBLANK($G$2),SUMIFS(Entradas!C:C,Entradas!A:A,'Cadastro-Estoque'!A:A),SUMIFS(Entradas!C:C,Entradas!A:A,'Cadastro-Estoque'!A:A,Entradas!B:B,CONCATENATE("<=",$G$2)))) -> 0 | I70: =IF(ISBLANK($G$2),SUMIFS(Saidas!E:E,Saidas!A:A,'Cadastro-Estoque'!A:A),SUMIFS(Saidas!E:E,Saidas!A:A,'Cadastro-Estoque'!A:A,Saidas!B:B,CONCATENATE("<=",$G$2)))/IF(IF(ISBLANK($G$2),SUMIFS(Saidas!C:C,Saidas!A:A,'Cadastro-Estoque'!A:A),SUMIFS(Saidas!C:C,Saidas!A:A,'Cadastro-Estoque'!A:A,Saidas!B:B,CONCATENATE("<=",$G$2)))=0,1,IF(ISBLANK($G$2),SUMIFS(Saidas!C:C,Saidas!A:A,'Cadastro-Estoque'!A:A),SUMIFS(Saidas!C:C,Saidas!A:A,'Cadastro-Estoque'!A:A,Saidas!B:B,CONCATENATE("<=",$G$2)))) -> 0 | K70: =#REF! -> #REF!
A71: 069-6X1 | B71: FARINHA GROSSA PERDIZ 06 X 1 K | C71: FARDOS | D71: ADRAM | F71: 0 | G71: =IF(ISBLANK($G$2),SUMIFS(Entradas!C:C,Entradas!A:A,'Cadastro-Estoque'!A:A)-SUMIFS(Saidas!C:C,Saidas!A:A,'Cadastro-Estoque'!A:A),SUMIFS(Entradas!C:C,Entradas!A:A,'Cadastro-Estoque'!A:A,Entradas!B:B,CONCATENATE("<=",$G$2))-SUMIFS(Saidas!C:C,Saidas!A:A,'Cadastro-Estoque'!A:A,Saidas!B:B,CONCATENATE("<=",$G$2)))+F71 -> 0 | H71: =IF(ISBLANK($G$2),SUMIFS(Entradas!E:E,Entradas!A:A,'Cadastro-Estoque'!A:A),SUMIFS(Entradas!E:E,Entradas!A:A,'Cadastro-Estoque'!A:A,Entradas!B:B,CONCATENATE("<=",$G$2)))/IF(IF(ISBLANK($G$2),SUMIFS(Entradas!C:C,Entradas!A:A,'Cadastro-Estoque'!A:A),SUMIFS(Entradas!C:C,Entradas!A:A,'Cadastro-Estoque'!A:A,Entradas!B:B,CONCATENATE("<=",$G$2)))=0,1,IF(ISBLANK($G$2),SUMIFS(Entradas!C:C,Entradas!A:A,'Cadastro-Estoque'!A:A),SUMIFS(Entradas!C:C,Entradas!A:A,'Cadastro-Estoque'!A:A,Entradas!B:B,CONCATENATE("<=",$G$2)))) -> 0 | I71: =IF(ISBLANK($G$2),SUMIFS(Saidas!E:E,Saidas!A:A,'Cadastro-Estoque'!A:A),SUMIFS(Saidas!E:E,Saidas!A:A,'Cadastro-Estoque'!A:A,Saidas!B:B,CONCATENATE("<=",$G$2)))/IF(IF(ISBLANK($G$2),SUMIFS(Saidas!C:C,Saidas!A:A,'Cadastro-Estoque'!A:A),SUMIFS(Saidas!C:C,Saidas!A:A,'Cadastro-Estoque'!A:A,Saidas!B:B,CONCATENATE("<=",$G$2)))=0,1,IF(ISBLANK($G$2),SUMIFS(Saidas!C:C,Saidas!A:A,'Cadastro-Estoque'!A:A),SUMIFS(Saidas!C:C,Saidas!A:A,'Cadastro-Estoque'!A:A,Saidas!B:B,CONCATENATE("<=",$G$2)))) -> 0 | K71: =#REF! -> #REF!
A72: 074-10X1 | B72: FARINHA GROSSA FRITZ E FRIDA 10 X 1 K | C72: FARDOS | D72: ADRAM | F72: 0 | G72: =IF(ISBLANK($G$2),SUMIFS(Entradas!C:C,Entradas!A:A,'Cadastro-Estoque'!A:A)-SUMIFS(Saidas!C:C,Saidas!A:A,'Cadastro-Estoque'!A:A),SUMIFS(Entradas!C:C,Entradas!A:A,'Cadastro-Estoque'!A:A,Entradas!B:B,CONCATENATE("<=",$G$2))-SUMIFS(Saidas!C:C,Saidas!A:A,'Cadastro-Estoque'!A:A,Saidas!B:B,CONCATENATE("<=",$G$2)))+F72 -> 0 | H72: =IF(ISBLANK($G$2),SUMIFS(Entradas!E:E,Entradas!A:A,'Cadastro-Estoque'!A:A),SUMIFS(Entradas!E:E,Entradas!A:A,'Cadastro-Estoque'!A:A,Entradas!B:B,CONCATENATE("<=",$G$2)))/IF(IF(ISBLANK($G$2),SUMIFS(Entradas!C:C,Entradas!A:A,'Cadastro-Estoque'!A:A),SUMIFS(Entradas!C:C,Entradas!A:A,'Cadastro-Estoque'!A:A,Entradas!B:B,CONCATENATE("<=",$G$2)))=0,1,IF(ISBLANK($G$2),SUMIFS(Entradas!C:C,Entradas!A:A,'Cadastro-Estoque'!A:A),SUMIFS(Entradas!C:C,Entradas!A:A,'Cadastro-Estoque'!A:A,Entradas!B:B,CONCATENATE("<=",$G$2)))) -> 0 | I72: =IF(ISBLANK($G$2),SUMIFS(Saidas!E:E,Saidas!A:A,'Cadastro-Estoque'!A:A),SUMIFS(Saidas!E:E,Saidas!A:A,'Cadastro-Estoque'!A:A,Saidas!B:B,CONCATENATE("<=",$G$2)))/IF(IF(ISBLANK($G$2),SUMIFS(Saidas!C:C,Saidas!A:A,'Cadastro-Estoque'!A:A),SUMIFS(Saidas!C:C,Saidas!A:A,'Cadastro-Estoque'!A:A,Saidas!B:B,CONCATENATE("<=",$G$2)))=0,1,IF(ISBLANK($G$2),SUMIFS(Saidas!C:C,Saidas!A:A,'Cadastro-Estoque'!A:A),SUMIFS(Saidas!C:C,Saidas!A:A,'Cadastro-Estoque'!A:A,Saidas!B:B,CONCATENATE("<=",$G$2)))) -> 0 | K72: =#REF! -> #REF!
F73: 0 | G73: =IF(ISBLANK($G$2),SUMIFS(Entradas!C:C,Entradas!A:A,'Cadastro-Estoque'!A:A)-SUMIFS(Saidas!C:C,Saidas!A:A,'Cadastro-Estoque'!A:A),SUMIFS(Entradas!C:C,Entradas!A:A,'Cadastro-Estoque'!A:A,Entradas!B:B,CONCATENATE("<=",$G$2))-SUMIFS(Saidas!C:C,Saidas!A:A,'Cadastro-Estoque'!A:A,Saidas!B:B,CONCATENATE("<=",$G$2)))+F73 -> 0 | H73: =IF(ISBLANK($G$2),SUMIFS(Entradas!E:E,Entradas!A:A,'Cadastro-Estoque'!A:A),SUMIFS(Entradas!E:E,Entradas!A:A,'Cadastro-Estoque'!A:A,Entradas!B:B,CONCATENATE("<=",$G$2)))/IF(IF(ISBLANK($G$2),SUMIFS(Entradas!C:C,Entradas!A:A,'Cadastro-Estoque'!A:A),SUMIFS(Entradas!C:C,Entradas!A:A,'Cadastro-Estoque'!A:A,Entradas!B:B,CONCATENATE("<=",$G$2)))=0,1,IF(ISBLANK($G$2),SUMIFS(Entradas!C:C,Entradas!A:A,'Cadastro-Estoque'!A:A),SUMIFS(Entradas!C:C,Entradas!A:A,'Cadastro-Estoque'!A:A,Entradas!B:B,CONCATENATE("<=",$G$2)))) -> 0 | I73: =IF(ISBLANK($G$2),SUMIFS(Saidas!E:E,Saidas!A:A,'Cadastro-Estoque'!A:A),SUMIFS(Saidas!E:E,Saidas!A:A,'Cadastro-Estoque'!A:A,Saidas!B:B,CONCATENATE("<=",$G$2)))/IF(IF(ISBLANK($G$2),SUMIFS(Saidas!C:C,Saidas!A:A,'Cadastro-Estoque'!A:A),SUMIFS(Saidas!C:C,Saidas!A:A,'Cadastro-Estoque'!A:A,Saidas!B:B,CONCATENATE("<=",$G$2)))=0,1,IF(ISBLANK($G$2),SUMIFS(Saidas!C:C,Saidas!A:A,'Cadastro-Estoque'!A:A),SUMIFS(Saidas!C:C,Saidas!A:A,'Cadastro-Estoque'!A:A,Saidas!B:B,CONCATENATE("<=",$G$2)))) -> 0 | K73: 0
A74: 003-20X500 | B74: CANJICA MUNGUZÁ 20 X 500 | C74: FARDOS | D74: ADRAM | F74: 732 | G74: =IF(ISBLANK($G$2),SUMIFS(Entradas!C:C,Entradas!A:A,'Cadastro-Estoque'!A:A)-SUMIFS(Saidas!C:C,Saidas!A:A,'Cadastro-Estoque'!A:A),SUMIFS(Entradas!C:C,Entradas!A:A,'Cadastro-Estoque'!A:A,Entradas!B:B,CONCATENATE("<=",$G$2))-SUMIFS(Saidas!C:C,Saidas!A:A,'Cadastro-Estoque'!A:A,Saidas!B:B,CONCATENATE("<=",$G$2)))+F74 -> 732 | H74: =IF(ISBLANK($G$2),SUMIFS(Entradas!E:E,Entradas!A:A,'Cadastro-Estoque'!A:A),SUMIFS(Entradas!E:E,Entradas!A:A,'Cadastro-Estoque'!A:A,Entradas!B:B,CONCATENATE("<=",$G$2)))/IF(IF(ISBLANK($G$2),SUMIFS(Entradas!C:C,Entradas!A:A,'Cadastro-Estoque'!A:A),SUMIFS(Entradas!C:C,Entradas!A:A,'Cadastro-Estoque'!A:A,Entradas!B:B,CONCATENATE("<=",$G$2)))=0,1,IF(ISBLANK($G$2),SUMIFS(Entradas!C:C,Entradas!A:A,'Cadastro-Estoque'!A:A),SUMIFS(Entradas!C:C,Entradas!A:A,'Cadastro-Estoque'!A:A,Entradas!B:B,CONCATENATE("<=",$G$2)))) -> 0 | I74: =IF(ISBLANK($G$2),SUMIFS(Saidas!E:E,Saidas!A:A,'Cadastro-Estoque'!A:A),SUMIFS(Saidas!E:E,Saidas!A:A,'Cadastro-Estoque'!A:A,Saidas!B:B,CONCATENATE("<=",$G$2)))/IF(IF(ISBLANK($G$2),SUMIFS(Saidas!C:C,Saidas!A:A,'Cadastro-Estoque'!A:A),SUMIFS(Saidas!C:C,Saidas!A:A,'Cadastro-Estoque'!A:A,Saidas!B:B,CONCATENATE("<=",$G$2)))=0,1,IF(ISBLANK($G$2),SUMIFS(Saidas!C:C,Saidas!A:A,'Cadastro-Estoque'!A:A),SUMIFS(Saidas!C:C,Saidas!A:A,'Cadastro-Estoque'!A:A,Saidas!B:B,CONCATENATE("<=",$G$2)))) -> 0 | K74: =#REF! -> #REF!
A75: 024-20X500 | B75: CANJICA XERÉM 20 X 500 | C75: FARDOS | D75: ADRAM | F75: 391 | G75: =IF(ISBLANK($G$2),SUMIFS(Entradas!C:C,Entradas!A:A,'Cadastro-Estoque'!A:A)-SUMIFS(Saidas!C:C,Saidas!A:A,'Cadastro-Estoque'!A:A),SUMIFS(Entradas!C:C,Entradas!A:A,'Cadastro-Estoque'!A:A,Entradas!B:B,CONCATENATE("<=",$G$2))-SUMIFS(Saidas!C:C,Saidas!A:A,'Cadastro-Estoque'!A:A,Saidas!B:B,CONCATENATE("<=",$G$2)))+F75 -> 391 | H75: =IF(ISBLANK($G$2),SUMIFS(Entradas!E:E,Entradas!A:A,'Cadastro-Estoque'!A:A),SUMIFS(Entradas!E:E,Entradas!A:A,'Cadastro-Estoque'!A:A,Entradas!B:B,CONCATENATE("<=",$G$2)))/IF(IF(ISBLANK($G$2),SUMIFS(Entradas!C:C,Entradas!A:A,'Cadastro-Estoque'!A:A),SUMIFS(Entradas!C:C,Entradas!A:A,'Cadastro-Estoque'!A:A,Entradas!B:B,CONCATENATE("<=",$G$2)))=0,1,IF(ISBLANK($G$2),SUMIFS(Entradas!C:C,Entradas!A:A,'Cadastro-Estoque'!A:A),SUMIFS(Entradas!C:C,Entradas!A:A,'Cadastro-Estoque'!A:A,Entradas!B:B,CONCATENATE("<=",$G$2)))) -> 0 | I75: =IF(ISBLANK($G$2),SUMIFS(Saidas!E:E,Saidas!A:A,'Cadastro-Estoque'!A:A),SUMIFS(Saidas!E:E,Saidas!A:A,'Cadastro-Estoque'!A:A,Saidas!B:B,CONCATENATE("<=",$G$2)))/IF(IF(ISBLANK($G$2),SUMIFS(Saidas!C:C,Saidas!A:A,'Cadastro-Estoque'!A:A),SUMIFS(Saidas!C:C,Saidas!A:A,'Cadastro-Estoque'!A:A,Saidas!B:B,CONCATENATE("<=",$G$2)))=0,1,IF(ISBLANK($G$2),SUMIFS(Saidas!C:C,Saidas!A:A,'Cadastro-Estoque'!A:A),SUMIFS(Saidas!C:C,Saidas!A:A,'Cadastro-Estoque'!A:A,Saidas!B:B,CONCATENATE("<=",$G$2)))) -> 0 | K75: =#REF! -> #REF!
A76: 051-20X500 | B76: PIPOCA NUTRIVITA 20 X 500 | C76: FARDOS | D76: ADRAM | F76: 0 | G76: =IF(ISBLANK($G$2),SUMIFS(Entradas!C:C,Entradas!A:A,'Cadastro-Estoque'!A:A)-SUMIFS(Saidas!C:C,Saidas!A:A,'Cadastro-Estoque'!A:A),SUMIFS(Entradas!C:C,Entradas!A:A,'Cadastro-Estoque'!A:A,Entradas!B:B,CONCATENATE("<=",$G$2))-SUMIFS(Saidas!C:C,Saidas!A:A,'Cadastro-Estoque'!A:A,Saidas!B:B,CONCATENATE("<=",$G$2)))+F76 -> 0 | H76: =IF(ISBLANK($G$2),SUMIFS(Entradas!E:E,Entradas!A:A,'Cadastro-Estoque'!A:A),SUMIFS(Entradas!E:E,Entradas!A:A,'Cadastro-Estoque'!A:A,Entradas!B:B,CONCATENATE("<=",$G$2)))/IF(IF(ISBLANK($G$2),SUMIFS(Entradas!C:C,Entradas!A:A,'Cadastro-Estoque'!A:A),SUMIFS(Entradas!C:C,Entradas!A:A,'Cadastro-Estoque'!A:A,Entradas!B:B,CONCATENATE("<=",$G$2)))=0,1,IF(ISBLANK($G$2),SUMIFS(Entradas!C:C,Entradas!A:A,'Cadastro-Estoque'!A:A),SUMIFS(Entradas!C:C,Entradas!A:A,'Cadastro-Estoque'!A:A,Entradas!B:B,CONCATENATE("<=",$G$2)))) -> 0 | I76: =IF(ISBLANK($G$2),SUMIFS(Saidas!E:E,Saidas!A:A,'Cadastro-Estoque'!A:A),SUMIFS(Saidas!E:E,Saidas!A:A,'Cadastro-Estoque'!A:A,Saidas!B:B,CONCATENATE("<=",$G$2)))/IF(IF(ISBLANK($G$2),SUMIFS(Saidas!C:C,Saidas!A:A,'Cadastro-Estoque'!A:A),SUMIFS(Saidas!C:C,Saidas!A:A,'Cadastro-Estoque'!A:A,Saidas!B:B,CONCATENATE("<=",$G$2)))=0,1,IF(ISBLANK($G$2),SUMIFS(Saidas!C:C,Saidas!A:A,'Cadastro-Estoque'!A:A),SUMIFS(Saidas!C:C,Saidas!A:A,'Cadastro-Estoque'!A:A,Saidas!B:B,CONCATENATE("<=",$G$2)))) -> 0 | K76: =#REF! -> #REF!
